Workbook

Sheet Raw Data
A1: Exported from Tally | I1: Dala Sales & Deliveries | R1: External Deliveries | Z1: Forwarding From Client | AH1: Client Restock | AP1: Dala Restock | AX1: Unique Locations
A3: item name | B3: Date | C3: Particulars | D3: Vch Type | E3: Vch No. | F3: Quantity | G3: Value | I3: item name | J3: Date | K3: Particulars | L3: Vch Type | M3: Vch No. | N3: Quantity | O3: Value | P3: Total Value | R3: item name | S3: Date | T3: Particulars | U3: Vch Type | V3: Vch No. | W3: Quantity | X3: Value | Z3: item name | AA3: Date | AB3: Particulars | AC3: Vch Type | AD3: Vch No. | AE3: Quantity | AF3: Value | AH3: item name | AI3: Date | AJ3: Particulars | AK3: Vch Type | AL3: Vch No. | AM3: Quantity | AN3: Value | AP3: item name | AQ3: Date | AR3: Particulars | AS3: Vch Type | AT3: Vch No. | AU3: Quantity | AV3: Value | AX3: {=counta(unique(C:C))-3} -> 72
A4: 1 ltr High Protien Sweetend Greek Yoghurt (6x) | B4: 45839 | C4: Zayith Food Company | D4: Purchase Inv-Dala | E4: 2066 | F4: 2 | G4: 84482.68 | I4: 250ml Strawberry Yoghurt (12x) | J4: 45839 | K4: Greenell Supermarket, Osapa | L4: Sales | M4: DT:001673 | N4: 2 | O4: 37122.1 | P4: =sumif(M:M,M4,O:O) -> 202050.2 | AP4: 1 ltr High Protien Sweetend Greek Yoghurt (6x) | AQ4: 45839 | AR4: Zayith Food Company | AS4: Purchase Inv-Dala | AT4: 2066 | AU4: 2 | AV4: 84482.68
A5: 1 ltr High Protien Unsweetend Greek Yoghurt (6x) | B5: 45839 | C5: Zayith Food Company | D5: Purchase Inv-Dala | E5: 2066 | F5: 2 | G5: 84482.68 | I5: 250ml Vanilla Yoghurt (12x) | J5: 45839 | K5: Greenell Supermarket, Osapa | L5: Sales | M5: DT:001673 | N5: 1 | O5: 18561.05 | P5: =sumif(M:M,M5,O:O) -> 202050.2 | AP5: 1 ltr High Protien Unsweetend Greek Yoghurt (6x) | AQ5: 45839 | AR5: Zayith Food Company | AS5: Purchase Inv-Dala | AT5: 2066 | AU5: 2 | AV5: 84482.68
A6: 1 ltr Low Fat Sweetend Greek Yoghurt (6x) | B6: 45839 | C6: Zayith Food Company | D6: Purchase Inv-Dala | E6: 2066 | F6: 2 | G6: 72211.82 | I6: 500ml High Protien Sweetend Greek Yoghurt (12x) | J6: 45839 | K6: Greenell Supermarket, Osapa | L6: Sales | M6: DT:001673 | N6: 1 | O6: 45657.74 | P6: =sumif(M:M,M6,O:O) -> 202050.2 | AP6: 1 ltr Low Fat Sweetend Greek Yoghurt (6x) | AQ6: 45839 | AR6: Zayith Food Company | AS6: Purchase Inv-Dala | AT6: 2066 | AU6: 2 | AV6: 72211.82
A7: 1 ltr Low Fat Unsweetend Greek Yoghurt (6x) | B7: 45839 | C7: Zayith Food Company | D7: Purchase Inv-Dala | E7: 2066 | F7: 2 | G7: 72211.82 | I7: 500ml Low Fat Sweetend Greek Yoghurt (12x) | J7: 45839 | K7: Greenell Supermarket, Osapa | L7: Sales | M7: DT:001673 | N7: 1 | O7: 40037.11 | P7: =sumif(M:M,M7,O:O) -> 202050.2 | AP7: 1 ltr Low Fat Unsweetend Greek Yoghurt (6x) | AQ7: 45839 | AR7: Zayith Food Company | AS7: Purchase Inv-Dala | AT7: 2066 | AU7: 2 | AV7: 72211.82
A8: 250ml Vanilla Yoghurt (12x) | B8: 45839 | C8: Zayith Food Company | D8: Purchase Inv-Dala | E8: 2066 | F8: 5 | G8: 92805.25 | I8: 500ml Strawberry Yoghurt (12x) | J8: 45839 | K8: Greenell Supermarket, Osapa | L8: Sales | M8: DT:001673 | N8: 2 | O8: 60672.2 | P8: =sumif(M:M,M8,O:O) -> 202050.2 | AP8: 250ml Vanilla Yoghurt (12x) | AQ8: 45839 | AR8: Zayith Food Company | AS8: Purchase Inv-Dala | AT8: 2066 | AU8: 5 | AV8: 92805.25
A9: 500ml Low Fat Sweetend Greek Yoghurt (12x) | B9: 45839 | C9: Zayith Food Company | D9: Purchase Inv-Dala | E9: 2066 | F9: 5 | G9: 200185.55 | I9: 500ml High Protien Sweetend Greek Yoghurt (12x) | J9: 45839 | K9: Prince Ebeano, ONIRU | L9: Sales | M9: DT:001676 | N9: 1 | O9: 45657.74 | P9: =sumif(M:M,M9,O:O) -> 116030.95 | AP9: 500ml Low Fat Sweetend Greek Yoghurt (12x) | AQ9: 45839 | AR9: Zayith Food Company | AS9: Purchase Inv-Dala | AT9: 2066 | AU9: 5 | AV9: 200185.55
A10: 500ml Low Fat Unsweetend Greek Yoghurt (12x) | B10: 45839 | C10: Zayith Food Company | D10: Purchase Inv-Dala | E10: 2066 | F10: 5 | G10: 200185.55 | I10: 500ml Low Fat Sweetend Greek Yoghurt (12x) | J10: 45839 | K10: Prince Ebeano, ONIRU | L10: Sales | M10: DT:001676 | N10: 1 | O10: 40037.11 | P10: =sumif(M:M,M10,O:O) -> 116030.95 | AP10: 500ml Low Fat Unsweetend Greek Yoghurt (12x) | AQ10: 45839 | AR10: Zayith Food Company | AS10: Purchase Inv-Dala | AT10: 2066 | AU10: 5 | AV10: 200185.55
A11: 1 ltr High Protien Sweetend Greek Yoghurt (6x) | B11: 45846 | C11: Zayith Food Company | D11: Purchase Inv-Dala | E11: 2071 | F11: 2 | G11: 84482.68 | I11: 500ml Strawberry Yoghurt (12x) | J11: 45839 | K11: Prince Ebeano, ONIRU | L11: Sales | M11: DT:001676 | N11: 1 | O11: 30336.1 | P11: =sumif(M:M,M11,O:O) -> 116030.95 | AP11: 1 ltr High Protien Sweetend Greek Yoghurt (6x) | AQ11: 45846 | AR11: Zayith Food Company | AS11: Purchase Inv-Dala | AT11: 2071 | AU11: 2 | AV11: 84482.68
A12: 1 ltr High Protien Unsweetend Greek Yoghurt (6x) | B12: 45846 | C12: Zayith Food Company | D12: Purchase Inv-Dala | E12: 2071 | F12: 2 | G12: 84482.68 | I12: 500ml Strawberry Yoghurt (12x) | J12: 45839 | K12: Rance Supermarket, Sangotedo | L12: Sales | M12: DT:001670 | N12: 0.5 | O12: 15168.05 | P12: =sumif(M:M,M12,O:O) -> 15168.05 | AP12: 1 ltr High Protien Unsweetend Greek Yoghurt (6x) | AQ12: 45846 | AR12: Zayith Food Company | AS12: Purchase Inv-Dala | AT12: 2071 | AU12: 2 | AV12: 84482.68
A13: 1 ltr Low Fat Sweetend Greek Yoghurt (6x) | B13: 45846 | C13: Zayith Food Company | D13: Purchase Inv-Dala | E13: 2071 | F13: 2 | G13: 72211.82 | I13: 250ml Vanilla Yoghurt (12x) | J13: 45840 | K13: Better Mart Supermartket, Ajah | L13: Sales | M13: DT:001689 | N13: 1 | O13: 19954 | P13: =sumif(M:M,M13,O:O) -> 35122.05 | AP13: 1 ltr Low Fat Sweetend Greek Yoghurt (6x) | AQ13: 45846 | AR13: Zayith Food Company | AS13: Purchase Inv-Dala | AT13: 2071 | AU13: 2 | AV13: 72211.82
A14: 1 ltr Low Fat Unsweetend Greek Yoghurt (6x) | B14: 45846 | C14: Zayith Food Company | D14: Purchase Inv-Dala | E14: 2071 | F14: 2 | G14: 72211.82 | I14: 500ml Strawberry Yoghurt (12x) | J14: 45840 | K14: Better Mart Supermartket, Ajah | L14: Sales | M14: DT:001689 | N14: 0.5 | O14: 15168.05 | P14: =sumif(M:M,M14,O:O) -> 35122.05 | AP14: 1 ltr Low Fat Unsweetend Greek Yoghurt (6x) | AQ14: 45846 | AR14: Zayith Food Company | AS14: Purchase Inv-Dala | AT14: 2071 | AU14: 2 | AV14: 72211.82
A15: 250ml Strawberry Yoghurt (12x) | B15: 45846 | C15: Zayith Food Company | D15: Purchase Inv-Dala | E15: 2071 | F15: 10 | G15: 185610.5 | I15: 500ml High Protien Sweetend Greek Yoghurt (12x) | J15: 45840 | K15: Buymore Supermarket, ABULEGBA | L15: Sales | M15: DT:001691 | N15: 1 | O15: 45657.74 | P15: =sumif(M:M,M15,O:O) -> 60825.79 | AP15: 250ml Strawberry Yoghurt (12x) | AQ15: 45846 | AR15: Zayith Food Company | AS15: Purchase Inv-Dala | AT15: 2071 | AU15: 10 | AV15: 185610.5
... A53: 500ml Strawberry Yoghurt (12x) | B53: 45867 | C53: Zayith Food Company | D53: Purchase Inv-Dala | E53: 2088 | F53: 10 | G53: 303361 | I53: 1 ltr High Protien Sweetend Greek Yoghurt (6x) | J53: 45841 | K53: Mitch & Good Supermarket | L53: Sales | M53: DT:001707 | N53: 1 | O53: 42241.34 | P53: =sumif(M:M,M53,O:O) -> 383160.25 | AP53: 500ml Strawberry Yoghurt (12x) | AQ53: 45867 | AR53: Zayith Food Company | AS53: Purchase Inv-Dala | AT53: 2088 | AU53: 10 | AV53: 303361
A54: 250ml Strawberry Yoghurt (12x) | B54: 45839 | C54: Greenell Supermarket, Osapa | D54: Sales | E54: DT:001673 | F54: 2 | G54: 37122.1 | I54: 1 ltr High Protien Unsweetend Greek Yoghurt (6x) | J54: 45841 | K54: Mitch & Good Supermarket | L54: Sales | M54: DT:001707 | N54: 1 | O54: 42241.34 | P54: =sumif(M:M,M54,O:O) -> 383160.25
A55: 250ml Vanilla Yoghurt (12x) | B55: 45839 | C55: Greenell Supermarket, Osapa | D55: Sales | E55: DT:001673 | F55: 1 | G55: 18561.05 | I55: 1 ltr Low Fat Sweetend Greek Yoghurt (6x) | J55: 45841 | K55: Mitch & Good Supermarket | L55: Sales | M55: DT:001707 | N55: 1 | O55: 36105.91 | P55: =sumif(M:M,M55,O:O) -> 383160.25
A56: 500ml High Protien Sweetend Greek Yoghurt (12x) | B56: 45839 | C56: Greenell Supermarket, Osapa | D56: Sales | E56: DT:001673 | F56: 1 | G56: 45657.74 | I56: 1 ltr Low Fat Unsweetend Greek Yoghurt (6x) | J56: 45841 | K56: Mitch & Good Supermarket | L56: Sales | M56: DT:001707 | N56: 1 | O56: 36105.91 | P56: =sumif(M:M,M56,O:O) -> 383160.25
A57: 500ml Low Fat Sweetend Greek Yoghurt (12x) | B57: 45839 | C57: Greenell Supermarket, Osapa | D57: Sales | E57: DT:001673 | F57: 1 | G57: 40037.11 | I57: 250ml Strawberry Yoghurt (12x) | J57: 45841 | K57: Mitch & Good Supermarket | L57: Sales | M57: DT:001707 | N57: 1 | O57: 19954 | P57: =sumif(M:M,M57,O:O) -> 383160.25
A58: 500ml Strawberry Yoghurt (12x) | B58: 45839 | C58: Greenell Supermarket, Osapa | D58: Sales | E58: DT:001673 | F58: 2 | G58: 60672.2 | I58: 250ml Vanilla Yoghurt (12x) | J58: 45841 | K58: Mitch & Good Supermarket | L58: Sales | M58: DT:001707 | N58: 1 | O58: 19954 | P58: =sumif(M:M,M58,O:O) -> 383160.25
A59: 500ml High Protien Sweetend Greek Yoghurt (12x) | B59: 45839 | C59: Prince Ebeano, ONIRU | D59: Sales | E59: DT:001676 | F59: 1 | G59: 45657.74 | I59: 500ml High Protien Sweetend Greek Yoghurt (12x) | J59: 45841 | K59: Mitch & Good Supermarket | L59: Sales | M59: DT:001707 | N59: 1 | O59: 45657.74 | P59: =sumif(M:M,M59,O:O) -> 383160.25
A60: 500ml Low Fat Sweetend Greek Yoghurt (12x) | B60: 45839 | C60: Prince Ebeano, ONIRU | D60: Sales | E60: DT:001676 | F60: 1 | G60: 40037.11 | I60: 500ml High Protien Unsweetend Greek Yoghurt (12x) | J60: 45841 | K60: Mitch & Good Supermarket | L60: Sales | M60: DT:001707 | N60: 1 | O60: 45657.74 | P60: =sumif(M:M,M60,O:O) -> 383160.25
A61: 500ml Strawberry Yoghurt (12x) | B61: 45839 | C61: Prince Ebeano, ONIRU | D61: Sales | E61: DT:001676 | F61: 1 | G61: 30336.1 | I61: 500ml Low Fat Sweetend Greek Yoghurt (12x) | J61: 45841 | K61: Mitch & Good Supermarket | L61: Sales | M61: DT:001707 | N61: 1 | O61: 40037.11 | P61: =sumif(M:M,M61,O:O) -> 383160.25
A62: 500ml Strawberry Yoghurt (12x) | B62: 45839 | C62: Rance Supermarket, Sangotedo | D62: Sales | E62: DT:001670 | F62: 0.5 | G62: 15168.05 | I62: 500ml Low Fat Unsweetend Greek Yoghurt (12x) | J62: 45841 | K62: Mitch & Good Supermarket | L62: Sales | M62: DT:001707 | N62: 1 | O62: 40037.11 | P62: =sumif(M:M,M62,O:O) -> 383160.25
A63: 250ml Vanilla Yoghurt (12x) | B63: 45840 | C63: Better Mart Supermartket, Ajah | D63: Sales | E63: DT:001689 | F63: 1 | G63: 19954 | I63: 500ml Strawberry Yoghurt (12x) | J63: 45841 | K63: Mitch & Good Supermarket | L63: Sales | M63: DT:001707 | N63: 0.5 | O63: 15168.05 | P63: =sumif(M:M,M63,O:O) -> 383160.25
A64: 500ml Strawberry Yoghurt (12x) | B64: 45840 | C64: Better Mart Supermartket, Ajah | D64: Sales | E64: DT:001689 | F64: 0.5 | G64: 15168.05 | I64: 500ml Low Fat Sweetend Greek Yoghurt (12x) | J64: 45842 | K64: Compramart Supermarket, ORCHID Rd. | L64: Sales | M64: DT:001731 | N64: 0.5 | O64: 20018.56 | P64: =sumif(M:M,M64,O:O) -> 20018.56
A65: 500ml High Protien Sweetend Greek Yoghurt (12x) | B65: 45840 | C65: Buymore Supermarket, ABULEGBA | D65: Sales | E65: DT:001691 | F65: 1 | G65: 45657.74 | I65: 250ml Strawberry Yoghurt (12x) | J65: 45842 | K65: Excel Plus Supermarket, Orchid Rd. | L65: Sales | M65: DT:001739 | N65: 1 | O65: 18561.05 | P65: =sumif(M:M,M65,O:O) -> 181415.11
... A378: 500ml Vanilla Yoghurt (12x) | B378: 45866 | C378: Pennymart Express, PALACEWAY OKOTA | D378: Sales | E378: DT:001955 | F378: 1 | G378: 30336.1 | I378: 500ml Vanilla Yoghurt (12x) | J378: 45869 | K378: Sundry Market Square, FESTAC | L378: Sales | M378: DT:001999 | N378: 0.5 | O378: 15168.05 | P378: =sumif(M:M,M378,O:O) -> 162700.47
A379: 500ml Vanilla Yoghurt (12x) | B379: 45866 | C379: Katta Supermarket | D379: Sales | E379: DT:001958 | F379: 1 | G379: 30226.1 | P379: =sumif(M:M,M379,O:O) -> 0
A380: 500ml Vanilla Yoghurt (12x) | B380: 45866 | C380: Life Back Pharmacy & stores | D380: Sales | E380: DT:001961 | F380: 1 | G380: 30336.1 | P380: =sumif(M:M,M380,O:O) -> 0
A381: 1 ltr High Protien Sweetend Greek Yoghurt (6x) | B381: 45867 | C381: De Royal Prince, GBAGADA | D381: Sales | E381: DT:001966 | F381: 2 | G381: 84482.68 | P381: =sumif(M:M,M381,O:O) -> 0
A382: 1 ltr Low Fat Sweetend Greek Yoghurt (6x) | B382: 45867 | C382: De Royal Prince, GBAGADA | D382: Sales | E382: DT:001966 | F382: 2 | G382: 72211.82 | P382: =sumif(M:M,M382,O:O) -> 0
A383: 1 ltr Low Fat Unsweetend Greek Yoghurt (6x) | B383: 45867 | C383: De Royal Prince, GBAGADA | D383: Sales | E383: DT:001966 | F383: 1 | G383: 36105.91 | P383: =sumif(M:M,M383,O:O) -> 0
A384: 500ml High Protien Sweetend Greek Yoghurt (12x) | B384: 45867 | C384: De Royal Prince, GBAGADA | D384: Sales | E384: DT:001966 | F384: 1 | G384: 45657.74 | P384: =sumif(M:M,M384,O:O) -> 0
A385: 500ml High Protien Sweetend Greek Yoghurt (12x) | B385: 45867 | C385: Prime Mart Superstores, CEMENT | D385: Sales | E385: DT:001971 | F385: 0.5 | G385: 22828.87 | P385: =sumif(M:M,M385,O:O) -> 0
A386: 500ml High Protien Unsweetend Greek Yoghurt (12x) | B386: 45867 | C386: Prime Mart Superstores, CEMENT | D386: Sales | E386: DT:001971 | F386: 0.5 | G386: 22828.87 | P386: =sumif(M:M,M386,O:O) -> 0
A387: 500ml Strawberry Yoghurt (12x) | B387: 45867 | C387: De Royal Prince, GBAGADA | D387: Sales | E387: DT:001966 | F387: 2 | G387: 60672.02 | P387: =sumif(M:M,M387,O:O) -> 0
A388: 500ml Strawberry Yoghurt (12x) | B388: 45867 | C388: Prime Mart Superstores, CEMENT | D388: Sales | E388: DT:001971 | F388: 0.5 | G388: 16305.66 | P388: =sumif(M:M,M388,O:O) -> 0
A389: 500ml Vanilla Yoghurt (12x) | B389: 45867 | C389: De Royal Prince, GBAGADA | D389: Sales | E389: DT:001966 | F389: 2 | G389: 60672.2 | P389: =sumif(M:M,M389,O:O) -> 0
A390: 500ml Vanilla Yoghurt (12x) | B390: 45867 | C390: Prime Mart Superstores, CEMENT | D390: Sales | E390: DT:001971 | F390: 0.5 | G390: 16305.66 | P390: =sumif(M:M,M390,O:O) -> 0
... A428: 500ml Vanilla Yoghurt (12x) | B428: 45869 | C428: Sundry Market Square, FESTAC | D428: Sales | E428: DT:001999 | F428: 0.5 | G428: 15168.05 | P428: =sumif(M:M,M428,O:O) -> 0
P429: =sumif(M:M,M429,O:O) -> 0
P430: =sumif(M:M,M430,O:O) -> 0
P431: =sumif(M:M,M431,O:O) -> 0
P432: =sumif(M:M,M432,O:O) -> 0
P433: =sumif(M:M,M433,O:O) -> 0
P434: =sumif(M:M,M434,O:O) -> 0
P435: =sumif(M:M,M435,O:O) -> 0
P436: =sumif(M:M,M436,O:O) -> 0
P437: =sumif(M:M,M437,O:O) -> 0
P438: =sumif(M:M,M438,O:O) -> 0
P439: =sumif(M:M,M439,O:O) -> 0
P440: =sumif(M:M,M440,O:O) -> 0
... P518: =sumif(M:M,M518,O:O) -> 0
P519: =sumif(K:K,K519,O:O) -> 0
P520: =sumif(K:K,K520,O:O) -> 0
P521: =sumif(K:K,K521,O:O) -> 0
P522: =sumif(K:K,K522,O:O) -> 0
P523: =sumif(K:K,K523,O:O) -> 0
P524: =sumif(K:K,K524,O:O) -> 0
P525: =sumif(K:K,K525,O:O) -> 0
P526: =sumif(K:K,K526,O:O) -> 0
P527: =sumif(K:K,K527,O:O) -> 0
P528: =sumif(K:K,K528,O:O) -> 0
P529: =sumif(K:K,K529,O:O) -> 0
P530: =sumif(K:K,K530,O:O) -> 0
... P1003: =sumif(K:K,K1003,O:O) -> 0

Sheet Payment Advice

Sheet Dala Sales & Deliveries
H1: Total Invoices Delivered | I1: =countifs(B:B,"<>",F:F,"<>")-1 -> 123 | K1: Sku Performance | L1: Units | M1: Value
H2: Unique Locations Supplied | I2: {=(COUNTA(UNIQUE(C:C))-1)} -> 73 | K2: ='Internal Summary'!B39 -> 1 ltr High Protien Sweetend Greek Yoghurt (6x) | L2: =sumif(D:D,K2,E:E) -> 13 | M2: =sumif(D:D,K2,F:F) -> 549137.42
H3: Total Value of orders | I3: =sum(F:F) -> 12906500 | K3: ='Internal Summary'!B40 -> 1 ltr High Protien Unsweetend Greek Yoghurt (6x) | L3: =sumif(D:D,K3,E:E) -> 8 | M3: =sumif(D:D,K3,F:F) -> 337930.72
K4: ='Internal Summary'!B41 -> 1 ltr Low Fat Sweetend Greek Yoghurt (6x) | L4: =sumif(D:D,K4,E:E) -> 15.5 | M4: =sumif(D:D,K4,F:F) -> 559641.62
K5: ='Internal Summary'!B42 -> 1 ltr Low Fat Unsweetend Greek Yoghurt (6x) | L5: =sumif(D:D,K5,E:E) -> 13.5 | M5: =sumif(D:D,K5,F:F) -> 487429.8
K6: ='Internal Summary'!B43 -> 250ml Strawberry Yoghurt (12x) | L6: =sumif(D:D,K6,E:E) -> 35.5 | M6: =sumif(D:D,K6,F:F) -> 665882.04
K7: ='Internal Summary'!B44 -> 250ml Vanilla Yoghurt (12x) | L7: =sumif(D:D,K7,E:E) -> 41.5 | M7: =sumif(D:D,K7,F:F) -> 780034.23
K8: ='Internal Summary'!B45 -> 500ml High Protien Sweetend Greek Yoghurt (12x) | L8: =sumif(D:D,K8,E:E) -> 56.5 | M8: =sumif(D:D,K8,F:F) -> 2583086.6
K9: ='Internal Summary'!B46 -> 500ml High Protien Unsweetend Greek Yoghurt (12x) | L9: =sumif(D:D,K9,E:E) -> 33 | M9: =sumif(D:D,K9,F:F) -> 1510129.7
K10: ='Internal Summary'!B47 -> 500ml Low Fat Sweetend Greek Yoghurt (12x) | L10: =sumif(D:D,K10,E:E) -> 43 | M10: =sumif(D:D,K10,F:F) -> 1721595.8
K11: ='Internal Summary'!B48 -> 500ml Low Fat Unsweetend Greek Yoghurt (12x) | L11: =sumif(D:D,K11,E:E) -> 28.5 | M11: =sumif(D:D,K11,F:F) -> 1136207.2
A12: 45794 | K12: ='Internal Summary'!B49 -> 500ml Strawberry Yoghurt (12x) | L12: =sumif(D:D,K12,E:E) -> 44 | M12: =sumif(D:D,K12,F:F) -> 1346164.3
K13: ='Internal Summary'!B50 -> 500ml Vanilla Yoghurt (12x) | L13: =sumif(D:D,K13,E:E) -> 40 | M13: =sumif(D:D,K13,F:F) -> 1229260.5
K14: ='Internal Summary'!B51 | L14: =sumif(D:D,K14,E:E) -> 0 | M14: =sumif(D:D,K14,F:F) -> 0
K15: ='Internal Summary'!B52 | L15: =sumif(D:D,K15,E:E) -> 0 | M15: =sumif(D:D,K15,F:F) -> 0
K18: ='Internal Summary'!B55 | L18: =sumif(D:D,K18,E:E) -> 0 | M18: =sumif(D:D,K18,F:F) -> 0
K21: ='Internal Summary'!B58 | L21: =sumif(D:D,K21,E:E) -> 0 | M21: =sumif(D:D,K21,F:F) -> 0
K24: ='Internal Summary'!B61 | L24: =sumif(D:D,K24,E:E) -> 0 | M24: =sumif(D:D,K24,F:F) -> 0
K27: ='Internal Summary'!B64 | L27: =sumif(D:D,K27,E:E) -> 0 | M27: =sumif(D:D,K27,F:F) -> 0
K30: ='Internal Summary'!B67 | L30: =sumif(D:D,K30,E:E) -> 0 | M30: =sumif(D:D,K30,F:F) -> 0
K33: ='Internal Summary'!B70 | L33: =sumif(D:D,K33,E:E) -> 0 | M33: =sumif(D:D,K33,F:F) -> 0
K36: ='Internal Summary'!B73 | L36: =sumif(D:D,K36,E:E) -> 0 | M36: =sumif(D:D,K36,F:F) -> 0
K39: ='Internal Summary'!B76 | L39: =sumif(D:D,K39,E:E) -> 0 | M39: =sumif(D:D,K39,F:F) -> 0
K42: ='Internal Summary'!B79 | L42: =sumif(D:D,K42,E:E) -> 0 | M42: =sumif(D:D,K42,F:F) -> 0
... K51: ='Internal Summary'!B88 | L51: =sumif(D:D,K51,E:E) -> 0 | M51: =sumif(D:D,K51,F:F) -> 0

Sheet External Delivery Fulfillment
H1: Total Invoices Delivered | I1: =countifs(B:B,"<>",F:F,"<>")-1 -> 0 | K1: Sku Performance | L1: Units | M1: Value
H2: Unique Locations Supplied | I2: {=(COUNTA(UNIQUE(C:C))-1)} -> 0 | K2: ='Internal Summary'!B39 -> 1 ltr High Protien Sweetend Greek Yoghurt (6x) | L2: =sumif(D:D,K2,E:E) -> 0 | M2: =sumif(D:D,K2,F:F) -> 0
H3: Total Value of orders | I3: =sum(F:F) -> 0 | K3: ='Internal Summary'!B40 -> 1 ltr High Protien Unsweetend Greek Yoghurt (6x) | L3: =sumif(D:D,K3,E:E) -> 0 | M3: =sumif(D:D,K3,F:F) -> 0
K4: ='Internal Summary'!B41 -> 1 ltr Low Fat Sweetend Greek Yoghurt (6x) | L4: =sumif(D:D,K4,E:E) -> 0 | M4: =sumif(D:D,K4,F:F) -> 0
K5: ='Internal Summary'!B42 -> 1 ltr Low Fat Unsweetend Greek Yoghurt (6x) | L5: =sumif(D:D,K5,E:E) -> 0 | M5: =sumif(D:D,K5,F:F) -> 0
K6: ='Internal Summary'!B43 -> 250ml Strawberry Yoghurt (12x) | L6: =sumif(D:D,K6,E:E) -> 0 | M6: =sumif(D:D,K6,F:F) -> 0
K7: ='Internal Summary'!B44 -> 250ml Vanilla Yoghurt (12x) | L7: =sumif(D:D,K7,E:E) -> 0 | M7: =sumif(D:D,K7,F:F) -> 0
K8: ='Internal Summary'!B45 -> 500ml High Protien Sweetend Greek Yoghurt (12x) | L8: =sumif(D:D,K8,E:E) -> 0 | M8: =sumif(D:D,K8,F:F) -> 0
K9: ='Internal Summary'!B46 -> 500ml High Protien Unsweetend Greek Yoghurt (12x) | L9: =sumif(D:D,K9,E:E) -> 0 | M9: =sumif(D:D,K9,F:F) -> 0
K10: ='Internal Summary'!B47 -> 500ml Low Fat Sweetend Greek Yoghurt (12x) | L10: =sumif(D:D,K10,E:E) -> 0 | M10: =sumif(D:D,K10,F:F) -> 0
K11: ='Internal Summary'!B48 -> 500ml Low Fat Unsweetend Greek Yoghurt (12x) | L11: =sumif(D:D,K11,E:E) -> 0 | M11: =sumif(D:D,K11,F:F) -> 0
K12: ='Internal Summary'!B49 -> 500ml Strawberry Yoghurt (12x) | L12: =sumif(D:D,K12,E:E) -> 0 | M12: =sumif(D:D,K12,F:F) -> 0
K13: ='Internal Summary'!B50 -> 500ml Vanilla Yoghurt (12x) | L13: =sumif(D:D,K13,E:E) -> 0 | M13: =sumif(D:D,K13,F:F) -> 0
K14: ='Internal Summary'!B51 | L14: =sumif(D:D,K14,E:E) -> 0 | M14: =sumif(D:D,K14,F:F) -> 0
K15: ='Internal Summary'!B52 | L15: =sumif(D:D,K15,E:E) -> 0 | M15: =sumif(D:D,K15,F:F) -> 0
... K24: ='Internal Summary'!B61 | L24: =sumif(D:D,K24,E:E) -> 0 | M24: =sumif(D:D,K24,F:F) -> 0

Sheet Forwarding From Client
H1: Total Invoices Delivered | I1: =countifs(B:B,"<>",F:F,"<>")-1 -> 0 | K1: Sku Performance | L1: Units | M1: Value
H2: Unique Locations Supplied | I2: {=(COUNTA(UNIQUE(C:C))-1)} -> 0 | K2: ='Internal Summary'!B39 -> 1 ltr High Protien Sweetend Greek Yoghurt (6x) | L2: =sumif(D:D,K2,E:E) -> 0
H3: Total Value of orders | I3: =sum(F:F) -> 0 | K3: ='Internal Summary'!B40 -> 1 ltr High Protien Unsweetend Greek Yoghurt (6x) | L3: =sumif(D:D,K3,E:E) -> 0
K4: ='Internal Summary'!B41 -> 1 ltr Low Fat Sweetend Greek Yoghurt (6x) | L4: =sumif(D:D,K4,E:E) -> 0
K5: ='Internal Summary'!B42 -> 1 ltr Low Fat Unsweetend Greek Yoghurt (6x) | L5: =sumif(D:D,K5,E:E) -> 0
K6: ='Internal Summary'!B43 -> 250ml Strawberry Yoghurt (12x) | L6: =sumif(D:D,K6,E:E) -> 0
K7: ='Internal Summary'!B44 -> 250ml Vanilla Yoghurt (12x) | L7: =sumif(D:D,K7,E:E) -> 0
K8: ='Internal Summary'!B45 -> 500ml High Protien Sweetend Greek Yoghurt (12x) | L8: =sumif(D:D,K8,E:E) -> 0
K9: ='Internal Summary'!B46 -> 500ml High Protien Unsweetend Greek Yoghurt (12x) | L9: =sumif(D:D,K9,E:E) -> 0
K10: ='Internal Summary'!B47 -> 500ml Low Fat Sweetend Greek Yoghurt (12x) | L10: =sumif(D:D,K10,E:E) -> 0
K11: ='Internal Summary'!B48 -> 500ml Low Fat Unsweetend Greek Yoghurt (12x) | L11: =sumif(D:D,K11,E:E) -> 0
K12: ='Internal Summary'!B49 -> 500ml Strawberry Yoghurt (12x) | L12: =sumif(D:D,K12,E:E) -> 0
K13: ='Internal Summary'!B50 -> 500ml Vanilla Yoghurt (12x) | L13: =sumif(D:D,K13,E:E) -> 0
K14: ='Internal Summary'!B51 | L14: =sumif(D:D,K14,E:E) -> 0
K15: ='Internal Summary'!B52 | L15: =sumif(D:D,K15,E:E) -> 0

Sheet Dala Restocking
H1: Total Invoices Delivered | I1: =countifs(B:B,"<>",F:F,"<>")-1 -> 7 | K1: Sku Performance | L1: Units
H2: Unique Locations Supplied | I2: {=(COUNTA(UNIQUE(C:C,,0))-1)} -> 1 | K2: ='Internal Summary'!B39 -> 1 ltr High Protien Sweetend Greek Yoghurt (6x) | L2: =sumif(D:D,K2,E:E) -> 14
H3: Total Value of orders | I3: =sum(F:F) -> 13229532 | K3: ='Internal Summary'!B40 -> 1 ltr High Protien Unsweetend Greek Yoghurt (6x) | L3: =sumif(D:D,K3,E:E) -> 10
K4: ='Internal Summary'!B41 -> 1 ltr Low Fat Sweetend Greek Yoghurt (6x) | L4: =sumif(D:D,K4,E:E) -> 14
K5: ='Internal Summary'!B42 -> 1 ltr Low Fat Unsweetend Greek Yoghurt (6x) | L5: =sumif(D:D,K5,E:E) -> 12
K6: ='Internal Summary'!B43 -> 250ml Strawberry Yoghurt (12x) | L6: =sumif(D:D,K6,E:E) -> 25
K7: ='Internal Summary'!B44 -> 250ml Vanilla Yoghurt (12x) | L7: =sumif(D:D,K7,E:E) -> 40
K8: ='Internal Summary'!B45 -> 500ml High Protien Sweetend Greek Yoghurt (12x) | L8: =sumif(D:D,K8,E:E) -> 55
K9: ='Internal Summary'!B46 -> 500ml High Protien Unsweetend Greek Yoghurt (12x) | L9: =sumif(D:D,K9,E:E) -> 40
K10: ='Internal Summary'!B47 -> 500ml Low Fat Sweetend Greek Yoghurt (12x) | L10: =sumif(D:D,K10,E:E) -> 45
K11: ='Internal Summary'!B48 -> 500ml Low Fat Unsweetend Greek Yoghurt (12x) | L11: =sumif(D:D,K11,E:E) -> 30
K12: ='Internal Summary'!B49 -> 500ml Strawberry Yoghurt (12x) | L12: =sumif(D:D,K12,E:E) -> 50
K13: ='Internal Summary'!B50 -> 500ml Vanilla Yoghurt (12x) | L13: =sumif(D:D,K13,E:E) -> 40
K14: ='Internal Summary'!B51 | L14: =sumif(D:D,K14,E:E) -> 0
K15: ='Internal Summary'!B52 | L15: =sumif(D:D,K15,E:E) -> 0
... K27: ='Internal Summary'!B64 | L27: =sumif(D:D,K27,E:E) -> 0

Sheet Client Restocking
H1: Total Invoices Delivered | I1: =countifs(B:B,"<>",F:F,"<>")-1 -> 0 | K1: Sku Performance | L1: Units
H2: Unique Locations Supplied | I2: {=(COUNTA(UNIQUE(C:C,,0))-1)} -> 0 | K2: ='Internal Summary'!B39 -> 1 ltr High Protien Sweetend Greek Yoghurt (6x) | L2: =sumif(D:D,K2,E:E) -> 0
H3: Total Value of orders | I3: =sum(F:F) -> 0 | K3: ='Internal Summary'!B40 -> 1 ltr High Protien Unsweetend Greek Yoghurt (6x) | L3: =sumif(D:D,K3,E:E) -> 0
K4: ='Internal Summary'!B41 -> 1 ltr Low Fat Sweetend Greek Yoghurt (6x) | L4: =sumif(D:D,K4,E:E) -> 0
K5: ='Internal Summary'!B42 -> 1 ltr Low Fat Unsweetend Greek Yoghurt (6x) | L5: =sumif(D:D,K5,E:E) -> 0
K6: ='Internal Summary'!B43 -> 250ml Strawberry Yoghurt (12x) | L6: =sumif(D:D,K6,E:E) -> 0
K7: ='Internal Summary'!B44 -> 250ml Vanilla Yoghurt (12x) | L7: =sumif(D:D,K7,E:E) -> 0
K8: ='Internal Summary'!B45 -> 500ml High Protien Sweetend Greek Yoghurt (12x) | L8: =sumif(D:D,K8,E:E) -> 0
K9: ='Internal Summary'!B46 -> 500ml High Protien Unsweetend Greek Yoghurt (12x) | L9: =sumif(D:D,K9,E:E) -> 0
K10: ='Internal Summary'!B47 -> 500ml Low Fat Sweetend Greek Yoghurt (12x) | L10: =sumif(D:D,K10,E:E) -> 0
K11: ='Internal Summary'!B48 -> 500ml Low Fat Unsweetend Greek Yoghurt (12x) | L11: =sumif(D:D,K11,E:E) -> 0
K12: ='Internal Summary'!B49 -> 500ml Strawberry Yoghurt (12x) | L12: =sumif(D:D,K12,E:E) -> 0
K13: ='Internal Summary'!B50 -> 500ml Vanilla Yoghurt (12x) | L13: =sumif(D:D,K13,E:E) -> 0
K14: ='Internal Summary'!B51 | L14: =sumif(D:D,K14,E:E) -> 0
K15: ='Internal Summary'!B52 | L15: =sumif(D:D,K15,E:E) -> 0

Sheet Internal Summary
B1: Description | C1: Units | D1: measurements | E1: total
A2: SALES | B2: Total Invoices Delivered | E2: ='Dala Sales & Deliveries'!I1+'External Delivery Fulfillment'!I1 -> 123
B3: Unique Locations Delivered To | E3: ='Raw Data'!AX3 -> 72
B4: Value of Dala Deliveries | E4: ='Dala Sales & Deliveries'!I3 -> 12906500
B5: VAT | E5: =E4*1.075-E4 -> 967987.48
B6: Total Value of Deliveries | E6: =sum(E4:E5) -> 13874487
A7: Remittance & Deductions | B7: Total Remitted to Partner | E7: 0
B8: Collection Fees | C8: 0.05 | E8: =E7*(C8+100%)-E7 -> 0
A9: Invoice Value Due | B9: Outstanding Paymets For Sales | E9: =E6-E7-E8 -> 13874487
A10: Debts | B10: Unpaid Subscription | C10: 1 | D10: 280000 | E10: =C10*D10 -> 280000
B11: Collection Fees | E11: =E9*C8 -> 693724.36
B12: Delivery Fees | D12: Table 1 | E12: =C21+C25 -> 969683.25
B13: Reimbursements Due To DALA | E13: 0
B14: Retailer Deductions (EXPIRY) | E14: =C29 -> 0
B15: Total Deductions | E15: =sum(E10:E14) -> 1943407.6
A16: Remmittance Due | B16: Total Balance to Remitt | E16: =E9-E15+C35 -> 11931080
A19: Inventory and Operational Fees
B20: Dala Pickup for Warehouse | C20: =U68 -> 375
B21: Warehouse Delivery Fee | C21: =V68 -> 240477.06
B22: Forwarding to Retail | C22: =S68 -> 0
B23: Forwarding Delivery Fee | C23: =T68 -> 0
B24: Dala Sales | C24: =67 -> 67
B25: Dala Delivery Fees | C25: =P68 -> 729206.19
B26: Exteranl Deliveries | C26: =Q68 -> 0
B27: External Delivery Fees | C27: =R68 -> 0
B28: Product Defects and Expirey Issues | C28: =F68 -> 0
B29: Deductions From Retailer | C29: 0
B30: Samples used | C30: =I68 -> 0
B31: Produce Replacements | C31: 0
B32: Expected Closing Inventory | C32: =L68 -> 3
B33: Physical Stock count | C33: =K68 -> 67.5
B34: Inventory Shortages | C34: 0
B35: Inventory Shortage Costs | C35: 0
B38: SKUs | C38: Retail Value | D38: Inbound Delivery Fee | E38: Outbound Delivery Fee | F38: Defects/Expirey | G38: Deductions | H38: Opening Inventory | I38: Samples Used | J38: Product Replacements | K38: Physical Closing Stock Count | L38: Expected Closing Inventory | M38: Inventory Shortages | N38: Shortages Costs | O38: Dala Deliveries | P38: Retail Sales Fee | Q38: External Delivery | R38: External Delivery Fee | S38: Forwarding from Client | T38: Forwarding Delivery Fee | U38: Dala Restocking | V38: Dala Restocking Fee | W38: Client Restocking
B39: 1 ltr High Protien Sweetend Greek Yoghurt (6x) | C39: 42241.3 | D39: 718.1021 | E39: 2238.79 | G39: =F39*C39 -> 0 | K39: 1 | L39: =H39+U39+W39-O39-Q39-I39-J39 -> 1 | M39: =K39-L39 -> 0 | N39: =M39*C39 -> 0 | O39: ='Dala Sales & Deliveries'!L2 -> 13 | P39: =O39*E39 -> 29104.27 | Q39: ='External Delivery Fulfillment'!L2 -> 0 | R39: =Q39*E39 -> 0 | S39: ='Forwarding From Client'!L2 -> 0 | T39: =S39*E39 -> 0 | U39: ='Dala Restocking'!L2 -> 14 | V39: =U39*D39 -> 10053.429 | W39: ='Client Restocking'!L2 -> 0
B40: 1 ltr High Protien Unsweetend Greek Yoghurt (6x) | C40: 42241.3 | D40: 718.1021 | E40: 2238.79 | G40: =F40*C40 -> 0 | K40: 1 | L40: =H40+U40+W40-O40-Q40-I40-J40 -> 2 | M40: =K40-L40 -> -1 | N40: =M40*C40 -> -42241.3 | O40: ='Dala Sales & Deliveries'!L3 -> 8 | P40: =O40*E40 -> 17910.32 | Q40: ='External Delivery Fulfillment'!L3 -> 0 | R40: =Q40*E40 -> 0 | S40: ='Forwarding From Client'!L3 -> 0 | T40: =S40*E40 -> 0 | U40: ='Dala Restocking'!L3 -> 10 | V40: =U40*D40 -> 7181.021 | W40: ='Client Restocking'!L3 -> 0
B41: 1 ltr Low Fat Sweetend Greek Yoghurt (6x) | C41: 38813.85 | D41: 659.83545 | E41: 2057.13 | G41: =F41*C41 -> 0 | K41: 0 | L41: =H41+U41+W41-O41-Q41-I41-J41 -> -1.5 | M41: =K41-L41 -> 1.5 | N41: =M41*C41 -> 58220.775 | O41: ='Dala Sales & Deliveries'!L4 -> 15.5 | P41: =O41*E41 -> 31885.515 | Q41: ='External Delivery Fulfillment'!L4 -> 0 | R41: =Q41*E41 -> 0 | S41: ='Forwarding From Client'!L4 -> 0 | T41: =S41*E41 -> 0 | U41: ='Dala Restocking'!L4 -> 14 | V41: =U41*D41 -> 9237.6963 | W41: ='Client Restocking'!L4 -> 0
B42: 1 ltr Low Fat Unsweetend Greek Yoghurt (6x) | C42: 38813.85 | D42: 659.83545 | E42: 2057.13 | G42: =F42*C42 -> 0 | K42: 0 | L42: =H42+U42+W42-O42-Q42-I42-J42 -> -1.5 | M42: =K42-L42 -> 1.5 | N42: =M42*C42 -> 58220.775 | O42: ='Dala Sales & Deliveries'!L5 -> 13.5 | P42: =O42*E42 -> 27771.255 | Q42: ='External Delivery Fulfillment'!L5 -> 0 | R42: =Q42*E42 -> 0 | S42: ='Forwarding From Client'!L5 -> 0 | T42: =S42*E42 -> 0 | U42: ='Dala Restocking'!L5 -> 12 | V42: =U42*D42 -> 7918.0254 | W42: ='Client Restocking'!L5 -> 0
B43: 250ml Strawberry Yoghurt (12x) | C43: 19953.12 | D43: 339.20304 | E43: 1057.52 | G43: =F43*C43 -> 0 | K43: 2 | L43: =H43+U43+W43-O43-Q43-I43-J43 -> -10.5 | M43: =K43-L43 -> 12.5 | N43: =M43*C43 -> 249414 | O43: ='Dala Sales & Deliveries'!L6 -> 35.5 | P43: =O43*E43 -> 37541.96 | Q43: ='External Delivery Fulfillment'!L6 -> 0 | R43: =Q43*E43 -> 0 | S43: ='Forwarding From Client'!L6 -> 0 | T43: =S43*E43 -> 0 | U43: ='Dala Restocking'!L6 -> 25 | V43: =U43*D43 -> 8480.076 | W43: ='Client Restocking'!L6 -> 0
B44: 250ml Vanilla Yoghurt (12x) | C44: 19953.12 | D44: 339.20304 | E44: 1057.52 | G44: =F44*C44 -> 0 | K44: 8 | L44: =H44+U44+W44-O44-Q44-I44-J44 -> -1.5 | M44: =K44-L44 -> 9.5 | N44: =M44*C44 -> 189554.64 | O44: ='Dala Sales & Deliveries'!L7 -> 41.5 | P44: =O44*E44 -> 43887.08 | Q44: ='External Delivery Fulfillment'!L7 -> 0 | R44: =Q44*E44 -> 0 | S44: ='Forwarding From Client'!L7 -> 0 | T44: =S44*E44 -> 0 | U44: ='Dala Restocking'!L7 -> 40 | V44: =U44*D44 -> 13568.122 | W44: ='Client Restocking'!L7 -> 0
B45: 500ml High Protien Sweetend Greek Yoghurt (12x) | C45: 49082.07 | D45: 834.39514 | E45: 2601.35 | G45: =F45*C45 -> 0 | K45: 11.5 | L45: =H45+U45+W45-O45-Q45-I45-J45 -> -1.5 | M45: =K45-L45 -> 13 | N45: =M45*C45 -> 638066.91 | O45: ='Dala Sales & Deliveries'!L8 -> 56.5 | P45: =O45*E45 -> 146976.27 | Q45: ='External Delivery Fulfillment'!L8 -> 0 | R45: =Q45*E45 -> 0 | S45: ='Forwarding From Client'!L8 -> 0 | T45: =S45*E45 -> 0 | U45: ='Dala Restocking'!L8 -> 55 | V45: =U45*D45 -> 45891.733 | W45: ='Client Restocking'!L8 -> 0
B46: 500ml High Protien Unsweetend Greek Yoghurt (12x) | C46: 49082.07 | D46: 834.39514 | E46: 2601.35 | G46: =F46*C46 -> 0 | K46: 12 | L46: =H46+U46+W46-O46-Q46-I46-J46 -> 7 | M46: =K46-L46 -> 5 | N46: =M46*C46 -> 245410.35 | O46: ='Dala Sales & Deliveries'!L9 -> 33 | P46: =O46*E46 -> 85844.55 | Q46: ='External Delivery Fulfillment'!L9 -> 0 | R46: =Q46*E46 -> 0 | S46: ='Forwarding From Client'!L9 -> 0 | T46: =S46*E46 -> 0 | U46: ='Dala Restocking'!L9 -> 40 | V46: =U46*D46 -> 33375.806 | W46: ='Client Restocking'!L9 -> 0
B47: 500ml Low Fat Sweetend Greek Yoghurt (12x) | C47: 43039.89 | D47: 731.67813 | E47: 2281.11 | G47: =F47*C47 -> 0 | K47: 12 | L47: =H47+U47+W47-O47-Q47-I47-J47 -> 2 | M47: =K47-L47 -> 10 | N47: =M47*C47 -> 430398.9 | O47: ='Dala Sales & Deliveries'!L10 -> 43 | P47: =O47*E47 -> 98087.73 | Q47: ='External Delivery Fulfillment'!L10 -> 0 | R47: =Q47*E47 -> 0 | S47: ='Forwarding From Client'!L10 -> 0 | T47: =S47*E47 -> 0 | U47: ='Dala Restocking'!L10 -> 45 | V47: =U47*D47 -> 32925.516 | W47: ='Client Restocking'!L10 -> 0
B48: 500ml Low Fat Unsweetend Greek Yoghurt (12x) | C48: 43039.89 | D48: 731.67813 | E48: 2281.11 | G48: =F48*C48 -> 0 | K48: 7 | L48: =H48+U48+W48-O48-Q48-I48-J48 -> 1.5 | M48: =K48-L48 -> 5.5 | N48: =M48*C48 -> 236719.39 | O48: ='Dala Sales & Deliveries'!L11 -> 28.5 | P48: =O48*E48 -> 65011.635 | Q48: ='External Delivery Fulfillment'!L11 -> 0 | R48: =Q48*E48 -> 0 | S48: ='Forwarding From Client'!L11 -> 0 | T48: =S48*E48 -> 0 | U48: ='Dala Restocking'!L11 -> 30 | V48: =U48*D48 -> 21950.344 | W48: ='Client Restocking'!L11 -> 0
B49: 500ml Strawberry Yoghurt (12x) | C49: 32611.3 | D49: 554.39213 | E49: 1728.4 | G49: =F49*C49 -> 0 | K49: 13 | L49: =H49+U49+W49-O49-Q49-I49-J49 -> 6 | M49: =K49-L49 -> 7 | N49: =M49*C49 -> 228279.1 | O49: ='Dala Sales & Deliveries'!L12 -> 44 | P49: =O49*E49 -> 76049.6 | Q49: ='External Delivery Fulfillment'!L12 -> 0 | R49: =Q49*E49 -> 0 | S49: ='Forwarding From Client'!L12 -> 0 | T49: =S49*E49 -> 0 | U49: ='Dala Restocking'!L12 -> 50 | V49: =U49*D49 -> 27719.607 | W49: ='Client Restocking'!L12 -> 0
B50: 500ml Vanilla Yoghurt (12x) | C50: 32611.3 | D50: 554.39213 | E50: 1728.4 | G50: =F50*C50 -> 0 | K50: 0 | L50: =H50+U50+W50-O50-Q50-I50-J50 -> 0 | M50: =K50-L50 -> 0 | N50: =M50*C50 -> 0 | O50: ='Dala Sales & Deliveries'!L13 -> 40 | P50: =O50*E50 -> 69136 | Q50: ='External Delivery Fulfillment'!L13 -> 0 | R50: =Q50*E50 -> 0 | S50: ='Forwarding From Client'!L13 -> 0 | T50: =S50*E50 -> 0 | U50: ='Dala Restocking'!L13 -> 40 | V50: =U50*D50 -> 22175.685 | W50: ='Client Restocking'!L13 -> 0
G51: =F51*C51 -> 0 | L51: =H51+U51+W51-O51-Q51-I51-J51 -> 0 | M51: =K51-L51 -> 0 | N51: =M51*C51 -> 0 | O51: ='Dala Sales & Deliveries'!L14 -> 0 | P51: =O51*E51 -> 0 | Q51: ='External Delivery Fulfillment'!L14 -> 0 | R51: =Q51*E51 -> 0 | S51: ='Forwarding From Client'!L14 -> 0 | T51: =S51*E51 -> 0 | U51: ='Dala Restocking'!L14 -> 0 | V51: =U51*D51 -> 0 | W51: ='Client Restocking'!L14 -> 0
G52: =F52*C52 -> 0 | L52: =H52+U52+W52-O52-Q52-I52-J52 -> 0 | M52: =K52-L52 -> 0 | N52: =M52*C52 -> 0 | O52: ='Dala Sales & Deliveries'!L15 -> 0 | P52: =O52*E52 -> 0 | Q52: ='External Delivery Fulfillment'!L15 -> 0 | R52: =Q52*E52 -> 0 | S52: ='Forwarding From Client'!L15 -> 0 | T52: =S52*E52 -> 0 | U52: ='Dala Restocking'!L15 -> 0 | V52: =U52*D52 -> 0 | W52: ='Client Restocking'!L15 -> 0
G53: =F53*C53 -> 0 | L53: =H53+U53+W53-O53-Q53-I53-J53 -> 0 | M53: =K53-L53 -> 0 | N53: =M53*C53 -> 0 | O53: ='Dala Sales & Deliveries'!L16 | P53: =O53*E53 -> 0 | Q53: ='External Delivery Fulfillment'!L16 | R53: =Q53*E53 -> 0 | S53: ='Forwarding From Client'!L16 | T53: =S53*E53 -> 0 | U53: ='Dala Restocking'!L16 | V53: =U53*D53 -> 0 | W53: ='Client Restocking'!L16
G54: =F54*C54 -> 0 | L54: =H54+U54+W54-O54-Q54-I54-J54 -> 0 | M54: =K54-L54 -> 0 | N54: =M54*C54 -> 0 | O54: ='Dala Sales & Deliveries'!L17 | P54: =O54*E54 -> 0 | Q54: ='External Delivery Fulfillment'!L17 | R54: =Q54*E54 -> 0 | S54: ='Forwarding From Client'!L17 | T54: =S54*E54 -> 0 | U54: ='Dala Restocking'!L17 | V54: =U54*D54 -> 0 | W54: ='Client Restocking'!L17
G55: =F55*C55 -> 0 | L55: =H55+U55+W55-O55-Q55-I55-J55 -> 0 | M55: =K55-L55 -> 0 | N55: =M55*C55 -> 0 | O55: ='Dala Sales & Deliveries'!L18 -> 0 | P55: =O55*E55 -> 0 | Q55: ='External Delivery Fulfillment'!L18 -> 0 | R55: =Q55*E55 -> 0 | S55: ='Forwarding From Client'!L18 | T55: =S55*E55 -> 0 | U55: ='Dala Restocking'!L18 -> 0 | V55: =U55*D55 -> 0 | W55: ='Client Restocking'!L18
G56: =F56*C56 -> 0 | L56: =H56+U56+W56-O56-Q56-I56-J56 -> 0 | M56: =K56-L56 -> 0 | N56: =M56*C56 -> 0 | O56: ='Dala Sales & Deliveries'!L19 | P56: =O56*E56 -> 0 | Q56: ='External Delivery Fulfillment'!L19 | R56: =Q56*E56 -> 0 | S56: ='Forwarding From Client'!L19 | T56: =S56*E56 -> 0 | U56: ='Dala Restocking'!L19 | V56: =U56*D56 -> 0 | W56: ='Client Restocking'!L19
G57: =F57*C57 -> 0 | L57: =H57+U57+W57-O57-Q57-I57-J57 -> 0 | M57: =K57-L57 -> 0 | N57: =M57*C57 -> 0 | O57: ='Dala Sales & Deliveries'!L20 | P57: =O57*E57 -> 0 | Q57: ='External Delivery Fulfillment'!L20 | R57: =Q57*E57 -> 0 | S57: ='Forwarding From Client'!L20 | T57: =S57*E57 -> 0 | U57: ='Dala Restocking'!L20 | V57: =U57*D57 -> 0 | W57: ='Client Restocking'!L20
G58: =F58*C58 -> 0 | L58: =H58+U58+W58-O58-Q58-I58-J58 -> 0 | M58: =K58-L58 -> 0 | N58: =M58*C58 -> 0 | O58: ='Dala Sales & Deliveries'!L21 -> 0 | P58: =O58*E58 -> 0 | Q58: ='External Delivery Fulfillment'!L21 -> 0 | R58: =Q58*E58 -> 0 | S58: ='Forwarding From Client'!L21 | T58: =S58*E58 -> 0 | U58: ='Dala Restocking'!L21 -> 0 | V58: =U58*D58 -> 0 | W58: ='Client Restocking'!L21
G59: =F59*C59 -> 0 | L59: =H59+U59+W59-O59-Q59-I59-J59 -> 0 | M59: =K59-L59 -> 0 | N59: =M59*C59 -> 0 | O59: ='Dala Sales & Deliveries'!L22 | P59: =O59*E59 -> 0 | Q59: ='External Delivery Fulfillment'!L22 | R59: =Q59*E59 -> 0 | S59: ='Forwarding From Client'!L22 | T59: =S59*E59 -> 0 | U59: ='Dala Restocking'!L22 | V59: =U59*D59 -> 0 | W59: ='Client Restocking'!L22
G60: =F60*C60 -> 0 | L60: =H60+U60+W60-O60-Q60-I60-J60 -> 0 | M60: =K60-L60 -> 0 | N60: =M60*C60 -> 0 | O60: ='Dala Sales & Deliveries'!L23 | P60: =O60*E60 -> 0 | Q60: ='External Delivery Fulfillment'!L23 | R60: =Q60*E60 -> 0 | S60: ='Forwarding From Client'!L23 | T60: =S60*E60 -> 0 | U60: ='Dala Restocking'!L23 | V60: =U60*D60 -> 0 | W60: ='Client Restocking'!L23
G61: =F61*C61 -> 0 | L61: =H61+U61+W61-O61-Q61-I61-J61 -> 0 | M61: =K61-L61 -> 0 | N61: =M61*C61 -> 0 | O61: ='Dala Sales & Deliveries'!L24 -> 0 | P61: =O61*E61 -> 0 | Q61: ='External Delivery Fulfillment'!L24 -> 0 | R61: =Q61*E61 -> 0 | S61: ='Forwarding From Client'!L24 | T61: =S61*E61 -> 0 | U61: ='Dala Restocking'!L24 -> 0 | V61: =U61*D61 -> 0 | W61: ='Client Restocking'!L24
G62: =F62*C62 -> 0 | L62: =H62+U62+W62-O62-Q62-I62-J62 -> 0 | M62: =K62-L62 -> 0 | N62: =M62*C62 -> 0 | O62: ='Dala Sales & Deliveries'!L25 | P62: =O62*E62 -> 0 | Q62: ='External Delivery Fulfillment'!L25 | R62: =Q62*E62 -> 0 | S62: ='Forwarding From Client'!L25 | T62: =S62*E62 -> 0 | U62: ='Dala Restocking'!L25 | V62: =U62*D62 -> 0 | W62: ='Client Restocking'!L25
... G66: =F66*C66 -> 0 | L66: =H66+U66+W66-O66-Q66-I66-J66 -> 0 | M66: =K66-L66 -> 0 | N66: =M66*C66 -> 0 | O66: ='Dala Sales & Deliveries'!L29 | P66: =O66*E66 -> 0 | Q66: ='External Delivery Fulfillment'!L29 | R66: =Q66*E66 -> 0 | S66: ='Forwarding From Client'!L29 | T66: =S66*E66 -> 0 | U66: ='Dala Restocking'!L29 | V66: =U66*D66 -> 0 | W66: ='Client Restocking'!L29
G67: =F67*C67 -> 0 | L67: =H67+U67+W67-O67-Q67-I67-J67 -> 0 | M67: =K67-L67 -> 0 | N67: =M67*C67 -> 0 | P67: =O67*E67 -> 0 | R67: =Q67*E67 -> 0 | S67: ='Forwarding From Client'!L30 | T67: =S67*E67 -> 0 | V67: =U67*D67 -> 0
B68: TOTAL | F68: =sum(F39:F67) -> 0 | G68: =sum(G39:G67) -> 0 | H68: =sum(H39:H67) -> 0 | I68: =sum(I39:I67) -> 0 | J68: =sum(J39:J67) -> 0 | K68: =sum(K39:K67) -> 67.5 | L68: =sum(L39:L67) -> 3 | M68: =sum(M39:M67) -> 64.5 | ... W68: =sum(W39:W67) -> 0
C69: x | D69: x | E69: x | F69: x | G69: x | H69: x | I69: x | J69: x | K69: x | L69: x | M69: x | N69: x | O69: x | P69: x | Q69: x | R69: x | S69: x | T69: x | U69: x | V69: x | W69: x

Sheet External Summary
B1: Description | C1: Units | D1: measurements | E1: total
A2: SALES | B2: Total Invoices Delivered | E2: ='Dala Sales & Deliveries'!I1+'External Delivery Fulfillment'!I1+'Forwarding From Client'!I1 -> 123
B3: Unique Locations Delivered To | E3: ='Raw Data'!AX3 -> 72
B4: Value of Dala Deliveries | E4: ='Dala Sales & Deliveries'!I3 -> 12906500
B5: VAT | E5: =E4*1.075-E4 -> 967987.48
B6: Total Value of Deliveries | E6: =sum(E4:E5) -> 13874487
A7: Remittance & Deductions | B7: Total Remitted to Partner
B8: Delivery Fees | C8: 0.04 | E8: =E7*(C8+100%)-E7 -> 0
B9: Collection Fees | C9: 0.07 | E9: =E7*(C9+100%)-E7 -> 0
A10: Debts | B10: Unpaid Subscription | D10: 350000 | E10: =C10*D10 -> 0
B11: Restocking Fees | E11: =V67 -> 240477.06
B12: External Delivery Fees | E12: =C24 -> 729206.19
B13: Reimbursements Due To DALA | E13: 0
B14: Retailer Deductions | E14: =C28 -> 0
B15: Total Owed to Dala | E15: =sum(E10:E14) -> 969683.25
A18: Inventory and Operational Fees
B19: Dala Pickup for Warehouse | C19: =U67 -> 375
B20: Warehouse Delivery Fee | C20: =V67 -> 240477.06
B21: Forwarding to Retail | C21: =S67 -> 0
B22: Forwarding Delivery Fee | C22: =T67 -> 0
B23: Dala Sales | C23: =O67 -> 372
B24: Dala Delivery Fees | C24: =P67 -> 729206.19
B25: Exteranl Deliveries | C25: =Q67 -> 0
B26: External Delivery Fees | C26: =R67 -> 0
B27: Product Defects and Expirey Issues | C27: =F67 -> 0
B28: Deductions From Retailer | C28: =G67 -> 0
B29: Samples used | C29: =I67 -> 0
B30: Returns/Replacements | C30: =J67 -> 0
B31: Expected Closing Inventory | C31: =L67 -> 3
B32: Physical Stock count | C32: =K67 -> 67.5
B33: Inventory Shortages | C33: 0
B34: Inventory Shortage Costs | C34: 0
B37: SKUs | C37: Retail Value | D37: Inbound Delivery Fee | E37: Outbound Delivery Fee | F37: Defects/Expirey | G37: Deductions | H37: Opening Inventory | I37: Samples Used | J37: Product Replacements | K37: Physical Closing Stock Count | L37: Expected Closing Inventory | M37: Inventory Shortages | N37: Shortages Costs | O37: Dala Sales | P37: Retail Sales Fee | Q37: External Delivery | R37: External Delivery Fee | S37: Forwarding from Client | T37: Forwarding Delivery Fee | U37: Dala Restocking | V37: Dala Restocking Fee | W37: Client Restocking
B38: ='Internal Summary'!B39 -> 1 ltr High Protien Sweetend Greek Yoghurt (6x) | C38: ='Internal Summary'!C39 -> 42241.3 | D38: ='Internal Summary'!D39 -> 718.1021 | E38: ='Internal Summary'!E39 -> 2238.79 | G38: =F38*C38 -> 0 | K38: 1 | L38: =H38+U38+W38-O38-Q38-I38-J38 -> 1 | M38: =K38-L38 -> 0 | N38: =M38*C38 -> 0 | O38: ='Dala Sales & Deliveries'!L2 -> 13 | P38: =O38*E38 -> 29104.27 | Q38: ='External Delivery Fulfillment'!L2 -> 0 | R38: =Q38*E38 -> 0 | S38: ='Forwarding From Client'!L2 -> 0 | T38: =S38*E38 -> 0 | U38: ='Dala Restocking'!L2 -> 14 | V38: =U38*D38 -> 10053.429 | W38: ='Client Restocking'!L2 -> 0
B39: ='Internal Summary'!B40 -> 1 ltr High Protien Unsweetend Greek Yoghurt (6x) | C39: ='Internal Summary'!C40 -> 42241.3 | D39: ='Internal Summary'!D40 -> 718.1021 | E39: ='Internal Summary'!E40 -> 2238.79 | G39: =F39*C39 -> 0 | K39: 1 | L39: =H39+U39+W39-O39-Q39-I39-J39 -> 2 | M39: =K39-L39 -> -1 | O39: ='Dala Sales & Deliveries'!L3 -> 8 | P39: =O39*E39 -> 17910.32 | Q39: ='External Delivery Fulfillment'!L3 -> 0 | R39: =Q39*E39 -> 0 | S39: ='Forwarding From Client'!L3 -> 0 | T39: =S39*E39 -> 0 | U39: ='Dala Restocking'!L3 -> 10 | V39: =U39*D39 -> 7181.021 | W39: ='Client Restocking'!L3 -> 0
B40: ='Internal Summary'!B41 -> 1 ltr Low Fat Sweetend Greek Yoghurt (6x) | C40: ='Internal Summary'!C41 -> 38813.85 | D40: ='Internal Summary'!D41 -> 659.83545 | E40: ='Internal Summary'!E41 -> 2057.13 | G40: =F40*C40 -> 0 | K40: 0 | L40: =H40+U40+W40-O40-Q40-I40-J40 -> -1.5 | M40: =K40-L40 -> 1.5 | O40: ='Dala Sales & Deliveries'!L4 -> 15.5 | P40: =O40*E40 -> 31885.515 | Q40: ='External Delivery Fulfillment'!L4 -> 0 | R40: =Q40*E40 -> 0 | S40: ='Forwarding From Client'!L4 -> 0 | T40: =S40*E40 -> 0 | U40: ='Dala Restocking'!L4 -> 14 | V40: =U40*D40 -> 9237.6963 | W40: ='Client Restocking'!L4 -> 0
B41: ='Internal Summary'!B42 -> 1 ltr Low Fat Unsweetend Greek Yoghurt (6x) | C41: ='Internal Summary'!C42 -> 38813.85 | D41: ='Internal Summary'!D42 -> 659.83545 | E41: ='Internal Summary'!E42 -> 2057.13 | G41: =F41*C41 -> 0 | K41: 0 | L41: =H41+U41+W41-O41-Q41-I41-J41 -> -1.5 | M41: =K41-L41 -> 1.5 | O41: ='Dala Sales & Deliveries'!L5 -> 13.5 | P41: =O41*E41 -> 27771.255 | Q41: ='External Delivery Fulfillment'!L5 -> 0 | R41: =Q41*E41 -> 0 | S41: ='Forwarding From Client'!L5 -> 0 | T41: =S41*E41 -> 0 | U41: ='Dala Restocking'!L5 -> 12 | V41: =U41*D41 -> 7918.0254 | W41: ='Client Restocking'!L5 -> 0
B42: ='Internal Summary'!B43 -> 250ml Strawberry Yoghurt (12x) | C42: ='Internal Summary'!C43 -> 19953.12 | D42: ='Internal Summary'!D43 -> 339.20304 | E42: ='Internal Summary'!E43 -> 1057.52 | G42: =F42*C42 -> 0 | K42: 2 | L42: =H42+U42+W42-O42-Q42-I42-J42 -> -10.5 | M42: =K42-L42 -> 12.5 | O42: ='Dala Sales & Deliveries'!L6 -> 35.5 | P42: =O42*E42 -> 37541.96 | Q42: ='External Delivery Fulfillment'!L6 -> 0 | R42: =Q42*E42 -> 0 | S42: ='Forwarding From Client'!L6 -> 0 | T42: =S42*E42 -> 0 | U42: ='Dala Restocking'!L6 -> 25 | V42: =U42*D42 -> 8480.076 | W42: ='Client Restocking'!L6 -> 0
B43: ='Internal Summary'!B44 -> 250ml Vanilla Yoghurt (12x) | C43: ='Internal Summary'!C44 -> 19953.12 | D43: ='Internal Summary'!D44 -> 339.20304 | E43: ='Internal Summary'!E44 -> 1057.52 | G43: =F43*C43 -> 0 | K43: 8 | L43: =H43+U43+W43-O43-Q43-I43-J43 -> -1.5 | M43: =K43-L43 -> 9.5 | O43: ='Dala Sales & Deliveries'!L7 -> 41.5 | P43: =O43*E43 -> 43887.08 | Q43: ='External Delivery Fulfillment'!L7 -> 0 | R43: =Q43*E43 -> 0 | S43: ='Forwarding From Client'!L7 -> 0 | T43: =S43*E43 -> 0 | U43: ='Dala Restocking'!L7 -> 40 | V43: =U43*D43 -> 13568.122 | W43: ='Client Restocking'!L7 -> 0
B44: ='Internal Summary'!B45 -> 500ml High Protien Sweetend Greek Yoghurt (12x) | C44: ='Internal Summary'!C45 -> 49082.07 | D44: ='Internal Summary'!D45 -> 834.39514 | E44: ='Internal Summary'!E45 -> 2601.35 | G44: =F44*C44 -> 0 | K44: 11.5 | L44: =H44+U44+W44-O44-Q44-I44-J44 -> -1.5 | M44: =K44-L44 -> 13 | O44: ='Dala Sales & Deliveries'!L8 -> 56.5 | P44: =O44*E44 -> 146976.27 | Q44: ='External Delivery Fulfillment'!L8 -> 0 | R44: =Q44*E44 -> 0 | S44: ='Forwarding From Client'!L8 -> 0 | T44: =S44*E44 -> 0 | U44: ='Dala Restocking'!L8 -> 55 | V44: =U44*D44 -> 45891.733 | W44: ='Client Restocking'!L8 -> 0
B45: ='Internal Summary'!B46 -> 500ml High Protien Unsweetend Greek Yoghurt (12x) | C45: ='Internal Summary'!C46 -> 49082.07 | D45: ='Internal Summary'!D46 -> 834.39514 | E45: ='Internal Summary'!E46 -> 2601.35 | G45: =F45*C45 -> 0 | K45: 12 | L45: =H45+U45+W45-O45-Q45-I45-J45 -> 7 | M45: =K45-L45 -> 5 | O45: ='Dala Sales & Deliveries'!L9 -> 33 | P45: =O45*E45 -> 85844.55 | Q45: ='External Delivery Fulfillment'!L9 -> 0 | R45: =Q45*E45 -> 0 | S45: ='Forwarding From Client'!L9 -> 0 | T45: =S45*E45 -> 0 | U45: ='Dala Restocking'!L9 -> 40 | V45: =U45*D45 -> 33375.806 | W45: ='Client Restocking'!L9 -> 0
B46: ='Internal Summary'!B47 -> 500ml Low Fat Sweetend Greek Yoghurt (12x) | C46: ='Internal Summary'!C47 -> 43039.89 | D46: ='Internal Summary'!D47 -> 731.67813 | E46: ='Internal Summary'!E47 -> 2281.11 | G46: =F46*C46 -> 0 | K46: 12 | L46: =H46+U46+W46-O46-Q46-I46-J46 -> 2 | M46: =K46-L46 -> 10 | O46: ='Dala Sales & Deliveries'!L10 -> 43 | P46: =O46*E46 -> 98087.73 | Q46: ='External Delivery Fulfillment'!L10 -> 0 | R46: =Q46*E46 -> 0 | S46: ='Forwarding From Client'!L10 -> 0 | T46: =S46*E46 -> 0 | U46: ='Dala Restocking'!L10 -> 45 | V46: =U46*D46 -> 32925.516 | W46: ='Client Restocking'!L10 -> 0
B47: ='Internal Summary'!B48 -> 500ml Low Fat Unsweetend Greek Yoghurt (12x) | C47: ='Internal Summary'!C48 -> 43039.89 | D47: ='Internal Summary'!D48 -> 731.67813 | E47: ='Internal Summary'!E48 -> 2281.11 | G47: =F47*C47 -> 0 | K47: 7 | L47: =H47+U47+W47-O47-Q47-I47-J47 -> 1.5 | M47: =K47-L47 -> 5.5 | O47: ='Dala Sales & Deliveries'!L11 -> 28.5 | P47: =O47*E47 -> 65011.635 | Q47: ='External Delivery Fulfillment'!L11 -> 0 | R47: =Q47*E47 -> 0 | S47: ='Forwarding From Client'!L11 -> 0 | T47: =S47*E47 -> 0 | U47: ='Dala Restocking'!L11 -> 30 | V47: =U47*D47 -> 21950.344 | W47: ='Client Restocking'!L11 -> 0
B48: ='Internal Summary'!B49 -> 500ml Strawberry Yoghurt (12x) | C48: ='Internal Summary'!C49 -> 32611.3 | D48: ='Internal Summary'!D49 -> 554.39213 | E48: ='Internal Summary'!E49 -> 1728.4 | G48: =F48*C48 -> 0 | K48: 13 | L48: =H48+U48+W48-O48-Q48-I48-J48 -> 6 | M48: =K48-L48 -> 7 | O48: ='Dala Sales & Deliveries'!L12 -> 44 | P48: =O48*E48 -> 76049.6 | Q48: ='External Delivery Fulfillment'!L12 -> 0 | R48: =Q48*E48 -> 0 | S48: ='Forwarding From Client'!L12 -> 0 | T48: =S48*E48 -> 0 | U48: ='Dala Restocking'!L12 -> 50 | V48: =U48*D48 -> 27719.607 | W48: ='Client Restocking'!L12 -> 0
B49: ='Internal Summary'!B50 -> 500ml Vanilla Yoghurt (12x) | C49: ='Internal Summary'!C50 -> 32611.3 | D49: ='Internal Summary'!D50 -> 554.39213 | E49: ='Internal Summary'!E50 -> 1728.4 | G49: =F49*C49 -> 0 | K49: 0 | L49: =H49+U49+W49-O49-Q49-I49-J49 -> 0 | M49: =K49-L49 -> 0 | O49: ='Dala Sales & Deliveries'!L13 -> 40 | P49: =O49*E49 -> 69136 | Q49: ='External Delivery Fulfillment'!L13 -> 0 | R49: =Q49*E49 -> 0 | S49: ='Forwarding From Client'!L13 -> 0 | T49: =S49*E49 -> 0 | U49: ='Dala Restocking'!L13 -> 40 | V49: =U49*D49 -> 22175.685 | W49: ='Client Restocking'!L13 -> 0
B50: ='Internal Summary'!B51 | C50: ='Internal Summary'!C51 | D50: ='Internal Summary'!D51 | E50: ='Internal Summary'!E51 | G50: =F50*C50 -> 0 | L50: =H50+U50+W50-O50-Q50-I50-J50 -> 0 | M50: =K50-L50 -> 0 | O50: ='Dala Sales & Deliveries'!L14 -> 0 | P50: =O50*E50 -> 0 | Q50: ='External Delivery Fulfillment'!L14 -> 0 | R50: =Q50*E50 -> 0 | S50: ='Forwarding From Client'!L14 -> 0 | T50: =S50*E50 -> 0 | U50: ='Dala Restocking'!L14 -> 0 | V50: =U50*D50 -> 0 | W50: ='Client Restocking'!L14 -> 0
B51: ='Internal Summary'!B52 | C51: ='Internal Summary'!C52 | D51: ='Internal Summary'!D52 | E51: ='Internal Summary'!E52 | G51: =F51*C51 -> 0 | L51: =H51+U51+W51-O51-Q51-I51-J51 -> 0 | M51: =K51-L51 -> 0 | O51: ='Dala Sales & Deliveries'!L15 -> 0 | P51: =O51*E51 -> 0 | Q51: ='External Delivery Fulfillment'!L15 -> 0 | R51: =Q51*E51 -> 0 | S51: ='Forwarding From Client'!L15 -> 0 | T51: =S51*E51 -> 0 | U51: ='Dala Restocking'!L15 -> 0 | V51: =U51*D51 -> 0 | W51: ='Client Restocking'!L15 -> 0
B52: ='Internal Summary'!B53 | C52: ='Internal Summary'!C53 | D52: ='Internal Summary'!D53 | E52: ='Internal Summary'!E53 | G52: =F52*C52 -> 0 | L52: =H52+U52+W52-O52-Q52-I52-J52 -> 0 | M52: =K52-L52 -> 0 | P52: =O52*E52 -> 0 | R52: =Q52*E52 -> 0 | S52: ='Forwarding From Client'!L16 | T52: =S52*E52 -> 0 | V52: =U52*D52 -> 0
B53: ='Internal Summary'!B54 | C53: ='Internal Summary'!C54 | D53: ='Internal Summary'!D54 | E53: ='Internal Summary'!E54 | G53: =F53*C53 -> 0 | L53: =H53+U53+W53-O53-Q53-I53-J53 -> 0 | M53: =K53-L53 -> 0 | P53: =O53*E53 -> 0 | R53: =Q53*E53 -> 0 | S53: ='Forwarding From Client'!L17 | T53: =S53*E53 -> 0 | V53: =U53*D53 -> 0
B54: ='Internal Summary'!B55 | C54: ='Internal Summary'!C55 | D54: ='Internal Summary'!D55 | E54: ='Internal Summary'!E55 | G54: =F54*C54 -> 0 | L54: =H54+U54+W54-O54-Q54-I54-J54 -> 0 | M54: =K54-L54 -> 0 | P54: =O54*E54 -> 0 | R54: =Q54*E54 -> 0 | S54: ='Forwarding From Client'!L18 | T54: =S54*E54 -> 0 | V54: =U54*D54 -> 0
B55: ='Internal Summary'!B56 | C55: ='Internal Summary'!C56 | D55: ='Internal Summary'!D56 | E55: ='Internal Summary'!E56 | G55: =F55*C55 -> 0 | L55: =H55+U55+W55-O55-Q55-I55-J55 -> 0 | M55: =K55-L55 -> 0 | P55: =O55*E55 -> 0 | R55: =Q55*E55 -> 0 | S55: ='Forwarding From Client'!L19 | T55: =S55*E55 -> 0 | V55: =U55*D55 -> 0
B56: ='Internal Summary'!B57 | C56: ='Internal Summary'!C57 | D56: ='Internal Summary'!D57 | E56: ='Internal Summary'!E57 | G56: =F56*C56 -> 0 | L56: =H56+U56+W56-O56-Q56-I56-J56 -> 0 | M56: =K56-L56 -> 0 | P56: =O56*E56 -> 0 | R56: =Q56*E56 -> 0 | S56: ='Forwarding From Client'!L20 | T56: =S56*E56 -> 0 | V56: =U56*D56 -> 0
B57: ='Internal Summary'!B58 | C57: ='Internal Summary'!C58 | D57: ='Internal Summary'!D58 | E57: ='Internal Summary'!E58 | G57: =F57*C57 -> 0 | L57: =H57+U57+W57-O57-Q57-I57-J57 -> 0 | M57: =K57-L57 -> 0 | P57: =O57*E57 -> 0 | R57: =Q57*E57 -> 0 | S57: ='Forwarding From Client'!L21 | T57: =S57*E57 -> 0 | V57: =U57*D57 -> 0
B58: ='Internal Summary'!B59 | C58: ='Internal Summary'!C59 | D58: ='Internal Summary'!D59 | E58: ='Internal Summary'!E59 | G58: =F58*C58 -> 0 | L58: =H58+U58+W58-O58-Q58-I58-J58 -> 0 | M58: =K58-L58 -> 0 | P58: =O58*E58 -> 0 | R58: =Q58*E58 -> 0 | S58: ='Forwarding From Client'!L22 | T58: =S58*E58 -> 0 | V58: =U58*D58 -> 0
B59: ='Internal Summary'!B60 | C59: ='Internal Summary'!C60 | D59: ='Internal Summary'!D60 | E59: ='Internal Summary'!E60 | G59: =F59*C59 -> 0 | L59: =H59+U59+W59-O59-Q59-I59-J59 -> 0 | M59: =K59-L59 -> 0 | P59: =O59*E59 -> 0 | R59: =Q59*E59 -> 0 | S59: ='Forwarding From Client'!L23 | T59: =S59*E59 -> 0 | V59: =U59*D59 -> 0
B60: ='Internal Summary'!B61 | C60: ='Internal Summary'!C61 | D60: ='Internal Summary'!D61 | E60: ='Internal Summary'!E61 | G60: =F60*C60 -> 0 | L60: =H60+U60+W60-O60-Q60-I60-J60 -> 0 | M60: =K60-L60 -> 0 | P60: =O60*E60 -> 0 | R60: =Q60*E60 -> 0 | S60: ='Forwarding From Client'!L24 | T60: =S60*E60 -> 0 | V60: =U60*D60 -> 0
B61: ='Internal Summary'!B62 | C61: ='Internal Summary'!C62 | D61: ='Internal Summary'!D62 | E61: ='Internal Summary'!E62 | G61: =F61*C61 -> 0 | L61: =H61+U61+W61-O61-Q61-I61-J61 -> 0 | M61: =K61-L61 -> 0 | P61: =O61*E61 -> 0 | R61: =Q61*E61 -> 0 | S61: ='Forwarding From Client'!L25 | T61: =S61*E61 -> 0 | V61: =U61*D61 -> 0
B62: ='Internal Summary'!B63 | C62: ='Internal Summary'!C63 | D62: ='Internal Summary'!D63 | E62: ='Internal Summary'!E63 | G62: =F62*C62 -> 0 | L62: =H62+U62+W62-O62-Q62-I62-J62 -> 0 | M62: =K62-L62 -> 0 | P62: =O62*E62 -> 0 | R62: =Q62*E62 -> 0 | S62: ='Forwarding From Client'!L26 | T62: =S62*E62 -> 0 | V62: =U62*D62 -> 0
B63: ='Internal Summary'!B64 | C63: ='Internal Summary'!C64 | D63: ='Internal Summary'!D64 | E63: ='Internal Summary'!E64 | G63: =F63*C63 -> 0 | L63: =H63+U63+W63-O63-Q63-I63-J63 -> 0 | M63: =K63-L63 -> 0 | P63: =O63*E63 -> 0 | R63: =Q63*E63 -> 0 | S63: ='Forwarding From Client'!L27 | T63: =S63*E63 -> 0 | V63: =U63*D63 -> 0
... B66: ='Internal Summary'!B67 | C66: ='Internal Summary'!C67 | D66: ='Internal Summary'!D67 | E66: ='Internal Summary'!E67 | G66: =F66*C66 -> 0 | L66: =H66+U66+W66-O66-Q66-I66-J66 -> 0 | M66: =K66-L66 -> 0 | P66: =O66*E66 -> 0 | R66: =Q66*E66 -> 0 | S66: ='Forwarding From Client'!L30 | T66: =S66*E66 -> 0 | V66: =U66*D66 -> 0
B67: TOTAL | F67: =sum(F38:F66) -> 0 | G67: =sum(G38:G66) -> 0 | H67: =sum(H38:H66) -> 0 | I67: =sum(I38:I66) -> 0 | J67: =sum(J38:J66) -> 0 | K67: =sum(K38:K66) -> 67.5 | L67: =sum(L38:L66) -> 3 | M67: =sum(M38:M66) -> 64.5 | ... W67: =sum(W38:W66) -> 0
C68: x | D68: x | E68: x | F68: x | H68: x | I68: x | J68: x | K68: x | L68: x | N68: x | O68: x | P68: x | Q68: x | R68: x | U68: x | V68: x | W68: x
