Workbook

Sheet Raw Data
A1: Exported from Tally | I1: Dala Sales & Deliveries | Q1: External Deliveries | Y1: Forwarding From Client | AG1: Client Restock | AO1: Dala Restock | AW1: Unique Locations
A2: item name | B2: Date | C2: Particulars | D2: Vch Type | E2: Vch No. | F2: Quantity | G2: Value | I2: item name | J2: Date | K2: Particulars | L2: Vch Type | M2: Vch No. | N2: Quantity | O2: Value | P2: Total Value | Q2: item name | R2: Date | S2: Particulars | T2: Vch Type | U2: Vch No. | V2: Quantity | W2: Value | Y2: item name | Z2: Date | AA2: Particulars | AB2: Vch Type | AC2: Vch No. | AD2: Quantity | AE2: Value | AG2: item name | AH2: Date | AI2: Particulars | AJ2: Vch Type | AK2: Vch No. | AL2: Quantity | AM2: Value | AO2: item name | AP2: Date | AQ2: Particulars | AR2: Vch Type | AS2: Vch No. | AT2: Quantity | AU2: Value | AW2: {=counta(unique(C:C))-2} -> 9
A3: 350ml Orisirisi Wallnut Drink (12x) | B3: 46072 | C3: Orisirisi Catring Service | D3: Inventory Supplied by Brands | E3: 2055 | F3: 1.75 | G3: 37800 | I3: =IFERROR(__xludf.DUMMYFUNCTION("IFERROR( FILTER($A$3:$G1844, LEN($A$3:$A1844), LOWER(TRIM($D$3:$D1844))=""sales""), )"),"350ml Orisirisi Wallnut with Ginger Drink (12x)") -> 350ml Orisirisi Wallnut with Ginger Drink (12x) | J3: =IFERROR(__xludf.DUMMYFUNCTION("""COMPUTED_VALUE"""),46069.0) -> 46069 | K3: =IFERROR(__xludf.DUMMYFUNCTION("""COMPUTED_VALUE"""),"Jendol Supermarket, AKASOLORI") -> Jendol Supermarket, AKASOLORI | L3: =IFERROR(__xludf.DUMMYFUNCTION("""COMPUTED_VALUE"""),"Sales") -> Sales | M3: =IFERROR(__xludf.DUMMYFUNCTION("""COMPUTED_VALUE"""),"DT:000958") -> DT:000958 | N3: =IFERROR(__xludf.DUMMYFUNCTION("""COMPUTED_VALUE"""),0.5) -> 0.5 | O3: =IFERROR(__xludf.DUMMYFUNCTION("""COMPUTED_VALUE"""),10800.0) -> 10800 | P3: =SUMIF(M:M,M3,O:O) -> 62400 | Q3: =IFERROR(__xludf.DUMMYFUNCTION("IFERROR( FILTER($A$3:$G1844, LEN($A$3:$A1844), REGEXMATCH(LOWER(TRIM($D$3:$D1844)), ""\bjournal\b"")), )"),"") | AG3: =IFERROR(__xludf.DUMMYFUNCTION("IFERROR(FILTER($A$3:$G1844, LEN($A$3:$A1844), LOWER(TRIM($D$3:$D1844))=""Inventory Supplied by Brands""),)"),"350ml Orisirisi Wallnut Drink (12x)") -> 350ml Orisirisi Wallnut Drink (12x) | AH3: =IFERROR(__xludf.DUMMYFUNCTION("""COMPUTED_VALUE"""),46072.0) -> 46072 | AI3: =IFERROR(__xludf.DUMMYFUNCTION("""COMPUTED_VALUE"""),"Orisirisi Catring Service") -> Orisirisi Catring Service | AJ3: =IFERROR(__xludf.DUMMYFUNCTION("""COMPUTED_VALUE"""),"Inventory Supplied by Brands") -> Inventory Supplied by Brands | AK3: =IFERROR(__xludf.DUMMYFUNCTION("""COMPUTED_VALUE"""),2055.0) -> 2055 | AL3: =IFERROR(__xludf.DUMMYFUNCTION("""COMPUTED_VALUE"""),1.75) -> 1.75 | AM3: =IFERROR(__xludf.DUMMYFUNCTION("""COMPUTED_VALUE"""),37800.0) -> 37800 | AO3: =IFERROR(__xludf.DUMMYFUNCTION("IFERROR(FILTER($A$3:$G1844, LEN($A$3:$A1844), LOWER(TRIM($D$3:$D1844))=""Inventory Pickup by Dala""),) "),"")
A4: 350ml Orisirisi Wallnut with Ginger Drink (12x) | B4: 46072 | C4: Orisirisi Catring Service | D4: Inventory Supplied by Brands | E4: 2055 | F4: 6 | G4: 129600 | I4: =IFERROR(__xludf.DUMMYFUNCTION("""COMPUTED_VALUE"""),"350ml Orisirisi Wallnut with Ginger Drink (12x)") -> 350ml Orisirisi Wallnut with Ginger Drink (12x) | J4: =IFERROR(__xludf.DUMMYFUNCTION("""COMPUTED_VALUE"""),46072.0) -> 46072 | K4: =IFERROR(__xludf.DUMMYFUNCTION("""COMPUTED_VALUE"""),"Buymore Supermarket, ISHERI") -> Buymore Supermarket, ISHERI | L4: =IFERROR(__xludf.DUMMYFUNCTION("""COMPUTED_VALUE"""),"Sales") -> Sales | M4: =IFERROR(__xludf.DUMMYFUNCTION("""COMPUTED_VALUE"""),"DT:001044") -> DT:001044 | N4: =IFERROR(__xludf.DUMMYFUNCTION("""COMPUTED_VALUE"""),1.0) -> 1 | O4: =IFERROR(__xludf.DUMMYFUNCTION("""COMPUTED_VALUE"""),21600.0) -> 21600 | P4: =SUMIF(M:M,M4,O:O) -> 21600 | AG4: =IFERROR(__xludf.DUMMYFUNCTION("""COMPUTED_VALUE"""),"350ml Orisirisi Wallnut with Ginger Drink (12x)") -> 350ml Orisirisi Wallnut with Ginger Drink (12x) | AH4: =IFERROR(__xludf.DUMMYFUNCTION("""COMPUTED_VALUE"""),46072.0) -> 46072 | AI4: =IFERROR(__xludf.DUMMYFUNCTION("""COMPUTED_VALUE"""),"Orisirisi Catring Service") -> Orisirisi Catring Service | AJ4: =IFERROR(__xludf.DUMMYFUNCTION("""COMPUTED_VALUE"""),"Inventory Supplied by Brands") -> Inventory Supplied by Brands | AK4: =IFERROR(__xludf.DUMMYFUNCTION("""COMPUTED_VALUE"""),2055.0) -> 2055 | AL4: =IFERROR(__xludf.DUMMYFUNCTION("""COMPUTED_VALUE"""),6.0) -> 6 | AM4: =IFERROR(__xludf.DUMMYFUNCTION("""COMPUTED_VALUE"""),129600.0) -> 129600
A5: 500ml Orisirisi Tiger Nut Drink (12x) | B5: 46072 | C5: Orisirisi Catring Service | D5: Inventory Supplied by Brands | E5: 2055 | F5: 8 | G5: 220800 | I5: =IFERROR(__xludf.DUMMYFUNCTION("""COMPUTED_VALUE"""),"500ml Orisirisi Tiger Nut Drink (12x)") -> 500ml Orisirisi Tiger Nut Drink (12x) | J5: =IFERROR(__xludf.DUMMYFUNCTION("""COMPUTED_VALUE"""),46066.0) -> 46066 | K5: =IFERROR(__xludf.DUMMYFUNCTION("""COMPUTED_VALUE"""),"Individual") -> Individual | L5: =IFERROR(__xludf.DUMMYFUNCTION("""COMPUTED_VALUE"""),"Sales") -> Sales | M5: =IFERROR(__xludf.DUMMYFUNCTION("""COMPUTED_VALUE"""),"DT:000885") -> DT:000885 | N5: =IFERROR(__xludf.DUMMYFUNCTION("""COMPUTED_VALUE"""),0.25) -> 0.25 | O5: =IFERROR(__xludf.DUMMYFUNCTION("""COMPUTED_VALUE"""),6900.0) -> 6900 | P5: =SUMIF(M:M,M5,O:O) -> 6900 | AG5: =IFERROR(__xludf.DUMMYFUNCTION("""COMPUTED_VALUE"""),"500ml Orisirisi Tiger Nut Drink (12x)") -> 500ml Orisirisi Tiger Nut Drink (12x) | AH5: =IFERROR(__xludf.DUMMYFUNCTION("""COMPUTED_VALUE"""),46072.0) -> 46072 | AI5: =IFERROR(__xludf.DUMMYFUNCTION("""COMPUTED_VALUE"""),"Orisirisi Catring Service") -> Orisirisi Catring Service | AJ5: =IFERROR(__xludf.DUMMYFUNCTION("""COMPUTED_VALUE"""),"Inventory Supplied by Brands") -> Inventory Supplied by Brands | AK5: =IFERROR(__xludf.DUMMYFUNCTION("""COMPUTED_VALUE"""),2055.0) -> 2055 | AL5: =IFERROR(__xludf.DUMMYFUNCTION("""COMPUTED_VALUE"""),8.0) -> 8 | AM5: =IFERROR(__xludf.DUMMYFUNCTION("""COMPUTED_VALUE"""),220800.0) -> 220800
A6: 500ml Orisirisi Zobo Drink (12x) | B6: 46072 | C6: Orisirisi Catring Service | D6: Inventory Supplied by Brands | E6: 2055 | F6: 9 | G6: 216000 | I6: =IFERROR(__xludf.DUMMYFUNCTION("""COMPUTED_VALUE"""),"500ml Orisirisi Tiger Nut Drink (12x)") -> 500ml Orisirisi Tiger Nut Drink (12x) | J6: =IFERROR(__xludf.DUMMYFUNCTION("""COMPUTED_VALUE"""),46066.0) -> 46066 | K6: =IFERROR(__xludf.DUMMYFUNCTION("""COMPUTED_VALUE"""),"Alvira Mart") -> Alvira Mart | L6: =IFERROR(__xludf.DUMMYFUNCTION("""COMPUTED_VALUE"""),"Sales") -> Sales | M6: =IFERROR(__xludf.DUMMYFUNCTION("""COMPUTED_VALUE"""),"DT:000910") -> DT:000910 | N6: =IFERROR(__xludf.DUMMYFUNCTION("""COMPUTED_VALUE"""),1.0) -> 1 | O6: =IFERROR(__xludf.DUMMYFUNCTION("""COMPUTED_VALUE"""),27600.0) -> 27600 | P6: =SUMIF(M:M,M6,O:O) -> 51600 | AG6: =IFERROR(__xludf.DUMMYFUNCTION("""COMPUTED_VALUE"""),"500ml Orisirisi Zobo Drink (12x)") -> 500ml Orisirisi Zobo Drink (12x) | AH6: =IFERROR(__xludf.DUMMYFUNCTION("""COMPUTED_VALUE"""),46072.0) -> 46072 | AI6: =IFERROR(__xludf.DUMMYFUNCTION("""COMPUTED_VALUE"""),"Orisirisi Catring Service") -> Orisirisi Catring Service | AJ6: =IFERROR(__xludf.DUMMYFUNCTION("""COMPUTED_VALUE"""),"Inventory Supplied by Brands") -> Inventory Supplied by Brands | AK6: =IFERROR(__xludf.DUMMYFUNCTION("""COMPUTED_VALUE"""),2055.0) -> 2055 | AL6: =IFERROR(__xludf.DUMMYFUNCTION("""COMPUTED_VALUE"""),9.0) -> 9 | AM6: =IFERROR(__xludf.DUMMYFUNCTION("""COMPUTED_VALUE"""),216000.0) -> 216000
A7: 500ml Orisirisi Zobo with Date Drink (12x) | B7: 46072 | C7: Orisirisi Catring Service | D7: Inventory Supplied by Brands | E7: 2055 | F7: 9 | G7: 216000 | I7: =IFERROR(__xludf.DUMMYFUNCTION("""COMPUTED_VALUE"""),"500ml Orisirisi Tiger Nut Drink (12x)") -> 500ml Orisirisi Tiger Nut Drink (12x) | J7: =IFERROR(__xludf.DUMMYFUNCTION("""COMPUTED_VALUE"""),46069.0) -> 46069 | K7: =IFERROR(__xludf.DUMMYFUNCTION("""COMPUTED_VALUE"""),"CMART Supermarket, ONIRU") -> CMART Supermarket, ONIRU | L7: =IFERROR(__xludf.DUMMYFUNCTION("""COMPUTED_VALUE"""),"Sales") -> Sales | M7: =IFERROR(__xludf.DUMMYFUNCTION("""COMPUTED_VALUE"""),"DT:000938") -> DT:000938 | N7: =IFERROR(__xludf.DUMMYFUNCTION("""COMPUTED_VALUE"""),0.5) -> 0.5 | O7: =IFERROR(__xludf.DUMMYFUNCTION("""COMPUTED_VALUE"""),13800.0) -> 13800 | P7: =SUMIF(M:M,M7,O:O) -> 37800 | AG7: =IFERROR(__xludf.DUMMYFUNCTION("""COMPUTED_VALUE"""),"500ml Orisirisi Zobo with Date Drink (12x)") -> 500ml Orisirisi Zobo with Date Drink (12x) | AH7: =IFERROR(__xludf.DUMMYFUNCTION("""COMPUTED_VALUE"""),46072.0) -> 46072 | AI7: =IFERROR(__xludf.DUMMYFUNCTION("""COMPUTED_VALUE"""),"Orisirisi Catring Service") -> Orisirisi Catring Service | AJ7: =IFERROR(__xludf.DUMMYFUNCTION("""COMPUTED_VALUE"""),"Inventory Supplied by Brands") -> Inventory Supplied by Brands | AK7: =IFERROR(__xludf.DUMMYFUNCTION("""COMPUTED_VALUE"""),2055.0) -> 2055 | AL7: =IFERROR(__xludf.DUMMYFUNCTION("""COMPUTED_VALUE"""),9.0) -> 9 | AM7: =IFERROR(__xludf.DUMMYFUNCTION("""COMPUTED_VALUE"""),216000.0) -> 216000
A8: 350ml Orisirisi Wallnut with Ginger Drink (12x) | B8: 46069 | C8: Jendol Supermarket, AKASOLORI | D8: Sales | E8: DT:000958 | F8: 0.5 | G8: 10800 | I8: =IFERROR(__xludf.DUMMYFUNCTION("""COMPUTED_VALUE"""),"500ml Orisirisi Tiger Nut Drink (12x)") -> 500ml Orisirisi Tiger Nut Drink (12x) | J8: =IFERROR(__xludf.DUMMYFUNCTION("""COMPUTED_VALUE"""),46069.0) -> 46069 | K8: =IFERROR(__xludf.DUMMYFUNCTION("""COMPUTED_VALUE"""),"Jendol Supermarket, AKASOLORI") -> Jendol Supermarket, AKASOLORI | L8: =IFERROR(__xludf.DUMMYFUNCTION("""COMPUTED_VALUE"""),"Sales") -> Sales | M8: =IFERROR(__xludf.DUMMYFUNCTION("""COMPUTED_VALUE"""),"DT:000958") -> DT:000958 | N8: =IFERROR(__xludf.DUMMYFUNCTION("""COMPUTED_VALUE"""),1.0) -> 1 | O8: =IFERROR(__xludf.DUMMYFUNCTION("""COMPUTED_VALUE"""),27600.0) -> 27600 | P8: =SUMIF(M:M,M8,O:O) -> 62400
A9: 350ml Orisirisi Wallnut with Ginger Drink (12x) | B9: 46072 | C9: Buymore Supermarket, ISHERI | D9: Sales | E9: DT:001044 | F9: 1 | G9: 21600 | I9: =IFERROR(__xludf.DUMMYFUNCTION("""COMPUTED_VALUE"""),"500ml Orisirisi Tiger Nut Drink (12x)") -> 500ml Orisirisi Tiger Nut Drink (12x) | J9: =IFERROR(__xludf.DUMMYFUNCTION("""COMPUTED_VALUE"""),46069.0) -> 46069 | K9: =IFERROR(__xludf.DUMMYFUNCTION("""COMPUTED_VALUE"""),"Jendol Supermarket, IJEDE") -> Jendol Supermarket, IJEDE | L9: =IFERROR(__xludf.DUMMYFUNCTION("""COMPUTED_VALUE"""),"Sales") -> Sales | M9: =IFERROR(__xludf.DUMMYFUNCTION("""COMPUTED_VALUE"""),"DT:000959") -> DT:000959 | N9: =IFERROR(__xludf.DUMMYFUNCTION("""COMPUTED_VALUE"""),1.0) -> 1 | O9: =IFERROR(__xludf.DUMMYFUNCTION("""COMPUTED_VALUE"""),27600.0) -> 27600 | P9: =SUMIF(M:M,M9,O:O) -> 27600
A10: 500ml Orisirisi Tiger Nut Drink (12x) | B10: 46066 | C10: Individual | D10: Sales | E10: DT:000885 | F10: 0.25 | G10: 6900 | I10: =IFERROR(__xludf.DUMMYFUNCTION("""COMPUTED_VALUE"""),"500ml Orisirisi Tiger Nut Drink (12x)") -> 500ml Orisirisi Tiger Nut Drink (12x) | J10: =IFERROR(__xludf.DUMMYFUNCTION("""COMPUTED_VALUE"""),46071.0) -> 46071 | K10: =IFERROR(__xludf.DUMMYFUNCTION("""COMPUTED_VALUE"""),"Renees Supermarket, LEKKI CENTRAL MOSQUE") -> Renees Supermarket, LEKKI CENTRAL MOSQUE | L10: =IFERROR(__xludf.DUMMYFUNCTION("""COMPUTED_VALUE"""),"Sales") -> Sales | M10: =IFERROR(__xludf.DUMMYFUNCTION("""COMPUTED_VALUE"""),"DT:000973") -> DT:000973 | N10: =IFERROR(__xludf.DUMMYFUNCTION("""COMPUTED_VALUE"""),1.0) -> 1 | O10: =IFERROR(__xludf.DUMMYFUNCTION("""COMPUTED_VALUE"""),27600.0) -> 27600 | P10: =SUMIF(M:M,M10,O:O) -> 27600
A11: 500ml Orisirisi Tiger Nut Drink (12x) | B11: 46066 | C11: Alvira Mart | D11: Sales | E11: DT:000910 | F11: 1 | G11: 27600 | I11: =IFERROR(__xludf.DUMMYFUNCTION("""COMPUTED_VALUE"""),"500ml Orisirisi Tiger Nut Drink (12x)") -> 500ml Orisirisi Tiger Nut Drink (12x) | J11: =IFERROR(__xludf.DUMMYFUNCTION("""COMPUTED_VALUE"""),46071.0) -> 46071 | K11: =IFERROR(__xludf.DUMMYFUNCTION("""COMPUTED_VALUE"""),"Value Village Superstore") -> Value Village Superstore | L11: =IFERROR(__xludf.DUMMYFUNCTION("""COMPUTED_VALUE"""),"Sales") -> Sales | M11: =IFERROR(__xludf.DUMMYFUNCTION("""COMPUTED_VALUE"""),"DT:000983") -> DT:000983 | N11: =IFERROR(__xludf.DUMMYFUNCTION("""COMPUTED_VALUE"""),1.0) -> 1 | O11: =IFERROR(__xludf.DUMMYFUNCTION("""COMPUTED_VALUE"""),27600.0) -> 27600 | P11: =SUMIF(M:M,M11,O:O) -> 27600
A12: 500ml Orisirisi Tiger Nut Drink (12x) | B12: 46069 | C12: CMART Supermarket, ONIRU | D12: Sales | E12: DT:000938 | F12: 0.5 | G12: 13800 | I12: =IFERROR(__xludf.DUMMYFUNCTION("""COMPUTED_VALUE"""),"500ml Orisirisi Zobo Drink (12x)") -> 500ml Orisirisi Zobo Drink (12x) | J12: =IFERROR(__xludf.DUMMYFUNCTION("""COMPUTED_VALUE"""),46069.0) -> 46069 | K12: =IFERROR(__xludf.DUMMYFUNCTION("""COMPUTED_VALUE"""),"CMART Supermarket, ONIRU") -> CMART Supermarket, ONIRU | L12: =IFERROR(__xludf.DUMMYFUNCTION("""COMPUTED_VALUE"""),"Sales") -> Sales | M12: =IFERROR(__xludf.DUMMYFUNCTION("""COMPUTED_VALUE"""),"DT:000938") -> DT:000938 | N12: =IFERROR(__xludf.DUMMYFUNCTION("""COMPUTED_VALUE"""),0.5) -> 0.5 | O12: =IFERROR(__xludf.DUMMYFUNCTION("""COMPUTED_VALUE"""),12000.0) -> 12000 | P12: =SUMIF(M:M,M12,O:O) -> 37800
A13: 500ml Orisirisi Tiger Nut Drink (12x) | B13: 46069 | C13: Jendol Supermarket, AKASOLORI | D13: Sales | E13: DT:000958 | F13: 1 | G13: 27600 | I13: =IFERROR(__xludf.DUMMYFUNCTION("""COMPUTED_VALUE"""),"500ml Orisirisi Zobo Drink (12x)") -> 500ml Orisirisi Zobo Drink (12x) | J13: =IFERROR(__xludf.DUMMYFUNCTION("""COMPUTED_VALUE"""),46071.0) -> 46071 | K13: =IFERROR(__xludf.DUMMYFUNCTION("""COMPUTED_VALUE"""),"Compramart Supermarket, MOBILE Rd.") -> Compramart Supermarket, MOBILE Rd. | L13: =IFERROR(__xludf.DUMMYFUNCTION("""COMPUTED_VALUE"""),"Sales") -> Sales | M13: =IFERROR(__xludf.DUMMYFUNCTION("""COMPUTED_VALUE"""),"DT:001056") -> DT:001056 | N13: =IFERROR(__xludf.DUMMYFUNCTION("""COMPUTED_VALUE"""),0.5) -> 0.5 | O13: =IFERROR(__xludf.DUMMYFUNCTION("""COMPUTED_VALUE"""),12000.0) -> 12000 | P13: =SUMIF(M:M,M13,O:O) -> 24000
A14: 500ml Orisirisi Tiger Nut Drink (12x) | B14: 46069 | C14: Jendol Supermarket, IJEDE | D14: Sales | E14: DT:000959 | F14: 1 | G14: 27600 | I14: =IFERROR(__xludf.DUMMYFUNCTION("""COMPUTED_VALUE"""),"500ml Orisirisi Zobo with Date Drink (12x)") -> 500ml Orisirisi Zobo with Date Drink (12x) | J14: =IFERROR(__xludf.DUMMYFUNCTION("""COMPUTED_VALUE"""),46066.0) -> 46066 | K14: =IFERROR(__xludf.DUMMYFUNCTION("""COMPUTED_VALUE"""),"Alvira Mart") -> Alvira Mart | L14: =IFERROR(__xludf.DUMMYFUNCTION("""COMPUTED_VALUE"""),"Sales") -> Sales | M14: =IFERROR(__xludf.DUMMYFUNCTION("""COMPUTED_VALUE"""),"DT:000910") -> DT:000910 | N14: =IFERROR(__xludf.DUMMYFUNCTION("""COMPUTED_VALUE"""),1.0) -> 1 | O14: =IFERROR(__xludf.DUMMYFUNCTION("""COMPUTED_VALUE"""),24000.0) -> 24000 | P14: =SUMIF(M:M,M14,O:O) -> 51600
A15: 500ml Orisirisi Tiger Nut Drink (12x) | B15: 46071 | C15: Renees Supermarket, LEKKI CENTRAL MOSQUE | D15: Sales | E15: DT:000973 | F15: 1 | G15: 27600 | I15: =IFERROR(__xludf.DUMMYFUNCTION("""COMPUTED_VALUE"""),"500ml Orisirisi Zobo with Date Drink (12x)") -> 500ml Orisirisi Zobo with Date Drink (12x) | J15: =IFERROR(__xludf.DUMMYFUNCTION("""COMPUTED_VALUE"""),46069.0) -> 46069 | K15: =IFERROR(__xludf.DUMMYFUNCTION("""COMPUTED_VALUE"""),"CMART Supermarket, ONIRU") -> CMART Supermarket, ONIRU | L15: =IFERROR(__xludf.DUMMYFUNCTION("""COMPUTED_VALUE"""),"Sales") -> Sales | M15: =IFERROR(__xludf.DUMMYFUNCTION("""COMPUTED_VALUE"""),"DT:000938") -> DT:000938 | N15: =IFERROR(__xludf.DUMMYFUNCTION("""COMPUTED_VALUE"""),0.5) -> 0.5 | O15: =IFERROR(__xludf.DUMMYFUNCTION("""COMPUTED_VALUE"""),12000.0) -> 12000 | P15: =SUMIF(M:M,M15,O:O) -> 37800
A16: 500ml Orisirisi Tiger Nut Drink (12x) | B16: 46071 | C16: Value Village Superstore | D16: Sales | E16: DT:000983 | F16: 1 | G16: 27600 | I16: =IFERROR(__xludf.DUMMYFUNCTION("""COMPUTED_VALUE"""),"500ml Orisirisi Zobo with Date Drink (12x)") -> 500ml Orisirisi Zobo with Date Drink (12x) | J16: =IFERROR(__xludf.DUMMYFUNCTION("""COMPUTED_VALUE"""),46069.0) -> 46069 | K16: =IFERROR(__xludf.DUMMYFUNCTION("""COMPUTED_VALUE"""),"Jendol Supermarket, AKASOLORI") -> Jendol Supermarket, AKASOLORI | L16: =IFERROR(__xludf.DUMMYFUNCTION("""COMPUTED_VALUE"""),"Sales") -> Sales | M16: =IFERROR(__xludf.DUMMYFUNCTION("""COMPUTED_VALUE"""),"DT:000958") -> DT:000958 | N16: =IFERROR(__xludf.DUMMYFUNCTION("""COMPUTED_VALUE"""),1.0) -> 1 | O16: =IFERROR(__xludf.DUMMYFUNCTION("""COMPUTED_VALUE"""),24000.0) -> 24000 | P16: =SUMIF(M:M,M16,O:O) -> 62400
A17: 500ml Orisirisi Zobo Drink (12x) | B17: 46069 | C17: CMART Supermarket, ONIRU | D17: Sales | E17: DT:000938 | F17: 0.5 | G17: 12000 | I17: =IFERROR(__xludf.DUMMYFUNCTION("""COMPUTED_VALUE"""),"500ml Orisirisi Zobo with Date Drink (12x)") -> 500ml Orisirisi Zobo with Date Drink (12x) | J17: =IFERROR(__xludf.DUMMYFUNCTION("""COMPUTED_VALUE"""),46071.0) -> 46071 | K17: =IFERROR(__xludf.DUMMYFUNCTION("""COMPUTED_VALUE"""),"Compramart Supermarket, MOBILE Rd.") -> Compramart Supermarket, MOBILE Rd. | L17: =IFERROR(__xludf.DUMMYFUNCTION("""COMPUTED_VALUE"""),"Sales") -> Sales | M17: =IFERROR(__xludf.DUMMYFUNCTION("""COMPUTED_VALUE"""),"DT:001056") -> DT:001056 | N17: =IFERROR(__xludf.DUMMYFUNCTION("""COMPUTED_VALUE"""),0.5) -> 0.5 | O17: =IFERROR(__xludf.DUMMYFUNCTION("""COMPUTED_VALUE"""),12000.0) -> 12000 | P17: =SUMIF(M:M,M17,O:O) -> 24000
A18: 500ml Orisirisi Zobo Drink (12x) | B18: 46071 | C18: Compramart Supermarket, MOBILE Rd. | D18: Sales | E18: DT:001056 | F18: 0.5 | G18: 12000 | P18: =SUMIF(M:M,M18,O:O) -> 0
A19: 500ml Orisirisi Zobo with Date Drink (12x) | B19: 46066 | C19: Alvira Mart | D19: Sales | E19: DT:000910 | F19: 1 | G19: 24000 | P19: =SUMIF(M:M,M19,O:O) -> 0
A20: 500ml Orisirisi Zobo with Date Drink (12x) | B20: 46069 | C20: CMART Supermarket, ONIRU | D20: Sales | E20: DT:000938 | F20: 0.5 | G20: 12000 | P20: =SUMIF(M:M,M20,O:O) -> 0
A21: 500ml Orisirisi Zobo with Date Drink (12x) | B21: 46069 | C21: Jendol Supermarket, AKASOLORI | D21: Sales | E21: DT:000958 | F21: 1 | G21: 24000 | P21: =SUMIF(M:M,M21,O:O) -> 0
A22: 500ml Orisirisi Zobo with Date Drink (12x) | B22: 46071 | C22: Compramart Supermarket, MOBILE Rd. | D22: Sales | E22: DT:001056 | F22: 0.5 | G22: 12000 | P22: =SUMIF(M:M,M22,O:O) -> 0
P23: =SUMIF(M:M,M23,O:O) -> 0
P24: =SUMIF(M:M,M24,O:O) -> 0
P25: =SUMIF(M:M,M25,O:O) -> 0
P26: =SUMIF(M:M,M26,O:O) -> 0
P27: =SUMIF(M:M,M27,O:O) -> 0
P28: =SUMIF(M:M,M28,O:O) -> 0
P29: =SUMIF(M:M,M29,O:O) -> 0
P30: =SUMIF(M:M,M30,O:O) -> 0
P31: =SUMIF(M:M,M31,O:O) -> 0
P32: =SUMIF(M:M,M32,O:O) -> 0
P33: =SUMIF(M:M,M33,O:O) -> 0
P34: =SUMIF(M:M,M34,O:O) -> 0
... P277: =SUMIF(M:M,M277,O:O) -> 0
T975: {=counta(UNIQUE(S2:S960))-1} -> 0 | AI975: {=UNIQUE(AI2:AI590)} -> Particulars | AQ975: {=UNIQUE(AQ2:AQ590)} -> Particulars
AI976: Orisirisi Catring Service

Sheet Payment Advice
F2: =sum(D:D) -> 287100

Sheet Dala Sales & Deliveries
H1: Total Invoices Delivered | I1: =countifs(B:B,"<>",F:F,"<>")-1 -> 9 | K1: Sku Performance | L1: Units | M1: Value
H2: Unique Locations Supplied | I2: {=(COUNTA(UNIQUE(C:C))-1)} -> 9 | K2: ='Internal Summary'!B40 -> 350ml Orisirisi Wallnut Drink (12x) | L2: =sumif(D:D,K2,E:E) -> 0 | M2: =sumif(D:D,K2,F:F) -> 0
H3: Total Value of orders | I3: =sum(F:F) -> 287100 | K3: ='Internal Summary'!B41 -> 350ml Orisirisi Wallnut with Ginger Drink (12x) | L3: =sumif(D:D,K3,E:E) -> 1.5 | M3: =sumif(D:D,K3,F:F) -> 32400
K4: ='Internal Summary'!B42 -> 500ml Orisirisi Tiger Nut Drink (12x) | L4: =sumif(D:D,K4,E:E) -> 5.75 | M4: =sumif(D:D,K4,F:F) -> 158700
K5: ='Internal Summary'!B43 -> 500ml Orisirisi Zobo Drink (12x) | L5: =sumif(D:D,K5,E:E) -> 1 | M5: =sumif(D:D,K5,F:F) -> 24000
K6: ='Internal Summary'!B44 -> 500ml Orisirisi Zobo with Date Drink (12x) | L6: =sumif(D:D,K6,E:E) -> 3 | M6: =sumif(D:D,K6,F:F) -> 72000
K7: ='Internal Summary'!B45 | L7: =sumif(D:D,K7,E:E) -> 0 | M7: =sumif(D:D,K7,F:F) -> 0
K8: ='Internal Summary'!B46 | L8: =sumif(D:D,K8,E:E) -> 0 | M8: =sumif(D:D,K8,F:F) -> 0
K9: ='Internal Summary'!B47 | L9: =sumif(D:D,K9,E:E) -> 0 | M9: =sumif(D:D,K9,F:F) -> 0
K10: ='Internal Summary'!B48 | L10: =sumif(D:D,K10,E:E) -> 0 | M10: =sumif(D:D,K10,F:F) -> 0
K11: ='Internal Summary'!B49 | L11: =sumif(D:D,K11,E:E) -> 0 | M11: =sumif(D:D,K11,F:F) -> 0
K12: ='Internal Summary'!B50 | L12: =sumif(D:D,K12,E:E) -> 0 | M12: =sumif(D:D,K12,F:F) -> 0
K13: ='Internal Summary'!B51 | L13: =sumif(D:D,K13,E:E) -> 0 | M13: =sumif(D:D,K13,F:F) -> 0

Sheet External Delivery Fulfillment
H1: Total Invoices Delivered | I1: =countifs(B:B,"<>",F:F,"<>")-1 -> 0 | K1: Sku Performance | L1: Units | M1: Value
H2: Unique Locations Supplied | I2: {=(COUNTA(UNIQUE(C:C))-1)} -> 0 | K2: ='Internal Summary'!B40 -> 350ml Orisirisi Wallnut Drink (12x) | L2: =sumif(D:D,K2,E:E) -> 0 | M2: =sumif(D:D,K2,F:F) -> 0
H3: Total Value of orders | I3: =sum(F:F) -> 0 | K3: ='Internal Summary'!B41 -> 350ml Orisirisi Wallnut with Ginger Drink (12x) | L3: =sumif(D:D,K3,E:E) -> 0 | M3: =sumif(D:D,K3,F:F) -> 0
K4: ='Internal Summary'!B42 -> 500ml Orisirisi Tiger Nut Drink (12x) | L4: =sumif(D:D,K4,E:E) -> 0 | M4: =sumif(D:D,K4,F:F) -> 0
K5: ='Internal Summary'!B43 -> 500ml Orisirisi Zobo Drink (12x) | L5: =sumif(D:D,K5,E:E) -> 0 | M5: =sumif(D:D,K5,F:F) -> 0
K6: ='Internal Summary'!B44 -> 500ml Orisirisi Zobo with Date Drink (12x) | L6: =sumif(D:D,K6,E:E) -> 0 | M6: =sumif(D:D,K6,F:F) -> 0
K7: ='Internal Summary'!B45 | L7: =sumif(D:D,K7,E:E) -> 0 | M7: =sumif(D:D,K7,F:F) -> 0
K8: ='Internal Summary'!B46 | L8: =sumif(D:D,K8,E:E) -> 0 | M8: =sumif(D:D,K8,F:F) -> 0
K9: ='Internal Summary'!B47 | L9: =sumif(D:D,K9,E:E) -> 0 | M9: =sumif(D:D,K9,F:F) -> 0
K10: ='Internal Summary'!B48 | L10: =sumif(D:D,K10,E:E) -> 0 | M10: =sumif(D:D,K10,F:F) -> 0
K11: ='Internal Summary'!B49 | L11: =sumif(D:D,K11,E:E) -> 0 | M11: =sumif(D:D,K11,F:F) -> 0
K12: ='Internal Summary'!B50 | L12: =sumif(D:D,K12,E:E) -> 0 | M12: =sumif(D:D,K12,F:F) -> 0
K13: ='Internal Summary'!B51 | L13: =sumif(D:D,K13,E:E) -> 0 | M13: =sumif(D:D,K13,F:F) -> 0

Sheet Forwarding From Client
H1: Total Invoices Delivered | I1: =countifs(B:B,"<>",F:F,"<>")-1 -> 0 | K1: Sku Performance | L1: Units | M1: Value
H2: Unique Locations Supplied | I2: {=(COUNTA(UNIQUE(C:C))-1)} -> 0 | K2: ='Internal Summary'!B40 -> 350ml Orisirisi Wallnut Drink (12x) | L2: =sumif(D:D,K2,E:E) -> 0 | M2: =sumif(D:D,K2,F:F) -> 0
H3: Total Value of orders | I3: =sum(F:F) -> 0 | K3: ='Internal Summary'!B41 -> 350ml Orisirisi Wallnut with Ginger Drink (12x) | L3: =sumif(D:D,K3,E:E) -> 0 | M3: =sumif(D:D,K3,F:F) -> 0
K4: ='Internal Summary'!B42 -> 500ml Orisirisi Tiger Nut Drink (12x) | L4: =sumif(D:D,K4,E:E) -> 0 | M4: =sumif(D:D,K4,F:F) -> 0
K5: ='Internal Summary'!B43 -> 500ml Orisirisi Zobo Drink (12x) | L5: =sumif(D:D,K5,E:E) -> 0 | M5: =sumif(D:D,K5,F:F) -> 0
K6: ='Internal Summary'!B44 -> 500ml Orisirisi Zobo with Date Drink (12x) | L6: =sumif(D:D,K6,E:E) -> 0 | M6: =sumif(D:D,K6,F:F) -> 0
K7: ='Internal Summary'!B45 | L7: =sumif(D:D,K7,E:E) -> 0 | M7: =sumif(D:D,K7,F:F) -> 0
K8: ='Internal Summary'!B46 | L8: =sumif(D:D,K8,E:E) -> 0 | M8: =sumif(D:D,K8,F:F) -> 0
K9: ='Internal Summary'!B47 | L9: =sumif(D:D,K9,E:E) -> 0 | M9: =sumif(D:D,K9,F:F) -> 0
K10: ='Internal Summary'!B48 | L10: =sumif(D:D,K10,E:E) -> 0 | M10: =sumif(D:D,K10,F:F) -> 0
K11: ='Internal Summary'!B49 | L11: =sumif(D:D,K11,E:E) -> 0 | M11: =sumif(D:D,K11,F:F) -> 0
K12: ='Internal Summary'!B50 | L12: =sumif(D:D,K12,E:E) -> 0 | M12: =sumif(D:D,K12,F:F) -> 0
K13: ='Internal Summary'!B51 | L13: =sumif(D:D,K13,E:E) -> 0 | M13: =sumif(D:D,K13,F:F) -> 0

Sheet Dala Restocking
H1: Total Invoices Delivered | I1: =countifs(B:B,"<>",F:F,"<>")-1 -> 0 | K1: Sku Performance | L1: Units
H2: Unique Locations Supplied | I2: {=(COUNTA(UNIQUE(C:C,,0))-1)} -> 0 | K2: ='Internal Summary'!B40 -> 350ml Orisirisi Wallnut Drink (12x) | L2: =sumif(D:D,K2,E:E) -> 0
H3: Total Value of orders | I3: =sum(F:F) -> 0 | K3: ='Internal Summary'!B41 -> 350ml Orisirisi Wallnut with Ginger Drink (12x) | L3: =sumif(D:D,K3,E:E) -> 0
K4: ='Internal Summary'!B42 -> 500ml Orisirisi Tiger Nut Drink (12x) | L4: =sumif(D:D,K4,E:E) -> 0
K5: ='Internal Summary'!B43 -> 500ml Orisirisi Zobo Drink (12x) | L5: =sumif(D:D,K5,E:E) -> 0
K6: ='Internal Summary'!B44 -> 500ml Orisirisi Zobo with Date Drink (12x) | L6: =sumif(D:D,K6,E:E) -> 0
K7: ='Internal Summary'!B45 | L7: =sumif(D:D,K7,E:E) -> 0
K8: ='Internal Summary'!B46 | L8: =sumif(D:D,K8,E:E) -> 0
K9: ='Internal Summary'!B47 | L9: =sumif(D:D,K9,E:E) -> 0
K10: ='Internal Summary'!B48 | L10: =sumif(D:D,K10,E:E) -> 0
K11: ='Internal Summary'!B49 | L11: =sumif(D:D,K11,E:E) -> 0
K12: ='Internal Summary'!B50 | L12: =sumif(D:D,K12,E:E) -> 0
K13: ='Internal Summary'!B51 | L13: =sumif(D:D,K13,E:E) -> 0

Sheet Client Restocking
H1: Total Invoices Delivered | I1: =countifs(B:B,"<>",F:F,"<>")-1 -> 1 | K1: Sku Performance | L1: Units
H2: Unique Locations Supplied | I2: {=(COUNTA(UNIQUE(C:C,,0))-1)} -> 1 | K2: ='Internal Summary'!B40 -> 350ml Orisirisi Wallnut Drink (12x) | L2: =sumif(D:D,K2,E:E) -> 1.75
H3: Total Value of orders | I3: =sum(F:F) -> 820200 | K3: ='Internal Summary'!B41 -> 350ml Orisirisi Wallnut with Ginger Drink (12x) | L3: =sumif(D:D,K3,E:E) -> 6
K4: ='Internal Summary'!B42 -> 500ml Orisirisi Tiger Nut Drink (12x) | L4: =sumif(D:D,K4,E:E) -> 8
K5: ='Internal Summary'!B43 -> 500ml Orisirisi Zobo Drink (12x) | L5: =sumif(D:D,K5,E:E) -> 9
K6: ='Internal Summary'!B44 -> 500ml Orisirisi Zobo with Date Drink (12x) | L6: =sumif(D:D,K6,E:E) -> 9
K7: ='Internal Summary'!B45 | L7: =sumif(D:D,K7,E:E) -> 0
K8: ='Internal Summary'!B46 | L8: =sumif(D:D,K8,E:E) -> 0
K9: ='Internal Summary'!B47 | L9: =sumif(D:D,K9,E:E) -> 0
K10: ='Internal Summary'!B48 | L10: =sumif(D:D,K10,E:E) -> 0
K11: ='Internal Summary'!B49 | L11: =sumif(D:D,K11,E:E) -> 0
K12: ='Internal Summary'!B50 | L12: =sumif(D:D,K12,E:E) -> 0
K13: ='Internal Summary'!B51 | L13: =sumif(D:D,K13,E:E) -> 0

Sheet Internal Summary
B1: Description | C1: Units | D1: measurements | E1: total
A2: SALES | B2: Total Invoices Delivered | E2: ='Dala Sales & Deliveries'!I1+'External Delivery Fulfillment'!I1 -> 9
B3: Unique Locations Delivered To | E3: ='Raw Data'!AW2 -> 9
B4: Value of Dala Deliveries | E4: ='Dala Sales & Deliveries'!I3 -> 287100
B5: Value of External Deliveries | E5: ='External Delivery Fulfillment'!I3 -> 0
B6: VAT on sales | E6: 0
B7: Total Value of Deliveries | E7: =sum(E4:E6) -> 287100
A8: Remittance & Deductions | B8: Total Remitted to Partner
B9: Collection Fees | C9: 0.1 | E9: =E8*(C9+100%)-E8 -> 0
A10: Invoice Value Due | B10: Outstanding Paymets For Sales | E10: =E7-E8-E9 -> 287100
A11: Debts | B11: Unpaid Subscription | C11: 0 | D11: 0 | E11: =C11*D11 -> 0
B12: Collection Fees | E12: =E7*C9 -> 28710
B13: Delivery Fees | E13: =C26 -> 8613
B14: Delivery Fees External & Pickup | D14: Table 1 | E14: =C29+C22 -> 0 | F14: free
B15: Reimbursements Due To DALA | E15: 0
B16: Retailer Deductions (EXPIRY) | E16: =C31 -> 0
B17: Total Deductions | E17: =sum(E11:E16) -> 37323
A18: Remmittance Due | B18: Total Balance to Remitt | E18: =E10-E17 -> 249777
A20: Inventory and Operational Fees
B21: Dala Pickup for Warehouse | C21: =U69 -> 0
B22: Warehouse Delivery Fee | C22: ='Dala Restocking'!I3*3% -> 0
B23: Forwarding to Retail | C23: =S69 -> 0
B24: Forwarding Delivery Fee | C24: =T69 -> 0
B25: Dala Sales | C25: 0
B26: Dala Delivery Fees | C26: =E7*3% -> 8613
B27: Exteranl Deliveries | C27: =Q69 -> 0
B28: External Delivery Fees | C28: ='External Delivery Fulfillment'!I3*3% -> 0
B29: Product Defects and Expirey Issues | C29: =F69 -> 0
B30: Deductions From Retailer | C30: 0
B31: Samples used | C31: =I69 -> 0
B32: Produce Replacements | C32: 0
B33: Expected Closing Inventory | C33: =L69 -> 24.58
B34: Physical Stock count | C34: =K69 -> 8.5
B35: Inventory Shortages | C35: 0
B36: Inventory Shortage Costs | C36: 0
B39: SKUs | C39: Retail Value | D39: Inbound Delivery Fee | E39: Outbound Delivery Fee | F39: Defects/Expirey | G39: Deductions | H39: Opening Inventory | I39: Samples Used | J39: Product Replacements | K39: Physical Closing Stock Count | L39: Expected Closing Inventory | M39: Inventory Shortages | N39: Shortages Costs | O39: Dala Deliveries | P39: Retail Sales Fee | Q39: External Delivery | R39: External Delivery Fee | S39: Forwarding from Client | T39: Forwarding Delivery Fee | U39: Dala Restocking | V39: Dala Restocking Fee | W39: Client Restocking
B40: 350ml Orisirisi Wallnut Drink (12x) | C40: 21600 | G40: =F40*C40 -> 0 | K40: 3.75 | L40: 3.75 | M40: =K40-L40 -> 0 | N40: =M40*C40 -> 0 | O40: ='Dala Sales & Deliveries'!L2 -> 0 | P40: =O40*E40 -> 0 | Q40: ='External Delivery Fulfillment'!L2 -> 0 | R40: =Q40*E40 -> 0 | S40: ='Forwarding From Client'!L2 -> 0 | T40: =S40*E40 -> 0 | U40: ='Dala Restocking'!L2 -> 0 | V40: =U40*D40 -> 0 | W40: ='Client Restocking'!L2 -> 1.75
B41: 350ml Orisirisi Wallnut with Ginger Drink (12x) | C41: 21600 | G41: =F41*C41 -> 0 | K41: 3.25 | L41: 7 | M41: =K41-L41 -> -3.75 | N41: =M41*C41 -> -81000 | O41: ='Dala Sales & Deliveries'!L3 -> 1.5 | P41: =O41*E41 -> 0 | Q41: ='External Delivery Fulfillment'!L3 -> 0 | R41: =Q41*E41 -> 0 | S41: ='Forwarding From Client'!L3 -> 0 | T41: =S41*E41 -> 0 | U41: ='Dala Restocking'!L3 -> 0 | V41: =U41*D41 -> 0 | W41: ='Client Restocking'!L3 -> 6
B42: 500ml Orisirisi Tiger Nut Drink (12x) | C42: 27600 | G42: =F42*C42 -> 0 | K42: 0.25 | L42: 5.67 | M42: =K42-L42 -> -5.42 | N42: =M42*C42 -> -149592 | O42: ='Dala Sales & Deliveries'!L4 -> 5.75 | P42: =O42*E42 -> 0 | Q42: ='External Delivery Fulfillment'!L4 -> 0 | R42: =Q42*E42 -> 0 | S42: ='Forwarding From Client'!L4 -> 0 | T42: =S42*E42 -> 0 | U42: ='Dala Restocking'!L4 -> 0 | V42: =U42*D42 -> 0 | W42: ='Client Restocking'!L4 -> 8
B43: 500ml Orisirisi Zobo Drink (12x) | C43: 24000 | G43: =F43*C43 -> 0 | K43: 1 | L43: 5.08 | M43: =K43-L43 -> -4.08 | N43: =M43*C43 -> -97920 | O43: ='Dala Sales & Deliveries'!L5 -> 1 | P43: =O43*E43 -> 0 | Q43: ='External Delivery Fulfillment'!L5 -> 0 | R43: =Q43*E43 -> 0 | S43: ='Forwarding From Client'!L5 -> 0 | T43: =S43*E43 -> 0 | U43: ='Dala Restocking'!L5 -> 0 | V43: =U43*D43 -> 0 | W43: ='Client Restocking'!L5 -> 9
B44: 500ml Orisirisi Zobo with Date Drink (12x) | C44: 24000 | G44: =F44*C44 -> 0 | K44: 0.25 | L44: 3.08 | M44: =K44-L44 -> -2.83 | N44: =M44*C44 -> -67920 | O44: ='Dala Sales & Deliveries'!L6 -> 3 | P44: =O44*E44 -> 0 | Q44: ='External Delivery Fulfillment'!L6 -> 0 | R44: =Q44*E44 -> 0 | S44: ='Forwarding From Client'!L6 -> 0 | T44: =S44*E44 -> 0 | U44: ='Dala Restocking'!L6 -> 0 | V44: =U44*D44 -> 0 | W44: ='Client Restocking'!L6 -> 9
G45: =F45*C45 -> 0 | M45: =K45-L45 -> 0 | N45: =M45*C45 -> 0 | O45: ='Dala Sales & Deliveries'!L7 -> 0 | P45: =O45*E45 -> 0 | Q45: ='External Delivery Fulfillment'!L7 -> 0 | R45: =Q45*E45 -> 0 | S45: ='Forwarding From Client'!L7 -> 0 | T45: =S45*E45 -> 0 | U45: ='Dala Restocking'!L7 -> 0 | V45: =U45*D45 -> 0 | W45: ='Client Restocking'!L7 -> 0
G46: =F46*C46 -> 0 | L46: =H46+U46+W46-O46-Q46-I46-J46 -> 0 | M46: =K46-L46 -> 0 | N46: =M46*C46 -> 0 | O46: ='Dala Sales & Deliveries'!L8 -> 0 | P46: =O46*E46 -> 0 | Q46: ='External Delivery Fulfillment'!L8 -> 0 | R46: =Q46*E46 -> 0 | S46: ='Forwarding From Client'!L8 -> 0 | T46: =S46*E46 -> 0 | U46: ='Dala Restocking'!L8 -> 0 | V46: =U46*D46 -> 0 | W46: ='Client Restocking'!L8 -> 0
G47: =F47*C47 -> 0 | L47: =H47+U47+W47-O47-Q47-I47-J47 -> 0 | M47: =K47-L47 -> 0 | N47: =M47*C47 -> 0 | O47: ='Dala Sales & Deliveries'!L9 -> 0 | P47: =O47*E47 -> 0 | Q47: ='External Delivery Fulfillment'!L9 -> 0 | R47: =Q47*E47 -> 0 | S47: ='Forwarding From Client'!L9 -> 0 | T47: =S47*E47 -> 0 | U47: ='Dala Restocking'!L9 -> 0 | V47: =U47*D47 -> 0 | W47: ='Client Restocking'!L9 -> 0
G48: =F48*C48 -> 0 | L48: =H48+U48+W48-O48-Q48-I48-J48 -> 0 | M48: =K48-L48 -> 0 | N48: =M48*C48 -> 0 | O48: ='Dala Sales & Deliveries'!L10 -> 0 | P48: =O48*E48 -> 0 | Q48: ='External Delivery Fulfillment'!L10 -> 0 | R48: =Q48*E48 -> 0 | S48: ='Forwarding From Client'!L10 -> 0 | T48: =S48*E48 -> 0 | U48: ='Dala Restocking'!L10 -> 0 | V48: =U48*D48 -> 0 | W48: ='Client Restocking'!L10 -> 0
G49: =F49*C49 -> 0 | L49: =H49+U49+W49-O49-Q49-I49-J49 -> 0 | M49: =K49-L49 -> 0 | N49: =M49*C49 -> 0 | O49: ='Dala Sales & Deliveries'!L11 -> 0 | P49: =O49*E49 -> 0 | Q49: ='External Delivery Fulfillment'!L11 -> 0 | R49: =Q49*E49 -> 0 | S49: ='Forwarding From Client'!L11 -> 0 | T49: =S49*E49 -> 0 | U49: ='Dala Restocking'!L11 -> 0 | V49: =U49*D49 -> 0 | W49: ='Client Restocking'!L11 -> 0
G50: =F50*C50 -> 0 | L50: =H50+U50+W50-O50-Q50-I50-J50 -> 0 | M50: =K50-L50 -> 0 | N50: =M50*C50 -> 0 | O50: ='Dala Sales & Deliveries'!L12 -> 0 | P50: =O50*E50 -> 0 | Q50: ='External Delivery Fulfillment'!L12 -> 0 | R50: =Q50*E50 -> 0 | S50: ='Forwarding From Client'!L12 -> 0 | T50: =S50*E50 -> 0 | U50: ='Dala Restocking'!L12 -> 0 | V50: =U50*D50 -> 0 | W50: ='Client Restocking'!L12 -> 0
G51: =F51*C51 -> 0 | L51: =H51+U51+W51-O51-Q51-I51-J51 -> 0 | M51: =K51-L51 -> 0 | N51: =M51*C51 -> 0 | O51: ='Dala Sales & Deliveries'!L13 -> 0 | P51: =O51*E51 -> 0 | Q51: ='External Delivery Fulfillment'!L13 -> 0 | R51: =Q51*E51 -> 0 | S51: ='Forwarding From Client'!L13 -> 0 | T51: =S51*E51 -> 0 | U51: ='Dala Restocking'!L13 -> 0 | V51: =U51*D51 -> 0 | W51: ='Client Restocking'!L13 -> 0
G52: =F52*C52 -> 0 | L52: =H52+U52+W52-O52-Q52-I52-J52 -> 0 | M52: =K52-L52 -> 0 | N52: =M52*C52 -> 0 | O52: ='Dala Sales & Deliveries'!L14 | P52: =O52*E52 -> 0 | Q52: ='External Delivery Fulfillment'!L14 | R52: =Q52*E52 -> 0 | S52: ='Forwarding From Client'!L14 | T52: =S52*E52 -> 0 | U52: ='Dala Restocking'!L14 | V52: =U52*D52 -> 0 | W52: ='Client Restocking'!L14
G53: =F53*C53 -> 0 | L53: =H53+U53+W53-O53-Q53-I53-J53 -> 0 | M53: =K53-L53 -> 0 | N53: =M53*C53 -> 0 | O53: ='Dala Sales & Deliveries'!L15 | P53: =O53*E53 -> 0 | Q53: ='External Delivery Fulfillment'!L15 | R53: =Q53*E53 -> 0 | S53: ='Forwarding From Client'!L15 | T53: =S53*E53 -> 0 | U53: ='Dala Restocking'!L15 | V53: =U53*D53 -> 0 | W53: ='Client Restocking'!L15
G54: =F54*C54 -> 0 | L54: =H54+U54+W54-O54-Q54-I54-J54 -> 0 | M54: =K54-L54 -> 0 | N54: =M54*C54 -> 0 | O54: ='Dala Sales & Deliveries'!L16 | P54: =O54*E54 -> 0 | Q54: ='External Delivery Fulfillment'!L16 | R54: =Q54*E54 -> 0 | S54: ='Forwarding From Client'!L16 | T54: =S54*E54 -> 0 | U54: ='Dala Restocking'!L16 | V54: =U54*D54 -> 0 | W54: ='Client Restocking'!L16
G55: =F55*C55 -> 0 | L55: =H55+U55+W55-O55-Q55-I55-J55 -> 0 | M55: =K55-L55 -> 0 | N55: =M55*C55 -> 0 | O55: ='Dala Sales & Deliveries'!L17 | P55: =O55*E55 -> 0 | Q55: ='External Delivery Fulfillment'!L17 | R55: =Q55*E55 -> 0 | S55: ='Forwarding From Client'!L17 | T55: =S55*E55 -> 0 | U55: ='Dala Restocking'!L17 | V55: =U55*D55 -> 0 | W55: ='Client Restocking'!L17
G56: =F56*C56 -> 0 | L56: =H56+U56+W56-O56-Q56-I56-J56 -> 0 | M56: =K56-L56 -> 0 | N56: =M56*C56 -> 0 | O56: ='Dala Sales & Deliveries'!L18 | P56: =O56*E56 -> 0 | Q56: ='External Delivery Fulfillment'!L18 | R56: =Q56*E56 -> 0 | S56: ='Forwarding From Client'!L18 | T56: =S56*E56 -> 0 | U56: ='Dala Restocking'!L18 | V56: =U56*D56 -> 0 | W56: ='Client Restocking'!L18
G57: =F57*C57 -> 0 | L57: =H57+U57+W57-O57-Q57-I57-J57 -> 0 | M57: =K57-L57 -> 0 | N57: =M57*C57 -> 0 | O57: ='Dala Sales & Deliveries'!L19 | P57: =O57*E57 -> 0 | Q57: ='External Delivery Fulfillment'!L19 | R57: =Q57*E57 -> 0 | S57: ='Forwarding From Client'!L19 | T57: =S57*E57 -> 0 | U57: ='Dala Restocking'!L19 | V57: =U57*D57 -> 0 | W57: ='Client Restocking'!L19
... G68: =F68*C68 -> 0 | L68: =H68+U68+W68-O68-Q68-I68-J68 -> 0 | M68: =K68-L68 -> 0 | N68: =M68*C68 -> 0 | O68: ='Dala Sales & Deliveries'!L30 | P68: =O68*E68 -> 0 | Q68: ='External Delivery Fulfillment'!L30 | R68: =Q68*E68 -> 0 | S68: ='Forwarding From Client'!L30 | T68: =S68*E68 -> 0 | U68: ='Dala Restocking'!L30 | V68: =U68*D68 -> 0 | W68: ='Client Restocking'!L30
B69: TOTAL | F69: =sum(F40:F68) -> 0 | G69: =sum(G40:G68) -> 0 | H69: =sum(H40:H68) -> 0 | I69: =sum(I40:I68) -> 0 | J69: =sum(J40:J68) -> 0 | K69: =sum(K40:K68) -> 8.5 | L69: =sum(L40:L68) -> 24.58 | M69: =sum(M40:M68) -> -16.08 | ... W69: =sum(W40:W68) -> 33.75
C70: x | D70: x | E70: x | F70: x | G70: x | H70: x | I70: x | J70: x | K70: x | L70: x | M70: x | N70: x | O70: x | P70: x | Q70: x | R70: x | S70: x | T70: x | U70: x | V70: x | W70: x
