Workbook

Sheet Raw Data
A1: Exported from Tally | I1: Dala Sales & Deliveries | M1: , | R1: External Deliveries | Z1: Forwarding From Client | AH1: Client Restock | AP1: Dala Restock | AX1: Unique Locations
A2: item name | B2: Date | C2: Particulars | D2: Vch Type | E2: Vch No. | F2: Quantity | G2: Value | I2: item name | J2: Date | K2: Particulars | L2: Vch Type | M2: Vch No. | N2: Quantity | O2: Value | P2: Total Value | R2: item name | S2: Date | T2: Particulars | U2: Vch Type | V2: Vch No. | W2: Quantity | X2: Value | Z2: item name | AA2: Date | AB2: Particulars | AC2: Vch Type | AD2: Vch No. | AE2: Quantity | AF2: Value | AH2: item name | AI2: Date | AJ2: Particulars | AK2: Vch Type | AL2: Vch No. | AM2: Quantity | AN2: Value | AP2: item name | AQ2: Date | AR2: Particulars | AS2: Vch Type | AT2: Vch No. | AU2: Quantity | AV2: Value | AX2: {=counta(unique(C:C))-2} -> 0
A3: 300g Bunnies Cereals | B3: 45875 | C3: Taiwo Supermarket, ISOLO | D3: Sales | E3: DT:002060 | F3: 1 | G3: 20465.12 | I3: 300g Bunnies Cereals | J3: 45875 | K3: Taiwo Supermarket, ISOLO | L3: Sales | M3: DT:002060 | N3: 1 | O3: 20465.12 | P3: =sumif(M:M,M3,O:O) -> 40930.24
A4: 350g Pocco Cornflakes Cereal | B4: 45875 | C4: Taiwo Supermarket, ISOLO | D4: Sales | E4: DT:002060 | F4: 1 | G4: 20465.12 | I4: 350g Pocco Cornflakes Cereal | J4: 45875 | K4: Taiwo Supermarket, ISOLO | L4: Sales | M4: DT:002060 | N4: 1 | O4: 20465.12 | P4: =sumif(M:M,M4,O:O) -> 40930.24
P5: =sumif(M:M,M5,O:O) -> 0
P6: =sumif(M:M,M6,O:O) -> 0
P7: =sumif(M:M,M7,O:O) -> 0
P8: =sumif(M:M,M8,O:O) -> 0
P9: =sumif(M:M,M9,O:O) -> 0
P10: =sumif(M:M,M10,O:O) -> 0
P11: =sumif(M:M,M11,O:O) -> 0
P12: =sumif(M:M,M12,O:O) -> 0
P13: =sumif(M:M,M13,O:O) -> 0
P14: =sumif(M:M,M14,O:O) -> 0
P15: =sumif(M:M,M15,O:O) -> 0
P16: =sumif(M:M,M16,O:O) -> 0
... P186: =sumif(M:M,M186,O:O) -> 0

Sheet payment Advice

Sheet Dala Sales & Deliveries
H1: Total Invoices Delivered | I1: =countifs(B:B,"<>",F:F,"<>")-1 -> 1 | K1: Sku Performance | L1: Units | M1: Value
H2: Unique Locations Supplied | I2: {=(COUNTA(UNIQUE(C:C))-1)} -> 1 | K2: ='Internal Summary'!B40 -> 25g Bunnies Cereal | L2: =sumif(D:D,K2,E:E) -> 0 | M2: =sumif(D:D,K2,F:F) -> 0
H3: Total Value of orders | I3: =sum(F:F) -> 40930.24 | K3: ='Internal Summary'!B41 -> 300g Bunnies Cereals | L3: =sumif(D:D,K3,E:E) -> 1 | M3: =sumif(D:D,K3,F:F) -> 20465.12
K4: ='Internal Summary'!B42 -> 30g Pocco Cornflakes Cereal | L4: =sumif(D:D,K4,E:E) -> 0 | M4: =sumif(D:D,K4,F:F) -> 0
K5: ='Internal Summary'!B43 -> 350g Pocco Cornflakes Cereal | L5: =sumif(D:D,K5,E:E) -> 1 | M5: =sumif(D:D,K5,F:F) -> 20465.12
K6: ='Internal Summary'!B44 | L6: =sumif(D:D,K6,E:E) -> 0 | M6: =sumif(D:D,K6,F:F) -> 0
K7: ='Internal Summary'!B45 | L7: =sumif(D:D,K7,E:E) -> 0 | M7: =sumif(D:D,K7,F:F) -> 0
K8: ='Internal Summary'!B46 | L8: =sumif(D:D,K8,E:E) -> 0 | M8: =sumif(D:D,K8,F:F) -> 0
K9: ='Internal Summary'!B47 | L9: =sumif(D:D,K9,E:E) -> 0 | M9: =sumif(D:D,K9,F:F) -> 0
K10: ='Internal Summary'!B48 | L10: =sumif(D:D,K10,E:E) -> 0 | M10: =sumif(D:D,K10,F:F) -> 0
K11: ='Internal Summary'!B49 | L11: =sumif(D:D,K11,E:E) -> 0 | M11: =sumif(D:D,K11,F:F) -> 0
A12: 45758 | K12: ='Internal Summary'!B50 | L12: =sumif(D:D,K12,E:E) -> 0 | M12: =sumif(D:D,K12,F:F) -> 0
K13: ='Internal Summary'!B51 | L13: =sumif(D:D,K13,E:E) -> 0 | M13: =sumif(D:D,K13,F:F) -> 0

Sheet External Delivery Fulfillment
H1: Total Invoices Delivered | I1: =countifs(B:B,"<>",F:F,"<>")-1 -> 0 | K1: Sku Performance | L1: Units | M1: Value
H2: Unique Locations Supplied | I2: {=(COUNTA(UNIQUE(C:C))-1)} -> 0 | K2: ='Internal Summary'!B40 -> 25g Bunnies Cereal | L2: =sumif(D:D,K2,E:E) -> 0 | M2: =sumif(D:D,K2,F:F) -> 0
H3: Total Value of orders | I3: =sum(F:F) -> 0 | K3: ='Internal Summary'!B41 -> 300g Bunnies Cereals | L3: =sumif(D:D,K3,E:E) -> 0 | M3: =sumif(D:D,K3,F:F) -> 0
K4: ='Internal Summary'!B42 -> 30g Pocco Cornflakes Cereal | L4: =sumif(D:D,K4,E:E) -> 0 | M4: =sumif(D:D,K4,F:F) -> 0
K5: ='Internal Summary'!B43 -> 350g Pocco Cornflakes Cereal | L5: =sumif(D:D,K5,E:E) -> 0 | M5: =sumif(D:D,K5,F:F) -> 0
K6: ='Internal Summary'!B44 | L6: =sumif(D:D,K6,E:E) -> 0 | M6: =sumif(D:D,K6,F:F) -> 0
K7: ='Internal Summary'!B45 | L7: =sumif(D:D,K7,E:E) -> 0 | M7: =sumif(D:D,K7,F:F) -> 0
K8: ='Internal Summary'!B46 | L8: =sumif(D:D,K8,E:E) -> 0 | M8: =sumif(D:D,K8,F:F) -> 0
K9: ='Internal Summary'!B47 | L9: =sumif(D:D,K9,E:E) -> 0 | M9: =sumif(D:D,K9,F:F) -> 0
K10: ='Internal Summary'!B48 | L10: =sumif(D:D,K10,E:E) -> 0 | M10: =sumif(D:D,K10,F:F) -> 0
K11: ='Internal Summary'!B49 | L11: =sumif(D:D,K11,E:E) -> 0 | M11: =sumif(D:D,K11,F:F) -> 0
K12: ='Internal Summary'!B50 | L12: =sumif(D:D,K12,E:E) -> 0 | M12: =sumif(D:D,K12,F:F) -> 0
K13: ='Internal Summary'!B51 | L13: =sumif(D:D,K13,E:E) -> 0 | M13: =sumif(D:D,K13,F:F) -> 0

Sheet Forwarding From Client
H1: Total Invoices Delivered | I1: =countifs(B:B,"<>",F:F,"<>")-1 -> 0 | K1: Sku Performance | L1: Units | M1: Value
H2: Unique Locations Supplied | I2: {=(COUNTA(UNIQUE(C:C))-1)} -> 0 | K2: ='Internal Summary'!B40 -> 25g Bunnies Cereal | L2: =sumif(D:D,K2,E:E) -> 0 | M2: =sumif(D:D,K2,F:F) -> 0
H3: Total Value of orders | I3: =sum(F:F) -> 0 | K3: ='Internal Summary'!B41 -> 300g Bunnies Cereals | L3: =sumif(D:D,K3,E:E) -> 0 | M3: =sumif(D:D,K3,F:F) -> 0
K4: ='Internal Summary'!B42 -> 30g Pocco Cornflakes Cereal | L4: =sumif(D:D,K4,E:E) -> 0 | M4: =sumif(D:D,K4,F:F) -> 0
K5: ='Internal Summary'!B43 -> 350g Pocco Cornflakes Cereal | L5: =sumif(D:D,K5,E:E) -> 0 | M5: =sumif(D:D,K5,F:F) -> 0
K6: ='Internal Summary'!B44 | L6: =sumif(D:D,K6,E:E) -> 0 | M6: =sumif(D:D,K6,F:F) -> 0
K7: ='Internal Summary'!B45 | L7: =sumif(D:D,K7,E:E) -> 0 | M7: =sumif(D:D,K7,F:F) -> 0
K8: ='Internal Summary'!B46 | L8: =sumif(D:D,K8,E:E) -> 0 | M8: =sumif(D:D,K8,F:F) -> 0
K9: ='Internal Summary'!B47 | L9: =sumif(D:D,K9,E:E) -> 0 | M9: =sumif(D:D,K9,F:F) -> 0
K10: ='Internal Summary'!B48 | L10: =sumif(D:D,K10,E:E) -> 0 | M10: =sumif(D:D,K10,F:F) -> 0
K11: ='Internal Summary'!B49 | L11: =sumif(D:D,K11,E:E) -> 0 | M11: =sumif(D:D,K11,F:F) -> 0
K12: ='Internal Summary'!B50 | L12: =sumif(D:D,K12,E:E) -> 0 | M12: =sumif(D:D,K12,F:F) -> 0
K13: ='Internal Summary'!B51 | L13: =sumif(D:D,K13,E:E) -> 0 | M13: =sumif(D:D,K13,F:F) -> 0

Sheet Dala Restocking
H1: Total Invoices Delivered | I1: =countifs(B:B,"<>",F:F,"<>")-1 -> 0 | K1: Sku Performance | L1: Units
H2: Unique Locations Supplied | I2: {=(COUNTA(UNIQUE(C:C,,0))-1)} -> 0 | K2: ='Internal Summary'!B40 -> 25g Bunnies Cereal | L2: =sumif(D:D,K2,E:E) -> 0
H3: Total Value of orders | I3: =sum(F:F) -> 0 | K3: ='Internal Summary'!B41 -> 300g Bunnies Cereals | L3: =sumif(D:D,K3,E:E) -> 0
K4: ='Internal Summary'!B42 -> 30g Pocco Cornflakes Cereal | L4: =sumif(D:D,K4,E:E) -> 0
K5: ='Internal Summary'!B43 -> 350g Pocco Cornflakes Cereal | L5: =sumif(D:D,K5,E:E) -> 0
K6: ='Internal Summary'!B44 | L6: =sumif(D:D,K6,E:E) -> 0
K7: ='Internal Summary'!B45 | L7: =sumif(D:D,K7,E:E) -> 0
K8: ='Internal Summary'!B46 | L8: =sumif(D:D,K8,E:E) -> 0
K9: ='Internal Summary'!B47 | L9: =sumif(D:D,K9,E:E) -> 0
K10: ='Internal Summary'!B48 | L10: =sumif(D:D,K10,E:E) -> 0
K11: ='Internal Summary'!B49 | L11: =sumif(D:D,K11,E:E) -> 0
K12: ='Internal Summary'!B50 | L12: =sumif(D:D,K12,E:E) -> 0
K13: ='Internal Summary'!B51 | L13: =sumif(D:D,K13,E:E) -> 0

Sheet Client Restocking
H1: Total Invoices Delivered | I1: =countifs(B:B,"<>",F:F,"<>")-1 -> 0 | K1: Sku Performance | L1: Units
H2: Unique Locations Supplied | I2: {=(COUNTA(UNIQUE(C:C,,0))-1)} -> 0 | K2: ='Internal Summary'!B40 -> 25g Bunnies Cereal | L2: =sumif(D:D,K2,E:E) -> 0
H3: Total Value of orders | I3: =sum(F:F) -> 0 | K3: ='Internal Summary'!B41 -> 300g Bunnies Cereals | L3: =sumif(D:D,K3,E:E) -> 0
K4: ='Internal Summary'!B42 -> 30g Pocco Cornflakes Cereal | L4: =sumif(D:D,K4,E:E) -> 0
K5: ='Internal Summary'!B43 -> 350g Pocco Cornflakes Cereal | L5: =sumif(D:D,K5,E:E) -> 0
K6: ='Internal Summary'!B44 | L6: =sumif(D:D,K6,E:E) -> 0
K7: ='Internal Summary'!B45 | L7: =sumif(D:D,K7,E:E) -> 0
K8: ='Internal Summary'!B46 | L8: =sumif(D:D,K8,E:E) -> 0
K9: ='Internal Summary'!B47 | L9: =sumif(D:D,K9,E:E) -> 0
K10: ='Internal Summary'!B48 | L10: =sumif(D:D,K10,E:E) -> 0
K11: ='Internal Summary'!B49 | L11: =sumif(D:D,K11,E:E) -> 0
K12: ='Internal Summary'!B50 | L12: =sumif(D:D,K12,E:E) -> 0
K13: ='Internal Summary'!B51 | L13: =sumif(D:D,K13,E:E) -> 0

Sheet Internal Summary
B1: Description | C1: Units | D1: measurements | E1: total
A2: SALES | B2: Total Invoices Delivered | E2: ='Dala Sales & Deliveries'!I1+'External Delivery Fulfillment'!I1 -> 1
B3: Unique Locations Delivered To | E3: ='Raw Data'!AX2 -> 0
B4: Value of Dala Deliveries | E4: ='Dala Sales & Deliveries'!I3 -> 40930.24
B5: Value of External Deliveries | E5: ='External Delivery Fulfillment'!I3 -> 0
B6: VAT on sales | E6: =E4*1.075-E4 -> 3069.768
B7: Total Value of Deliveries | E7: =sum(E4:E6) -> 44000.008
A8: Remittance & Deductions | B8: Total Remitted to Partner
B9: Collection Fees | C9: 0.12 | E9: =E8*(C9+100%)-E8 -> 0
A10: Invoice Value Due | B10: Outstanding Paymets For Sales | E10: =E7-E8-E9 -> 44000.008
A11: Debts | B11: Unpaid Subscription | C11: 1 | D11: 150000 | E11: =C11*D11 -> 150000
B12: Collection Fees | E12: =E10*C9 -> 5280.001
B13: Delivery Fees | D13: Table 1 | E13: =C22+C26 -> 2000
B14: Reimbursements Due To DALA | E14: 0
B15: Retailer Deductions | E15: =C30 -> 0
B16: Total Deductions | E16: =sum(E11:E15) -> 157280
A17: Remmittance Due | B17: Total Balance to Remitt | E17: =E10-E16+C36 -> -113279.99
A20: Inventory and Operational Fees
B21: Dala Pickup for Warehouse | C21: =U69 -> 0
B22: Warehouse Delivery Fee | C22: =V69 -> 0
B23: Forwarding to Retail | C23: =S69 -> 0
B24: Forwarding Delivery Fee | C24: =T69 -> 0
B25: Dala Sales | C25: =67 -> 67
B26: Dala Delivery Fees | C26: =P69 -> 2000
B27: Exteranl Deliveries | C27: =Q69 -> 0
B28: External Delivery Fees | C28: =R69 -> 0
B29: Product Defects and Expirey Issues | C29: =F69 -> 0
B30: Deductions From Retailer | C30: =G69 -> 0
B31: Samples used | C31: =I69 -> 0
B32: Produce Replacements | C32: =J69 -> 0
B33: Expected Closing Inventory | C33: 0
B34: Physical Stock count | C34: =K69 -> 54.5
B35: Inventory Shortages | C35: 0
B36: Inventory Shortage Costs | C36: 0
B39: SKUs | C39: Retail Value | D39: Inbound Delivery Fee | E39: Outbound Delivery Fee | F39: Defects/Expirey | G39: Deductions | H39: Opening Inventory | I39: Samples Used | J39: Product Replacements | K39: Physical Closing Stock Count | L39: Expected Closing Inventory | M39: Inventory Shortages | N39: Shortages Costs | O39: Dala Deliveries | P39: Retail Sales Fee | Q39: External Delivery | R39: External Delivery Fee | S39: Forwarding from Client | T39: Forwarding Delivery Fee | U39: Dala Restocking | V39: Dala Restocking Fee | W39: Client Restocking
B40: 25g Bunnies Cereal | C40: 16800 | D40: 500 | E40: 800 | G40: =F40*C40 -> 0 | K40: 3.5 | L40: =H40+U40+W40-O40-Q40-I40-J40 -> 0 | M40: =K40-L40 -> 3.5 | N40: =M40*C40 -> 58800 | O40: ='Dala Sales & Deliveries'!L2 -> 0 | P40: =O40*E40 -> 0 | Q40: ='External Delivery Fulfillment'!L2 -> 0 | R40: =Q40*E40 -> 0 | S40: ='Forwarding From Client'!L2 -> 0 | T40: =S40*E40 -> 0 | U40: ='Dala Restocking'!L2 -> 0 | V40: =U40*D40 -> 0 | W40: ='Client Restocking'!L2 -> 0
B41: 300g Bunnies Cereals | C41: 22000 | D41: 650 | E41: 1000 | G41: =F41*C41 -> 0 | K41: 24 | L41: =H41+U41+W41-O41-Q41-I41-J41 -> -1 | M41: =K41-L41 -> 25 | N41: =M41*C41 -> 550000 | O41: ='Dala Sales & Deliveries'!L3 -> 1 | P41: =O41*E41 -> 1000 | Q41: ='External Delivery Fulfillment'!L3 -> 0 | R41: =Q41*E41 -> 0 | S41: ='Forwarding From Client'!L3 -> 0 | T41: =S41*E41 -> 0 | U41: ='Dala Restocking'!L3 -> 0 | V41: =U41*D41 -> 0 | W41: ='Client Restocking'!L3 -> 0
B42: 30g Pocco Cornflakes Cereal | C42: 16800 | D42: 500 | E42: 800 | G42: =F42*C42 -> 0 | K42: 2.5 | L42: =H42+U42+W42-O42-Q42-I42-J42 -> 0 | M42: =K42-L42 -> 2.5 | N42: =M42*C42 -> 42000 | O42: ='Dala Sales & Deliveries'!L4 -> 0 | P42: =O42*E42 -> 0 | Q42: ='External Delivery Fulfillment'!L4 -> 0 | R42: =Q42*E42 -> 0 | S42: ='Forwarding From Client'!L4 -> 0 | T42: =S42*E42 -> 0 | U42: ='Dala Restocking'!L4 -> 0 | V42: =U42*D42 -> 0 | W42: ='Client Restocking'!L4 -> 0
B43: 350g Pocco Cornflakes Cereal | C43: 22000 | D43: 650 | E43: 1000 | G43: =F43*C43 -> 0 | K43: 24.5 | L43: =H43+U43+W43-O43-Q43-I43-J43 -> -1 | M43: =K43-L43 -> 25.5 | N43: =M43*C43 -> 561000 | O43: ='Dala Sales & Deliveries'!L5 -> 1 | P43: =O43*E43 -> 1000 | Q43: ='External Delivery Fulfillment'!L5 -> 0 | R43: =Q43*E43 -> 0 | S43: ='Forwarding From Client'!L5 -> 0 | T43: =S43*E43 -> 0 | U43: ='Dala Restocking'!L5 -> 0 | V43: =U43*D43 -> 0 | W43: ='Client Restocking'!L5 -> 0
G44: =F44*C44 -> 0 | L44: =H44+U44+W44-O44-Q44-I44-J44 -> 0 | M44: =K44-L44 -> 0 | N44: =M44*C44 -> 0 | O44: ='Dala Sales & Deliveries'!L6 -> 0 | P44: =O44*E44 -> 0 | Q44: ='External Delivery Fulfillment'!L6 -> 0 | R44: =Q44*E44 -> 0 | S44: ='Forwarding From Client'!L6 -> 0 | T44: =S44*E44 -> 0 | U44: ='Dala Restocking'!L6 -> 0 | V44: =U44*D44 -> 0 | W44: ='Client Restocking'!L6 -> 0
G45: =F45*C45 -> 0 | L45: =H45+U45+W45-O45-Q45-I45-J45 -> 0 | M45: =K45-L45 -> 0 | N45: =M45*C45 -> 0 | O45: ='Dala Sales & Deliveries'!L7 -> 0 | P45: =O45*E45 -> 0 | Q45: ='External Delivery Fulfillment'!L7 -> 0 | R45: =Q45*E45 -> 0 | S45: ='Forwarding From Client'!L7 -> 0 | T45: =S45*E45 -> 0 | U45: ='Dala Restocking'!L7 -> 0 | V45: =U45*D45 -> 0 | W45: ='Client Restocking'!L7 -> 0
G46: =F46*C46 -> 0 | L46: =H46+U46+W46-O46-Q46-I46-J46 -> 0 | M46: =K46-L46 -> 0 | N46: =M46*C46 -> 0 | O46: ='Dala Sales & Deliveries'!L8 -> 0 | P46: =O46*E46 -> 0 | Q46: ='External Delivery Fulfillment'!L8 -> 0 | R46: =Q46*E46 -> 0 | S46: ='Forwarding From Client'!L8 -> 0 | T46: =S46*E46 -> 0 | U46: ='Dala Restocking'!L8 -> 0 | V46: =U46*D46 -> 0 | W46: ='Client Restocking'!L8 -> 0
G47: =F47*C47 -> 0 | L47: =H47+U47+W47-O47-Q47-I47-J47 -> 0 | M47: =K47-L47 -> 0 | N47: =M47*C47 -> 0 | O47: ='Dala Sales & Deliveries'!L9 -> 0 | P47: =O47*E47 -> 0 | Q47: ='External Delivery Fulfillment'!L9 -> 0 | R47: =Q47*E47 -> 0 | S47: ='Forwarding From Client'!L9 -> 0 | T47: =S47*E47 -> 0 | U47: ='Dala Restocking'!L9 -> 0 | V47: =U47*D47 -> 0 | W47: ='Client Restocking'!L9 -> 0
G48: =F48*C48 -> 0 | L48: =H48+U48+W48-O48-Q48-I48-J48 -> 0 | M48: =K48-L48 -> 0 | N48: =M48*C48 -> 0 | O48: ='Dala Sales & Deliveries'!L10 -> 0 | P48: =O48*E48 -> 0 | Q48: ='External Delivery Fulfillment'!L10 -> 0 | R48: =Q48*E48 -> 0 | S48: ='Forwarding From Client'!L10 -> 0 | T48: =S48*E48 -> 0 | U48: ='Dala Restocking'!L10 -> 0 | V48: =U48*D48 -> 0 | W48: ='Client Restocking'!L10 -> 0
G49: =F49*C49 -> 0 | L49: =H49+U49+W49-O49-Q49-I49-J49 -> 0 | M49: =K49-L49 -> 0 | N49: =M49*C49 -> 0 | O49: ='Dala Sales & Deliveries'!L11 -> 0 | P49: =O49*E49 -> 0 | Q49: ='External Delivery Fulfillment'!L11 -> 0 | R49: =Q49*E49 -> 0 | S49: ='Forwarding From Client'!L11 -> 0 | T49: =S49*E49 -> 0 | U49: ='Dala Restocking'!L11 -> 0 | V49: =U49*D49 -> 0 | W49: ='Client Restocking'!L11 -> 0
G50: =F50*C50 -> 0 | L50: =H50+U50+W50-O50-Q50-I50-J50 -> 0 | M50: =K50-L50 -> 0 | N50: =M50*C50 -> 0 | O50: ='Dala Sales & Deliveries'!L12 -> 0 | P50: =O50*E50 -> 0 | Q50: ='External Delivery Fulfillment'!L12 -> 0 | R50: =Q50*E50 -> 0 | S50: ='Forwarding From Client'!L12 -> 0 | T50: =S50*E50 -> 0 | U50: ='Dala Restocking'!L12 -> 0 | V50: =U50*D50 -> 0 | W50: ='Client Restocking'!L12 -> 0
G51: =F51*C51 -> 0 | L51: =H51+U51+W51-O51-Q51-I51-J51 -> 0 | M51: =K51-L51 -> 0 | N51: =M51*C51 -> 0 | O51: ='Dala Sales & Deliveries'!L13 -> 0 | P51: =O51*E51 -> 0 | Q51: ='External Delivery Fulfillment'!L13 -> 0 | R51: =Q51*E51 -> 0 | S51: ='Forwarding From Client'!L13 -> 0 | T51: =S51*E51 -> 0 | U51: ='Dala Restocking'!L13 -> 0 | V51: =U51*D51 -> 0 | W51: ='Client Restocking'!L13 -> 0
G52: =F52*C52 -> 0 | L52: =H52+U52+W52-O52-Q52-I52-J52 -> 0 | M52: =K52-L52 -> 0 | N52: =M52*C52 -> 0 | O52: ='Dala Sales & Deliveries'!L14 | P52: =O52*E52 -> 0 | Q52: ='External Delivery Fulfillment'!L14 | R52: =Q52*E52 -> 0 | S52: ='Forwarding From Client'!L14 | T52: =S52*E52 -> 0 | U52: ='Dala Restocking'!L14 | V52: =U52*D52 -> 0 | W52: ='Client Restocking'!L14
G53: =F53*C53 -> 0 | L53: =H53+U53+W53-O53-Q53-I53-J53 -> 0 | M53: =K53-L53 -> 0 | N53: =M53*C53 -> 0 | O53: ='Dala Sales & Deliveries'!L15 | P53: =O53*E53 -> 0 | Q53: ='External Delivery Fulfillment'!L15 | R53: =Q53*E53 -> 0 | S53: ='Forwarding From Client'!L15 | T53: =S53*E53 -> 0 | U53: ='Dala Restocking'!L15 | V53: =U53*D53 -> 0 | W53: ='Client Restocking'!L15
G54: =F54*C54 -> 0 | L54: =H54+U54+W54-O54-Q54-I54-J54 -> 0 | M54: =K54-L54 -> 0 | N54: =M54*C54 -> 0 | O54: ='Dala Sales & Deliveries'!L16 | P54: =O54*E54 -> 0 | Q54: ='External Delivery Fulfillment'!L16 | R54: =Q54*E54 -> 0 | S54: ='Forwarding From Client'!L16 | T54: =S54*E54 -> 0 | U54: ='Dala Restocking'!L16 | V54: =U54*D54 -> 0 | W54: ='Client Restocking'!L16
G55: =F55*C55 -> 0 | L55: =H55+U55+W55-O55-Q55-I55-J55 -> 0 | M55: =K55-L55 -> 0 | N55: =M55*C55 -> 0 | O55: ='Dala Sales & Deliveries'!L17 | P55: =O55*E55 -> 0 | Q55: ='External Delivery Fulfillment'!L17 | R55: =Q55*E55 -> 0 | S55: ='Forwarding From Client'!L17 | T55: =S55*E55 -> 0 | U55: ='Dala Restocking'!L17 | V55: =U55*D55 -> 0 | W55: ='Client Restocking'!L17
... G68: =F68*C68 -> 0 | L68: =H68+U68+W68-O68-Q68-I68-J68 -> 0 | M68: =K68-L68 -> 0 | N68: =M68*C68 -> 0 | O68: ='Dala Sales & Deliveries'!L30 | P68: =O68*E68 -> 0 | Q68: ='External Delivery Fulfillment'!L30 | R68: =Q68*E68 -> 0 | S68: ='Forwarding From Client'!L30 | T68: =S68*E68 -> 0 | U68: ='Dala Restocking'!L30 | V68: =U68*D68 -> 0 | W68: ='Client Restocking'!L30
B69: TOTAL | F69: =sum(F40:F68) -> 0 | G69: =sum(G40:G68) -> 0 | H69: =sum(H40:H68) -> 0 | I69: =sum(I40:I68) -> 0 | J69: =sum(J40:J68) -> 0 | K69: =sum(K40:K68) -> 54.5 | L69: =sum(L40:L68) -> -2 | M69: =sum(M40:M68) -> 56.5 | ... W69: =sum(W40:W68) -> 0
C70: x | D70: x | E70: x | F70: x | G70: x | H70: x | I70: x | J70: x | K70: x | L70: x | M70: x | N70: x | O70: x | P70: x | Q70: x | R70: x | S70: x | T70: x | U70: x | V70: x | W70: x

Sheet External Summary
B1: Description | C1: Units | D1: measurements | E1: total
A2: SALES | B2: Total Invoices Delivered | E2: ='Dala Sales & Deliveries'!I1+'External Delivery Fulfillment'!I1+'Forwarding From Client'!I1 -> 1
B3: Unique Locations Delivered To | E3: ='Raw Data'!AX2 -> 0
B4: Value of Dala Deliveries | E4: ='Dala Sales & Deliveries'!I3 -> 40930.24
B5: VAT | E5: =E4*1.075-E4 -> 3069.768
B6: Total Value of Deliveries | E6: =sum(E4:E5) -> 44000.008
A7: Remittance & Deductions | B7: Total Remitted to Partner
B8: Delivery Fees | C8: 0.06 | E8: =E7*(C8+100%)-E7 -> 0
B9: Collection Fees | C9: 0.1 | E9: =E7*(C9+100%)-E7 -> 0
A10: Debts | B10: Unpaid Subscription | C10: 1 | D10: 150000 | E10: =C10*D10 -> 150000
B11: Restocking Fees | E11: =V67 -> 0
B12: External Delivery Fees | E12: =R67 -> 0
B13: Reimbursements Due To DALA | E13: 0
B14: Retailer Deductions | E14: =C28 -> 0
B15: Total Owed to Dala | E15: =sum(E10:E14) -> 150000
A18: Inventory and Operational Fees
B19: Dala Pickup for Warehouse | C19: =U67 -> 0
B20: Warehouse Delivery Fee | C20: =V67 -> 0
B21: Forwarding to Retail | C21: =S67 -> 0
B22: Forwarding Delivery Fee | C22: =T67 -> 0
B23: Dala Sales | C23: =O67 -> 2
B24: Dala Delivery Fees | C24: =P67 -> 2000
B25: Exteranl Deliveries | C25: =Q67 -> 0
B26: External Delivery Fees | C26: =R67 -> 0
B27: Product Defects and Expirey Issues | C27: =F67 -> 0
B28: Deductions From Retailer | C28: =G67 -> 0
B29: Samples used | C29: =I67 -> 0
B30: Returns/Replacements | C30: =J67 -> 0
B31: Expected Closing Inventory | C31: =L67 -> -2
B32: Physical Stock count | C32: =K67 -> 54.5
B33: Inventory Shortages | C33: 0
B34: Inventory Shortage Costs | C34: 0
B37: SKUs | C37: Retail Value | D37: Inbound Delivery Fee | E37: Outbound Delivery Fee | F37: Defects/Expirey | G37: Deductions | H37: Opening Inventory | I37: Samples Used | J37: Product Replacements | K37: Physical Closing Stock Count | L37: Expected Closing Inventory | M37: Inventory Shortages | N37: Shortages Costs | O37: Dala Sales | P37: Retail Sales Fee | Q37: External Delivery | R37: External Delivery Fee | S37: Forwarding from Client | T37: Forwarding Delivery Fee | U37: Dala Restocking | V37: Dala Restocking Fee | W37: Client Restocking
B38: 25g Bunnies Cereal | C38: ='Internal Summary'!C40 -> 16800 | D38: ='Internal Summary'!D40 -> 500 | E38: ='Internal Summary'!E40 -> 800 | G38: =F38*C38 -> 0 | K38: 3.5 | L38: =H38+U38+W38-O38-Q38-I38-J38 -> 0 | M38: =K38-L38 -> 3.5 | N38: =M38*C38 -> 58800 | O38: ='Dala Sales & Deliveries'!L2 -> 0 | P38: =O38*E38 -> 0 | Q38: ='External Delivery Fulfillment'!L2 -> 0 | R38: =Q38*E38 -> 0 | S38: ='Forwarding From Client'!L2 -> 0 | T38: =S38*E38 -> 0 | U38: ='Dala Restocking'!L2 -> 0 | V38: =U38*D38 -> 0 | W38: ='Client Restocking'!L2 -> 0
B39: 300g Bunnies Cereals | C39: ='Internal Summary'!C41 -> 22000 | D39: ='Internal Summary'!D41 -> 650 | E39: ='Internal Summary'!E41 -> 1000 | G39: =F39*C39 -> 0 | K39: 24 | L39: =H39+U39+W39-O39-Q39-I39-J39 -> -1 | M39: =K39-L39 -> 25 | N39: =M39*C39 -> 550000 | O39: ='Dala Sales & Deliveries'!L3 -> 1 | P39: =O39*E39 -> 1000 | Q39: ='External Delivery Fulfillment'!L3 -> 0 | R39: =Q39*E39 -> 0 | S39: ='Forwarding From Client'!L3 -> 0 | T39: =S39*E39 -> 0 | U39: ='Dala Restocking'!L3 -> 0 | V39: =U39*D39 -> 0 | W39: ='Client Restocking'!L3 -> 0
B40: 30g Pocco Cornflakes Cereal | C40: ='Internal Summary'!C42 -> 16800 | D40: ='Internal Summary'!D42 -> 500 | E40: ='Internal Summary'!E42 -> 800 | G40: =F40*C40 -> 0 | K40: 2.5 | L40: =H40+U40+W40-O40-Q40-I40-J40 -> 0 | M40: =K40-L40 -> 2.5 | N40: =M40*C40 -> 42000 | O40: ='Dala Sales & Deliveries'!L4 -> 0 | P40: =O40*E40 -> 0 | Q40: ='External Delivery Fulfillment'!L4 -> 0 | R40: =Q40*E40 -> 0 | S40: ='Forwarding From Client'!L4 -> 0 | T40: =S40*E40 -> 0 | U40: ='Dala Restocking'!L4 -> 0 | V40: =U40*D40 -> 0 | W40: ='Client Restocking'!L4 -> 0
B41: 350g Pocco Cornflakes Cereal | C41: ='Internal Summary'!C43 -> 22000 | D41: ='Internal Summary'!D43 -> 650 | E41: ='Internal Summary'!E43 -> 1000 | G41: =F41*C41 -> 0 | K41: 24.5 | L41: =H41+U41+W41-O41-Q41-I41-J41 -> -1 | M41: =K41-L41 -> 25.5 | N41: =M41*C41 -> 561000 | O41: ='Dala Sales & Deliveries'!L5 -> 1 | P41: =O41*E41 -> 1000 | Q41: ='External Delivery Fulfillment'!L5 -> 0 | R41: =Q41*E41 -> 0 | S41: ='Forwarding From Client'!L5 -> 0 | T41: =S41*E41 -> 0 | U41: ='Dala Restocking'!L5 -> 0 | V41: =U41*D41 -> 0 | W41: ='Client Restocking'!L5 -> 0
B42: ='Internal Summary'!B44 | C42: ='Internal Summary'!C44 | D42: ='Internal Summary'!D44 | E42: ='Internal Summary'!E44 | G42: =F42*C42 -> 0 | L42: =H42+U42+W42-O42-Q42-I42-J42 -> 0 | M42: =K42-L42 -> 0 | N42: =M42*C42 -> 0 | O42: ='Dala Sales & Deliveries'!L6 -> 0 | P42: =O42*E42 -> 0 | Q42: ='External Delivery Fulfillment'!L6 -> 0 | R42: =Q42*E42 -> 0 | S42: ='Forwarding From Client'!L6 -> 0 | T42: =S42*E42 -> 0 | U42: ='Dala Restocking'!L6 -> 0 | V42: =U42*D42 -> 0 | W42: ='Client Restocking'!L6 -> 0
B43: ='Internal Summary'!B45 | C43: ='Internal Summary'!C45 | D43: ='Internal Summary'!D45 | E43: ='Internal Summary'!E45 | G43: =F43*C43 -> 0 | L43: =H43+U43+W43-O43-Q43-I43-J43 -> 0 | M43: =K43-L43 -> 0 | N43: =M43*C43 -> 0 | O43: ='Dala Sales & Deliveries'!L7 -> 0 | P43: =O43*E43 -> 0 | Q43: ='External Delivery Fulfillment'!L7 -> 0 | R43: =Q43*E43 -> 0 | S43: ='Forwarding From Client'!L7 -> 0 | T43: =S43*E43 -> 0 | U43: ='Dala Restocking'!L7 -> 0 | V43: =U43*D43 -> 0 | W43: ='Client Restocking'!L7 -> 0
B44: ='Internal Summary'!B46 | C44: ='Internal Summary'!C46 | D44: ='Internal Summary'!D46 | E44: ='Internal Summary'!E46 | G44: =F44*C44 -> 0 | L44: =H44+U44+W44-O44-Q44-I44-J44 -> 0 | M44: =K44-L44 -> 0 | N44: =M44*C44 -> 0 | O44: ='Dala Sales & Deliveries'!L8 -> 0 | P44: =O44*E44 -> 0 | Q44: ='External Delivery Fulfillment'!L8 -> 0 | R44: =Q44*E44 -> 0 | S44: ='Forwarding From Client'!L8 -> 0 | T44: =S44*E44 -> 0 | U44: ='Dala Restocking'!L8 -> 0 | V44: =U44*D44 -> 0 | W44: ='Client Restocking'!L8 -> 0
B45: ='Internal Summary'!B47 | C45: ='Internal Summary'!C47 | D45: ='Internal Summary'!D47 | E45: ='Internal Summary'!E47 | G45: =F45*C45 -> 0 | L45: =H45+U45+W45-O45-Q45-I45-J45 -> 0 | M45: =K45-L45 -> 0 | N45: =M45*C45 -> 0 | O45: ='Dala Sales & Deliveries'!L9 -> 0 | P45: =O45*E45 -> 0 | Q45: ='External Delivery Fulfillment'!L9 -> 0 | R45: =Q45*E45 -> 0 | S45: ='Forwarding From Client'!L9 -> 0 | T45: =S45*E45 -> 0 | U45: ='Dala Restocking'!L9 -> 0 | V45: =U45*D45 -> 0 | W45: ='Client Restocking'!L9 -> 0
B46: ='Internal Summary'!B48 | C46: ='Internal Summary'!C48 | D46: ='Internal Summary'!D48 | E46: ='Internal Summary'!E48 | G46: =F46*C46 -> 0 | L46: =H46+U46+W46-O46-Q46-I46-J46 -> 0 | M46: =K46-L46 -> 0 | N46: =M46*C46 -> 0 | O46: ='Dala Sales & Deliveries'!L10 -> 0 | P46: =O46*E46 -> 0 | Q46: ='External Delivery Fulfillment'!L10 -> 0 | R46: =Q46*E46 -> 0 | S46: ='Forwarding From Client'!L10 -> 0 | T46: =S46*E46 -> 0 | U46: ='Dala Restocking'!L10 -> 0 | V46: =U46*D46 -> 0 | W46: ='Client Restocking'!L10 -> 0
B47: ='Internal Summary'!B49 | C47: ='Internal Summary'!C49 | D47: ='Internal Summary'!D49 | E47: ='Internal Summary'!E49 | G47: =F47*C47 -> 0 | L47: =H47+U47+W47-O47-Q47-I47-J47 -> 0 | M47: =K47-L47 -> 0 | N47: =M47*C47 -> 0 | O47: ='Dala Sales & Deliveries'!L11 -> 0 | P47: =O47*E47 -> 0 | Q47: ='External Delivery Fulfillment'!L11 -> 0 | R47: =Q47*E47 -> 0 | S47: ='Forwarding From Client'!L11 -> 0 | T47: =S47*E47 -> 0 | U47: ='Dala Restocking'!L11 -> 0 | V47: =U47*D47 -> 0 | W47: ='Client Restocking'!L11 -> 0
B48: ='Internal Summary'!B50 | C48: ='Internal Summary'!C50 | D48: ='Internal Summary'!D50 | E48: ='Internal Summary'!E50 | G48: =F48*C48 -> 0 | L48: =H48+U48+W48-O48-Q48-I48-J48 -> 0 | M48: =K48-L48 -> 0 | N48: =M48*C48 -> 0 | O48: ='Dala Sales & Deliveries'!L12 -> 0 | P48: =O48*E48 -> 0 | Q48: ='External Delivery Fulfillment'!L12 -> 0 | R48: =Q48*E48 -> 0 | S48: ='Forwarding From Client'!L12 -> 0 | T48: =S48*E48 -> 0 | U48: ='Dala Restocking'!L12 -> 0 | V48: =U48*D48 -> 0 | W48: ='Client Restocking'!L12 -> 0
B49: ='Internal Summary'!B51 | C49: ='Internal Summary'!C51 | D49: ='Internal Summary'!D51 | E49: ='Internal Summary'!E51 | G49: =F49*C49 -> 0 | L49: =H49+U49+W49-O49-Q49-I49-J49 -> 0 | M49: =K49-L49 -> 0 | N49: =M49*C49 -> 0 | O49: ='Dala Sales & Deliveries'!L13 -> 0 | P49: =O49*E49 -> 0 | Q49: ='External Delivery Fulfillment'!L13 -> 0 | R49: =Q49*E49 -> 0 | S49: ='Forwarding From Client'!L13 -> 0 | T49: =S49*E49 -> 0 | U49: ='Dala Restocking'!L13 -> 0 | V49: =U49*D49 -> 0 | W49: ='Client Restocking'!L13 -> 0
B50: ='Internal Summary'!B52 | C50: ='Internal Summary'!C52 | D50: ='Internal Summary'!D52 | E50: ='Internal Summary'!E52 | G50: =F50*C50 -> 0 | L50: =H50+U50+W50-O50-Q50-I50-J50 -> 0 | M50: =K50-L50 -> 0 | N50: =M50*C50 -> 0 | O50: ='Dala Sales & Deliveries'!L14 | P50: =O50*E50 -> 0 | Q50: ='External Delivery Fulfillment'!L14 | R50: =Q50*E50 -> 0 | S50: ='Forwarding From Client'!L14 | T50: =S50*E50 -> 0 | U50: ='Dala Restocking'!L14 | V50: =U50*D50 -> 0 | W50: ='Client Restocking'!L14
B51: ='Internal Summary'!B53 | C51: ='Internal Summary'!C53 | D51: ='Internal Summary'!D53 | E51: ='Internal Summary'!E53 | G51: =F51*C51 -> 0 | L51: =H51+U51+W51-O51-Q51-I51-J51 -> 0 | M51: =K51-L51 -> 0 | N51: =M51*C51 -> 0 | O51: ='Dala Sales & Deliveries'!L15 | P51: =O51*E51 -> 0 | Q51: ='External Delivery Fulfillment'!L15 | R51: =Q51*E51 -> 0 | S51: ='Forwarding From Client'!L15 | T51: =S51*E51 -> 0 | U51: ='Dala Restocking'!L15 | V51: =U51*D51 -> 0 | W51: ='Client Restocking'!L15
B52: ='Internal Summary'!B54 | C52: ='Internal Summary'!C54 | D52: ='Internal Summary'!D54 | E52: ='Internal Summary'!E54 | G52: =F52*C52 -> 0 | L52: =H52+U52+W52-O52-Q52-I52-J52 -> 0 | M52: =K52-L52 -> 0 | N52: =M52*C52 -> 0 | O52: ='Dala Sales & Deliveries'!L16 | P52: =O52*E52 -> 0 | Q52: ='External Delivery Fulfillment'!L16 | R52: =Q52*E52 -> 0 | S52: ='Forwarding From Client'!L16 | T52: =S52*E52 -> 0 | U52: ='Dala Restocking'!L16 | V52: =U52*D52 -> 0 | W52: ='Client Restocking'!L16
B53: ='Internal Summary'!B55 | C53: ='Internal Summary'!C55 | D53: ='Internal Summary'!D55 | E53: ='Internal Summary'!E55 | G53: =F53*C53 -> 0 | L53: =H53+U53+W53-O53-Q53-I53-J53 -> 0 | M53: =K53-L53 -> 0 | N53: =M53*C53 -> 0 | O53: ='Dala Sales & Deliveries'!L17 | P53: =O53*E53 -> 0 | Q53: ='External Delivery Fulfillment'!L17 | R53: =Q53*E53 -> 0 | S53: ='Forwarding From Client'!L17 | T53: =S53*E53 -> 0 | U53: ='Dala Restocking'!L17 | V53: =U53*D53 -> 0 | W53: ='Client Restocking'!L17
... B66: ='Internal Summary'!B68 | C66: ='Internal Summary'!C68 | D66: ='Internal Summary'!D68 | E66: ='Internal Summary'!E68 | G66: =F66*C66 -> 0 | L66: =H66+U66+W66-O66-Q66-I66-J66 -> 0 | M66: =K66-L66 -> 0 | N66: =M66*C66 -> 0 | O66: ='Dala Sales & Deliveries'!L30 | P66: =O66*E66 -> 0 | Q66: ='External Delivery Fulfillment'!L30 | R66: =Q66*E66 -> 0 | S66: ='Forwarding From Client'!L30 | T66: =S66*E66 -> 0 | U66: ='Dala Restocking'!L30 | V66: =U66*D66 -> 0 | W66: ='Client Restocking'!L30
B67: TOTAL | F67: =sum(F38:F66) -> 0 | G67: =sum(G38:G66) -> 0 | H67: =sum(H38:H66) -> 0 | I67: =sum(I38:I66) -> 0 | J67: =sum(J38:J66) -> 0 | K67: =sum(K38:K66) -> 54.5 | L67: =sum(L38:L66) -> -2 | M67: =sum(M38:M66) -> 56.5 | ... W67: =sum(W38:W66) -> 0
C68: x | D68: x | E68: x | F68: x | H68: x | I68: x | J68: x | K68: x | L68: x | N68: x | O68: x | P68: x | Q68: x | R68: x | U68: x | V68: x | W68: x
