Workbook

Sheet Raw Data
I1: Dala Sales & Deliveries | R1: External Deliveries | Z1: Forwarding From Client | AH1: Client Restock | AP1: Dala Restock | AX1: Unique Locations
A2: item name | B2: Date | C2: Particulars | D2: Vch Type | E2: Vch No. | F2: Quantity | G2: Value | I2: item name | J2: Date | K2: Particulars | L2: Vch Type | M2: Vch No. | N2: Quantity | O2: Value | P2: Total Value | R2: item name | S2: Date | T2: Particulars | U2: Vch Type | V2: Vch No. | W2: Quantity | X2: Value | Z2: item name | AA2: Date | AB2: Particulars | AC2: Vch Type | AD2: Vch No. | AE2: Quantity | AF2: Value | AH2: item name | AI2: Date | AJ2: Particulars | AK2: Vch Type | AL2: Vch No. | AM2: Quantity | AN2: Value | AP2: item name | AQ2: Date | AR2: Particulars | AS2: Vch Type | AT2: Vch No. | AU2: Quantity | AV2: Value | AX2: {=counta(unique(C:C))-3} -> 4
A3: 150g Segunfunmi Hibiscus Tea pineapple, Cloves, Ginger (24x) | B3: 45668 | C3: Sambethel Supermarket | D3: Sales | E3: DT:003195 | F3: 0.50 ctn | G3: 21000 | I3: =IFERROR(__xludf.DUMMYFUNCTION("IFERROR( FILTER($A$3:$G1000, LEN($A$3:$A1000), LOWER(TRIM($D$3:$D1000))=""sales""), )"),"150g Segunfunmi Hibiscus Tea pineapple, Cloves, Ginger (24x)") -> 150g Segunfunmi Hibiscus Tea pineapple, Cloves, Ginger (24x) | J3: =IFERROR(__xludf.DUMMYFUNCTION("""COMPUTED_VALUE"""),45668.0) -> 45668 | K3: =IFERROR(__xludf.DUMMYFUNCTION("""COMPUTED_VALUE"""),"Sambethel Supermarket") -> Sambethel Supermarket | L3: =IFERROR(__xludf.DUMMYFUNCTION("""COMPUTED_VALUE"""),"Sales") -> Sales | M3: =IFERROR(__xludf.DUMMYFUNCTION("""COMPUTED_VALUE"""),"DT:003195") -> DT:003195 | N3: =IFERROR(__xludf.DUMMYFUNCTION("""COMPUTED_VALUE"""),"0.50 ctn") -> 0.50 ctn | O3: =IFERROR(__xludf.DUMMYFUNCTION("""COMPUTED_VALUE"""),21000.0) -> 21000 | P3: =sumif(M:M,M3,O:O) -> 21000 | R3: =IFERROR(__xludf.DUMMYFUNCTION("IFERROR( FILTER($A$3:$G1000, LEN($A$3:$A1000), REGEXMATCH(LOWER(TRIM($D$3:$D1000)), ""\bjournal\b"")), ) "),"") | AH3: =IFERROR(__xludf.DUMMYFUNCTION("IFERROR( FILTER($A$3:$G1000, LEN($A$3:$A1000), LOWER(TRIM($D$3:$D1000))=""Inventory Supplied by Brands""), )"),"") | AP3: =IFERROR(__xludf.DUMMYFUNCTION("IFERROR( FILTER($A$3:$G1000, LEN($A$3:$A1000), LOWER(TRIM($D$3:$D1000))=""Inventory Pickup by Dala""), ) "),"")
A4: 150g Segunfunmi Hibiscus Tea pineapple, Cloves, Ginger (24x) | B4: 45668 | C4: Value Exchange Supermarket, AREPO | D4: Sales | E4: DT:003203 | F4: 0.25 ctn | G4: 21000 | I4: =IFERROR(__xludf.DUMMYFUNCTION("""COMPUTED_VALUE"""),"150g Segunfunmi Hibiscus Tea pineapple, Cloves, Ginger (24x)") -> 150g Segunfunmi Hibiscus Tea pineapple, Cloves, Ginger (24x) | J4: =IFERROR(__xludf.DUMMYFUNCTION("""COMPUTED_VALUE"""),45668.0) -> 45668 | K4: =IFERROR(__xludf.DUMMYFUNCTION("""COMPUTED_VALUE"""),"Value Exchange Supermarket, AREPO") -> Value Exchange Supermarket, AREPO | L4: =IFERROR(__xludf.DUMMYFUNCTION("""COMPUTED_VALUE"""),"Sales") -> Sales | M4: =IFERROR(__xludf.DUMMYFUNCTION("""COMPUTED_VALUE"""),"DT:003203") -> DT:003203 | N4: =IFERROR(__xludf.DUMMYFUNCTION("""COMPUTED_VALUE"""),"0.25 ctn") -> 0.25 ctn | O4: =IFERROR(__xludf.DUMMYFUNCTION("""COMPUTED_VALUE"""),21000.0) -> 21000 | P4: =sumif(M:M,M4,O:O) -> 21000
A5: 1kg Segunfunmi Granola Oat, Fruit, Nut (12x) | B5: 45727 | C5: Jendol Supermarket, ISHERI (Rg.11) | D5: Sales | E5: DT:003208 | F5: 1.00 ctn | G5: 78000 | I5: =IFERROR(__xludf.DUMMYFUNCTION("""COMPUTED_VALUE"""),"1kg Segunfunmi Granola Oat, Fruit, Nut (12x)") -> 1kg Segunfunmi Granola Oat, Fruit, Nut (12x) | J5: =IFERROR(__xludf.DUMMYFUNCTION("""COMPUTED_VALUE"""),45727.0) -> 45727 | K5: =IFERROR(__xludf.DUMMYFUNCTION("""COMPUTED_VALUE"""),"Jendol Supermarket, ISHERI (Rg.11)") -> Jendol Supermarket, ISHERI (Rg.11) | L5: =IFERROR(__xludf.DUMMYFUNCTION("""COMPUTED_VALUE"""),"Sales") -> Sales | M5: =IFERROR(__xludf.DUMMYFUNCTION("""COMPUTED_VALUE"""),"DT:003208") -> DT:003208 | N5: =IFERROR(__xludf.DUMMYFUNCTION("""COMPUTED_VALUE"""),"1.00 ctn") -> 1.00 ctn | O5: =IFERROR(__xludf.DUMMYFUNCTION("""COMPUTED_VALUE"""),78000.0) -> 78000 | P5: =sumif(M:M,M5,O:O) -> 78000
A6: 2kg Segunfunmi Ofada Rice (12x) | B6: 45788 | C6: Renees Supermarket, LEKKI CENTRAL MOSQUE | D6: Sales | E6: DT:003254 | F6: 0.50 ctn | G6: 52800 | I6: =IFERROR(__xludf.DUMMYFUNCTION("""COMPUTED_VALUE"""),"2kg Segunfunmi Ofada Rice (12x)") -> 2kg Segunfunmi Ofada Rice (12x) | J6: =IFERROR(__xludf.DUMMYFUNCTION("""COMPUTED_VALUE"""),45788.0) -> 45788 | K6: =IFERROR(__xludf.DUMMYFUNCTION("""COMPUTED_VALUE"""),"Renees Supermarket, LEKKI CENTRAL MOSQUE") -> Renees Supermarket, LEKKI CENTRAL MOSQUE | L6: =IFERROR(__xludf.DUMMYFUNCTION("""COMPUTED_VALUE"""),"Sales") -> Sales | M6: =IFERROR(__xludf.DUMMYFUNCTION("""COMPUTED_VALUE"""),"DT:003254") -> DT:003254 | N6: =IFERROR(__xludf.DUMMYFUNCTION("""COMPUTED_VALUE"""),"0.50 ctn") -> 0.50 ctn | O6: =IFERROR(__xludf.DUMMYFUNCTION("""COMPUTED_VALUE"""),52800.0) -> 52800 | P6: =sumif(M:M,M6,O:O) -> 52800
A7: 500g Segunfunmi Granola Oat, Fruit, Nut (24x) | B7: 45668 | C7: Katta Supermarket | D7: Sales | E7: DT:003193 | F7: 0.25 ctn | G7: 19810.72 | I7: =IFERROR(__xludf.DUMMYFUNCTION("""COMPUTED_VALUE"""),"500g Segunfunmi Granola Oat, Fruit, Nut (24x)") -> 500g Segunfunmi Granola Oat, Fruit, Nut (24x) | J7: =IFERROR(__xludf.DUMMYFUNCTION("""COMPUTED_VALUE"""),45668.0) -> 45668 | K7: =IFERROR(__xludf.DUMMYFUNCTION("""COMPUTED_VALUE"""),"Katta Supermarket") -> Katta Supermarket | L7: =IFERROR(__xludf.DUMMYFUNCTION("""COMPUTED_VALUE"""),"Sales") -> Sales | M7: =IFERROR(__xludf.DUMMYFUNCTION("""COMPUTED_VALUE"""),"DT:003193") -> DT:003193 | N7: =IFERROR(__xludf.DUMMYFUNCTION("""COMPUTED_VALUE"""),"0.25 ctn") -> 0.25 ctn | O7: =IFERROR(__xludf.DUMMYFUNCTION("""COMPUTED_VALUE"""),19810.72) -> 19810.72 | P7: =sumif(M:M,M7,O:O) -> 19810.72
A8: 500g Segunfunmi Granola Oat, Fruit, Nut (24x) | B8: 45758 | C8: Jendol Supermarket, OJODU | D8: Sales | E8: DT:003248 | F8: 0.50 ctn | G8: 39621.43 | I8: =IFERROR(__xludf.DUMMYFUNCTION("""COMPUTED_VALUE"""),"500g Segunfunmi Granola Oat, Fruit, Nut (24x)") -> 500g Segunfunmi Granola Oat, Fruit, Nut (24x) | J8: =IFERROR(__xludf.DUMMYFUNCTION("""COMPUTED_VALUE"""),45758.0) -> 45758 | K8: =IFERROR(__xludf.DUMMYFUNCTION("""COMPUTED_VALUE"""),"Jendol Supermarket, OJODU") -> Jendol Supermarket, OJODU | L8: =IFERROR(__xludf.DUMMYFUNCTION("""COMPUTED_VALUE"""),"Sales") -> Sales | M8: =IFERROR(__xludf.DUMMYFUNCTION("""COMPUTED_VALUE"""),"DT:003248") -> DT:003248 | N8: =IFERROR(__xludf.DUMMYFUNCTION("""COMPUTED_VALUE"""),"0.50 ctn") -> 0.50 ctn | O8: =IFERROR(__xludf.DUMMYFUNCTION("""COMPUTED_VALUE"""),39621.43) -> 39621.43 | P8: =sumif(M:M,M8,O:O) -> 39621.43
P9: =sumif(M:M,M9,O:O) -> 0
P10: =sumif(M:M,M10,O:O) -> 0
P11: =sumif(M:M,M11,O:O) -> 0
P12: =sumif(M:M,M12,O:O) -> 0
P13: =sumif(M:M,M13,O:O) -> 0
P14: =sumif(M:M,M14,O:O) -> 0
P15: =sumif(M:M,M15,O:O) -> 0
P16: =sumif(M:M,M16,O:O) -> 0
P17: =sumif(M:M,M17,O:O) -> 0
P18: =sumif(M:M,M18,O:O) -> 0
P19: =sumif(M:M,M19,O:O) -> 0
P20: =sumif(M:M,M20,O:O) -> 0
... P86: =sumif(M:M,M86,O:O) -> 0

Sheet Paymnet Advice

Sheet Dala Sales & Deliveries
H1: Total Invoices Delivered | I1: =countifs(B:B,"<>",F:F,"<>")-1 -> 6 | K1: Sku Performance | L1: Units | M1: Value
H2: Unique Locations Supplied | I2: {=(COUNTA(UNIQUE(C:C))-1)} -> 6 | K2: ='Internal Summary'!B39 -> 150g Segunfunmi Granola Oat, Fruit, Nut (24x) | L2: =sumif(D:D,K2,E:E) -> 0 | M2: =sumif(D:D,K2,F:F) -> 0
H3: Total Value of orders | I3: =sum(F:F) -> 232232.15 | K3: ='Internal Summary'!B40 -> 150g Segunfunmi Hibiscus Tea pineapple, Cloves, Ginger (24x) | L3: =sumif(D:D,K3,E:E) -> 0 | M3: =sumif(D:D,K3,F:F) -> 42000
K4: ='Internal Summary'!B41 -> 1kg Segunfunmi Granola Oat, Fruit, Nut (12x) | L4: =sumif(D:D,K4,E:E) -> 0 | M4: =sumif(D:D,K4,F:F) -> 78000
K5: ='Internal Summary'!B42 -> 1kg Segunfunmi Lafun Flour Cassava (12x) | L5: =sumif(D:D,K5,E:E) -> 0 | M5: =sumif(D:D,K5,F:F) -> 0
K6: ='Internal Summary'!B43 -> 1kg Segunfunmi Ofada Rice (24x) | L6: =sumif(D:D,K6,E:E) -> 0 | M6: =sumif(D:D,K6,F:F) -> 0
K7: ='Internal Summary'!B44 -> 1kg Segunfunmi Yam Flour (12x) | L7: =sumif(D:D,K7,E:E) -> 0 | M7: =sumif(D:D,K7,F:F) -> 0
K8: ='Internal Summary'!B45 -> 200g Segunfunmi Chilli Pepper (12x) | L8: =sumif(D:D,K8,E:E) -> 0 | M8: =sumif(D:D,K8,F:F) -> 0
K9: ='Internal Summary'!B46 -> 250g Segunfunmi Granola Oat, Fruit, Nut (24x) | L9: =sumif(D:D,K9,E:E) -> 0 | M9: =sumif(D:D,K9,F:F) -> 0
K10: ='Internal Summary'!B47 -> 2kg Segunfunmi Ofada Rice (12x) | L10: =sumif(D:D,K10,E:E) -> 0 | M10: =sumif(D:D,K10,F:F) -> 52800
K11: ='Internal Summary'!B48 -> 500g Segunfunmi Granola Oat, Fruit, Nut (24x) | L11: =sumif(D:D,K11,E:E) -> 0 | M11: =sumif(D:D,K11,F:F) -> 0
K12: ='Internal Summary'!B49 -> 5kg Segunfunmi Ofada Rice (12x) | L12: =sumif(D:D,K12,E:E) -> 0 | M12: =sumif(D:D,K12,F:F) -> 0
K13: ='Internal Summary'!B50 | L13: =sumif(D:D,K13,E:E) -> 0 | M13: =sumif(D:D,K13,F:F) -> 0
K14: ='Internal Summary'!B51 | L14: =sumif(D:D,K14,E:E) -> 0 | M14: =sumif(D:D,K14,F:F) -> 0
K15: ='Internal Summary'!B52 | L15: =sumif(D:D,K15,E:E) -> 0 | M15: =sumif(D:D,K15,F:F) -> 0
... K51: ='Internal Summary'!B88 | L51: =sumif(D:D,K51,E:E) -> 0 | M51: =sumif(D:D,K51,F:F) -> 0

Sheet External Delivery Fulfillment
H1: Total Invoices Delivered | I1: =countifs(B:B,"<>",F:F,"<>")-1 -> 0 | K1: Sku Performance | L1: Units | M1: Value
H2: Unique Locations Supplied | I2: {=(COUNTA(UNIQUE(C:C))-1)} -> 0 | K2: ='Internal Summary'!B39 -> 150g Segunfunmi Granola Oat, Fruit, Nut (24x) | L2: =sumif(D:D,K2,E:E) -> 0 | M2: =sumif(D:D,K2,F:F) -> 0
H3: Total Value of orders | I3: =sum(F:F) -> 0 | K3: ='Internal Summary'!B40 -> 150g Segunfunmi Hibiscus Tea pineapple, Cloves, Ginger (24x) | L3: =sumif(D:D,K3,E:E) -> 0 | M3: =sumif(D:D,K3,F:F) -> 0
K4: ='Internal Summary'!B41 -> 1kg Segunfunmi Granola Oat, Fruit, Nut (12x) | L4: =sumif(D:D,K4,E:E) -> 0 | M4: =sumif(D:D,K4,F:F) -> 0
K5: ='Internal Summary'!B42 -> 1kg Segunfunmi Lafun Flour Cassava (12x) | L5: =sumif(D:D,K5,E:E) -> 0 | M5: =sumif(D:D,K5,F:F) -> 0
K6: ='Internal Summary'!B43 -> 1kg Segunfunmi Ofada Rice (24x) | L6: =sumif(D:D,K6,E:E) -> 0 | M6: =sumif(D:D,K6,F:F) -> 0
K7: ='Internal Summary'!B44 -> 1kg Segunfunmi Yam Flour (12x) | L7: =sumif(D:D,K7,E:E) -> 0 | M7: =sumif(D:D,K7,F:F) -> 0
K8: ='Internal Summary'!B45 -> 200g Segunfunmi Chilli Pepper (12x) | L8: =sumif(D:D,K8,E:E) -> 0 | M8: =sumif(D:D,K8,F:F) -> 0
K9: ='Internal Summary'!B46 -> 250g Segunfunmi Granola Oat, Fruit, Nut (24x) | L9: =sumif(D:D,K9,E:E) -> 0 | M9: =sumif(D:D,K9,F:F) -> 0
K10: ='Internal Summary'!B47 -> 2kg Segunfunmi Ofada Rice (12x) | L10: =sumif(D:D,K10,E:E) -> 0 | M10: =sumif(D:D,K10,F:F) -> 0
K11: ='Internal Summary'!B48 -> 500g Segunfunmi Granola Oat, Fruit, Nut (24x) | L11: =sumif(D:D,K11,E:E) -> 0 | M11: =sumif(D:D,K11,F:F) -> 0
K12: ='Internal Summary'!B49 -> 5kg Segunfunmi Ofada Rice (12x) | L12: =sumif(D:D,K12,E:E) -> 0 | M12: =sumif(D:D,K12,F:F) -> 0
K13: ='Internal Summary'!B50 | L13: =sumif(D:D,K13,E:E) -> 0 | M13: =sumif(D:D,K13,F:F) -> 0
K14: ='Internal Summary'!B51 | L14: =sumif(D:D,K14,E:E) -> 0 | M14: =sumif(D:D,K14,F:F) -> 0
K15: ='Internal Summary'!B52 | L15: =sumif(D:D,K15,E:E) -> 0 | M15: =sumif(D:D,K15,F:F) -> 0
... K24: ='Internal Summary'!B61 | L24: =sumif(D:D,K24,E:E) -> 0 | M24: =sumif(D:D,K24,F:F) -> 0

Sheet Forwarding From Client
H1: Total Invoices Delivered | I1: =countifs(B:B,"<>",F:F,"<>")-1 -> 0 | K1: Sku Performance | L1: Units | M1: Value
H2: Unique Locations Supplied | I2: {=(COUNTA(UNIQUE(C:C))-1)} -> 0 | K2: ='Internal Summary'!B39 -> 150g Segunfunmi Granola Oat, Fruit, Nut (24x) | L2: =sumif(D:D,K2,E:E) -> 0
H3: Total Value of orders | I3: =sum(F:F) -> 0 | K3: ='Internal Summary'!B40 -> 150g Segunfunmi Hibiscus Tea pineapple, Cloves, Ginger (24x) | L3: =sumif(D:D,K3,E:E) -> 0
K4: ='Internal Summary'!B41 -> 1kg Segunfunmi Granola Oat, Fruit, Nut (12x) | L4: =sumif(D:D,K4,E:E) -> 0
K5: ='Internal Summary'!B42 -> 1kg Segunfunmi Lafun Flour Cassava (12x) | L5: =sumif(D:D,K5,E:E) -> 0
K6: ='Internal Summary'!B43 -> 1kg Segunfunmi Ofada Rice (24x) | L6: =sumif(D:D,K6,E:E) -> 0
K7: ='Internal Summary'!B44 -> 1kg Segunfunmi Yam Flour (12x) | L7: =sumif(D:D,K7,E:E) -> 0
K8: ='Internal Summary'!B45 -> 200g Segunfunmi Chilli Pepper (12x) | L8: =sumif(D:D,K8,E:E) -> 0
K9: ='Internal Summary'!B46 -> 250g Segunfunmi Granola Oat, Fruit, Nut (24x) | L9: =sumif(D:D,K9,E:E) -> 0
K10: ='Internal Summary'!B47 -> 2kg Segunfunmi Ofada Rice (12x) | L10: =sumif(D:D,K10,E:E) -> 0
K11: ='Internal Summary'!B48 -> 500g Segunfunmi Granola Oat, Fruit, Nut (24x) | L11: =sumif(D:D,K11,E:E) -> 0
K12: ='Internal Summary'!B49 -> 5kg Segunfunmi Ofada Rice (12x) | L12: =sumif(D:D,K12,E:E) -> 0
K13: ='Internal Summary'!B50 | L13: =sumif(D:D,K13,E:E) -> 0
K14: ='Internal Summary'!B51 | L14: =sumif(D:D,K14,E:E) -> 0
K15: ='Internal Summary'!B52 | L15: =sumif(D:D,K15,E:E) -> 0

Sheet Dala Restocking
H1: Total Invoices Delivered | I1: =countifs(B:B,"<>",F:F,"<>")-1 -> 0 | K1: Sku Performance | L1: Units
H2: Unique Locations Supplied | I2: {=(COUNTA(UNIQUE(C:C,,0))-1)} -> 0 | K2: ='Internal Summary'!B39 -> 150g Segunfunmi Granola Oat, Fruit, Nut (24x) | L2: =sumif(D:D,K2,E:E) -> 0
H3: Total Value of orders | I3: =sum(F:F) -> 0 | K3: ='Internal Summary'!B40 -> 150g Segunfunmi Hibiscus Tea pineapple, Cloves, Ginger (24x) | L3: =sumif(D:D,K3,E:E) -> 0
K4: ='Internal Summary'!B41 -> 1kg Segunfunmi Granola Oat, Fruit, Nut (12x) | L4: =sumif(D:D,K4,E:E) -> 0
K5: ='Internal Summary'!B42 -> 1kg Segunfunmi Lafun Flour Cassava (12x) | L5: =sumif(D:D,K5,E:E) -> 0
K6: ='Internal Summary'!B43 -> 1kg Segunfunmi Ofada Rice (24x) | L6: =sumif(D:D,K6,E:E) -> 0
K7: ='Internal Summary'!B44 -> 1kg Segunfunmi Yam Flour (12x) | L7: =sumif(D:D,K7,E:E) -> 0
K8: ='Internal Summary'!B45 -> 200g Segunfunmi Chilli Pepper (12x) | L8: =sumif(D:D,K8,E:E) -> 0
K9: ='Internal Summary'!B46 -> 250g Segunfunmi Granola Oat, Fruit, Nut (24x) | L9: =sumif(D:D,K9,E:E) -> 0
K10: ='Internal Summary'!B47 -> 2kg Segunfunmi Ofada Rice (12x) | L10: =sumif(D:D,K10,E:E) -> 0
K11: ='Internal Summary'!B48 -> 500g Segunfunmi Granola Oat, Fruit, Nut (24x) | L11: =sumif(D:D,K11,E:E) -> 0
K12: ='Internal Summary'!B49 -> 5kg Segunfunmi Ofada Rice (12x) | L12: =sumif(D:D,K12,E:E) -> 0
K13: ='Internal Summary'!B50 | L13: =sumif(D:D,K13,E:E) -> 0
K14: ='Internal Summary'!B51 | L14: =sumif(D:D,K14,E:E) -> 0
K15: ='Internal Summary'!B52 | L15: =sumif(D:D,K15,E:E) -> 0
... K27: ='Internal Summary'!B64 | L27: =sumif(D:D,K27,E:E) -> 0

Sheet Client Restocking
H1: Total Invoices Delivered | I1: =countifs(B:B,"<>",F:F,"<>")-1 -> 0 | K1: Sku Performance | L1: Units
H2: Unique Locations Supplied | I2: {=(COUNTA(UNIQUE(C:C,,0))-1)} -> 0 | K2: ='Internal Summary'!B39 -> 150g Segunfunmi Granola Oat, Fruit, Nut (24x) | L2: =sumif(D:D,K2,E:E) -> 0
H3: Total Value of orders | I3: =sum(F:F) -> 0 | K3: ='Internal Summary'!B40 -> 150g Segunfunmi Hibiscus Tea pineapple, Cloves, Ginger (24x) | L3: =sumif(D:D,K3,E:E) -> 0
K4: ='Internal Summary'!B41 -> 1kg Segunfunmi Granola Oat, Fruit, Nut (12x) | L4: =sumif(D:D,K4,E:E) -> 0
K5: ='Internal Summary'!B42 -> 1kg Segunfunmi Lafun Flour Cassava (12x) | L5: =sumif(D:D,K5,E:E) -> 0
K6: ='Internal Summary'!B43 -> 1kg Segunfunmi Ofada Rice (24x) | L6: =sumif(D:D,K6,E:E) -> 0
K7: ='Internal Summary'!B44 -> 1kg Segunfunmi Yam Flour (12x) | L7: =sumif(D:D,K7,E:E) -> 0
K8: ='Internal Summary'!B45 -> 200g Segunfunmi Chilli Pepper (12x) | L8: =sumif(D:D,K8,E:E) -> 0
K9: ='Internal Summary'!B46 -> 250g Segunfunmi Granola Oat, Fruit, Nut (24x) | L9: =sumif(D:D,K9,E:E) -> 0
K10: ='Internal Summary'!B47 -> 2kg Segunfunmi Ofada Rice (12x) | L10: =sumif(D:D,K10,E:E) -> 0
K11: ='Internal Summary'!B48 -> 500g Segunfunmi Granola Oat, Fruit, Nut (24x) | L11: =sumif(D:D,K11,E:E) -> 0
K12: ='Internal Summary'!B49 -> 5kg Segunfunmi Ofada Rice (12x) | L12: =sumif(D:D,K12,E:E) -> 0
K13: ='Internal Summary'!B50 | L13: =sumif(D:D,K13,E:E) -> 0
K14: ='Internal Summary'!B51 | L14: =sumif(D:D,K14,E:E) -> 0
K15: ='Internal Summary'!B52 | L15: =sumif(D:D,K15,E:E) -> 0

Sheet Internal Summary
B1: Description | C1: Units | D1: measurements | E1: total
A2: SALES | B2: Total Invoices Delivered | E2: ='Dala Sales & Deliveries'!I1+'External Delivery Fulfillment'!I1 -> 6
B3: Unique Locations Delivered To | E3: ='Raw Data'!AX2 -> 4
B4: Value of Dala Deliveries | E4: ='Dala Sales & Deliveries'!I3 -> 232232.15
B5: VAT
B6: Total Value of Deliveries | E6: =sum(E4:E5) -> 232232.15
A7: Remittance & Deductions | B7: Total Remitted to Partner | E7: 0
B8: Collection Fees | C8: 0.15 | E8: =E7*(C8+100%)-E7 -> 0
A9: Invoice Value Due | B9: Outstanding Paymets For Sales | E9: =E6-E7-E8 -> 232232.15
A10: Debts | B10: Unpaid Subscription | C10: 0 | D10: 0 | E10: =C10*D10 -> 0
B11: Collection Fees | E11: =E4*C8 -> 34834.823
B12: Delivery Fees | D12: Table 1 | E12: =C21+C25 -> 0
B13: Reimbursements Due To DALA | E13: 0
B14: Retailer Deductions (EXPIRY) | E14: =C29 -> 0
B15: Total Deductions | E15: =sum(E10:E14) -> 34834.823
A16: Remmittance Due | B16: Total Balance to Remitt | E16: =E9-E15+C35 -> 197397.33
A19: Inventory and Operational Fees
B20: Dala Pickup for Warehouse | C20: =U68 -> 0
B21: Warehouse Delivery Fee | C21: =V68 -> 0
B22: Forwarding to Retail | C22: =S68 -> 0
B23: Forwarding Delivery Fee | C23: =T68 -> 0
B24: Dala Sales | C24: =67 -> 67
B25: Dala Delivery Fees | C25: =P68 -> 0
B26: Exteranl Deliveries | C26: =Q68 -> 0
B27: External Delivery Fees | C27: =R68 -> 0
B28: Product Defects and Expirey Issues | C28: =F68 -> 0
B29: Deductions From Retailer | C29: 0
B30: Samples used | C30: =I68 -> 0
B31: Produce Replacements | C31: 0
B32: Expected Closing Inventory | C32: =L68 -> 0
B33: Physical Stock count | C33: =K68 -> 0
B34: Inventory Shortages | C34: 0
B35: Inventory Shortage Costs | C35: 0
B38: SKUs | C38: Retail Value | D38: Inbound Delivery Fee | E38: Outbound Delivery Fee | F38: Defects/Expirey | G38: Deductions | H38: Opening Inventory | I38: Samples Used | J38: Product Replacements | K38: Physical Closing Stock Count | L38: Expected Closing Inventory | M38: Inventory Shortages | N38: Shortages Costs | O38: Dala Deliveries | P38: Retail Sales Fee | Q38: External Delivery | R38: External Delivery Fee | S38: Forwarding from Client | T38: Forwarding Delivery Fee | U38: Dala Restocking | V38: Dala Restocking Fee | W38: Client Restocking
B39: 150g Segunfunmi Granola Oat, Fruit, Nut (24x) | G39: =F39*C39 -> 0 | M39: =K39-L39 -> 0 | N39: =M39*C39 -> 0 | O39: ='Dala Sales & Deliveries'!L2 -> 0 | P39: =O39*E39 -> 0 | Q39: ='External Delivery Fulfillment'!L2 -> 0 | R39: =Q39*E39 -> 0 | S39: ='Forwarding From Client'!L2 -> 0 | T39: =S39*E39 -> 0 | U39: ='Dala Restocking'!L2 -> 0 | V39: =U39*D39 -> 0 | W39: ='Client Restocking'!L2 -> 0
B40: 150g Segunfunmi Hibiscus Tea pineapple, Cloves, Ginger (24x) | G40: =F40*C40 -> 0 | M40: =K40-L40 -> 0 | N40: =M40*C40 -> 0 | O40: ='Dala Sales & Deliveries'!L3 -> 0 | P40: =O40*E40 -> 0 | Q40: ='External Delivery Fulfillment'!L3 -> 0 | R40: =Q40*E40 -> 0 | S40: ='Forwarding From Client'!L3 -> 0 | T40: =S40*E40 -> 0 | U40: ='Dala Restocking'!L3 -> 0 | V40: =U40*D40 -> 0 | W40: ='Client Restocking'!L3 -> 0
B41: 1kg Segunfunmi Granola Oat, Fruit, Nut (12x) | G41: =F41*C41 -> 0 | M41: =K41-L41 -> 0 | N41: =M41*C41 -> 0 | O41: ='Dala Sales & Deliveries'!L4 -> 0 | P41: =O41*E41 -> 0 | Q41: ='External Delivery Fulfillment'!L4 -> 0 | R41: =Q41*E41 -> 0 | S41: ='Forwarding From Client'!L4 -> 0 | T41: =S41*E41 -> 0 | U41: ='Dala Restocking'!L4 -> 0 | V41: =U41*D41 -> 0 | W41: ='Client Restocking'!L4 -> 0
B42: 1kg Segunfunmi Lafun Flour Cassava (12x) | G42: =F42*C42 -> 0 | M42: =K42-L42 -> 0 | N42: =M42*C42 -> 0 | O42: ='Dala Sales & Deliveries'!L5 -> 0 | P42: =O42*E42 -> 0 | Q42: ='External Delivery Fulfillment'!L5 -> 0 | R42: =Q42*E42 -> 0 | S42: ='Forwarding From Client'!L5 -> 0 | T42: =S42*E42 -> 0 | U42: ='Dala Restocking'!L5 -> 0 | V42: =U42*D42 -> 0 | W42: ='Client Restocking'!L5 -> 0
B43: 1kg Segunfunmi Ofada Rice (24x) | G43: =F43*C43 -> 0 | M43: =K43-L43 -> 0 | N43: =M43*C43 -> 0 | O43: ='Dala Sales & Deliveries'!L6 -> 0 | P43: =O43*E43 -> 0 | Q43: ='External Delivery Fulfillment'!L6 -> 0 | R43: =Q43*E43 -> 0 | S43: ='Forwarding From Client'!L6 -> 0 | T43: =S43*E43 -> 0 | U43: ='Dala Restocking'!L6 -> 0 | V43: =U43*D43 -> 0 | W43: ='Client Restocking'!L6 -> 0
B44: 1kg Segunfunmi Yam Flour (12x) | G44: =F44*C44 -> 0 | M44: =K44-L44 -> 0 | N44: =M44*C44 -> 0 | O44: ='Dala Sales & Deliveries'!L7 -> 0 | P44: =O44*E44 -> 0 | Q44: ='External Delivery Fulfillment'!L7 -> 0 | R44: =Q44*E44 -> 0 | S44: ='Forwarding From Client'!L7 -> 0 | T44: =S44*E44 -> 0 | U44: ='Dala Restocking'!L7 -> 0 | V44: =U44*D44 -> 0 | W44: ='Client Restocking'!L7 -> 0
B45: 200g Segunfunmi Chilli Pepper (12x) | G45: =F45*C45 -> 0 | M45: =K45-L45 -> 0 | N45: =M45*C45 -> 0 | O45: ='Dala Sales & Deliveries'!L8 -> 0 | P45: =O45*E45 -> 0 | Q45: ='External Delivery Fulfillment'!L8 -> 0 | R45: =Q45*E45 -> 0 | S45: ='Forwarding From Client'!L8 -> 0 | T45: =S45*E45 -> 0 | U45: ='Dala Restocking'!L8 -> 0 | V45: =U45*D45 -> 0 | W45: ='Client Restocking'!L8 -> 0
B46: 250g Segunfunmi Granola Oat, Fruit, Nut (24x) | G46: =F46*C46 -> 0 | M46: =K46-L46 -> 0 | N46: =M46*C46 -> 0 | O46: ='Dala Sales & Deliveries'!L9 -> 0 | P46: =O46*E46 -> 0 | Q46: ='External Delivery Fulfillment'!L9 -> 0 | R46: =Q46*E46 -> 0 | S46: ='Forwarding From Client'!L9 -> 0 | T46: =S46*E46 -> 0 | U46: ='Dala Restocking'!L9 -> 0 | V46: =U46*D46 -> 0 | W46: ='Client Restocking'!L9 -> 0
B47: 2kg Segunfunmi Ofada Rice (12x) | G47: =F47*C47 -> 0 | M47: =K47-L47 -> 0 | N47: =M47*C47 -> 0 | O47: ='Dala Sales & Deliveries'!L10 -> 0 | P47: =O47*E47 -> 0 | Q47: ='External Delivery Fulfillment'!L10 -> 0 | R47: =Q47*E47 -> 0 | S47: ='Forwarding From Client'!L10 -> 0 | T47: =S47*E47 -> 0 | U47: ='Dala Restocking'!L10 -> 0 | V47: =U47*D47 -> 0 | W47: ='Client Restocking'!L10 -> 0
B48: 500g Segunfunmi Granola Oat, Fruit, Nut (24x) | G48: =F48*C48 -> 0 | M48: =K48-L48 -> 0 | N48: =M48*C48 -> 0 | O48: ='Dala Sales & Deliveries'!L11 -> 0 | P48: =O48*E48 -> 0 | Q48: ='External Delivery Fulfillment'!L11 -> 0 | R48: =Q48*E48 -> 0 | S48: ='Forwarding From Client'!L11 -> 0 | T48: =S48*E48 -> 0 | U48: ='Dala Restocking'!L11 -> 0 | V48: =U48*D48 -> 0 | W48: ='Client Restocking'!L11 -> 0
B49: 5kg Segunfunmi Ofada Rice (12x) | G49: =F49*C49 -> 0 | M49: =K49-L49 -> 0 | N49: =M49*C49 -> 0 | O49: ='Dala Sales & Deliveries'!L12 -> 0 | P49: =O49*E49 -> 0 | Q49: ='External Delivery Fulfillment'!L12 -> 0 | R49: =Q49*E49 -> 0 | S49: ='Forwarding From Client'!L12 -> 0 | T49: =S49*E49 -> 0 | U49: ='Dala Restocking'!L12 -> 0 | V49: =U49*D49 -> 0 | W49: ='Client Restocking'!L12 -> 0
G50: =F50*C50 -> 0 | L50: =H50+U50+W50-O50-Q50-I50-J50 -> 0 | M50: =K50-L50 -> 0 | N50: =M50*C50 -> 0 | O50: ='Dala Sales & Deliveries'!L13 -> 0 | P50: =O50*E50 -> 0 | Q50: ='External Delivery Fulfillment'!L13 -> 0 | R50: =Q50*E50 -> 0 | S50: ='Forwarding From Client'!L13 -> 0 | T50: =S50*E50 -> 0 | U50: ='Dala Restocking'!L13 -> 0 | V50: =U50*D50 -> 0 | W50: ='Client Restocking'!L13 -> 0
G51: =F51*C51 -> 0 | L51: =H51+U51+W51-O51-Q51-I51-J51 -> 0 | M51: =K51-L51 -> 0 | N51: =M51*C51 -> 0 | O51: ='Dala Sales & Deliveries'!L14 -> 0 | P51: =O51*E51 -> 0 | Q51: ='External Delivery Fulfillment'!L14 -> 0 | R51: =Q51*E51 -> 0 | S51: ='Forwarding From Client'!L14 -> 0 | T51: =S51*E51 -> 0 | U51: ='Dala Restocking'!L14 -> 0 | V51: =U51*D51 -> 0 | W51: ='Client Restocking'!L14 -> 0
G52: =F52*C52 -> 0 | L52: =H52+U52+W52-O52-Q52-I52-J52 -> 0 | M52: =K52-L52 -> 0 | N52: =M52*C52 -> 0 | O52: ='Dala Sales & Deliveries'!L15 -> 0 | P52: =O52*E52 -> 0 | Q52: ='External Delivery Fulfillment'!L15 -> 0 | R52: =Q52*E52 -> 0 | S52: ='Forwarding From Client'!L15 -> 0 | T52: =S52*E52 -> 0 | U52: ='Dala Restocking'!L15 -> 0 | V52: =U52*D52 -> 0 | W52: ='Client Restocking'!L15 -> 0
G53: =F53*C53 -> 0 | L53: =H53+U53+W53-O53-Q53-I53-J53 -> 0 | M53: =K53-L53 -> 0 | N53: =M53*C53 -> 0 | O53: ='Dala Sales & Deliveries'!L16 | P53: =O53*E53 -> 0 | Q53: ='External Delivery Fulfillment'!L16 | R53: =Q53*E53 -> 0 | S53: ='Forwarding From Client'!L16 | T53: =S53*E53 -> 0 | U53: ='Dala Restocking'!L16 | V53: =U53*D53 -> 0 | W53: ='Client Restocking'!L16
G54: =F54*C54 -> 0 | L54: =H54+U54+W54-O54-Q54-I54-J54 -> 0 | M54: =K54-L54 -> 0 | N54: =M54*C54 -> 0 | O54: ='Dala Sales & Deliveries'!L17 | P54: =O54*E54 -> 0 | Q54: ='External Delivery Fulfillment'!L17 | R54: =Q54*E54 -> 0 | S54: ='Forwarding From Client'!L17 | T54: =S54*E54 -> 0 | U54: ='Dala Restocking'!L17 | V54: =U54*D54 -> 0 | W54: ='Client Restocking'!L17
G55: =F55*C55 -> 0 | L55: =H55+U55+W55-O55-Q55-I55-J55 -> 0 | M55: =K55-L55 -> 0 | N55: =M55*C55 -> 0 | O55: ='Dala Sales & Deliveries'!L18 -> 0 | P55: =O55*E55 -> 0 | Q55: ='External Delivery Fulfillment'!L18 -> 0 | R55: =Q55*E55 -> 0 | S55: ='Forwarding From Client'!L18 | T55: =S55*E55 -> 0 | U55: ='Dala Restocking'!L18 -> 0 | V55: =U55*D55 -> 0 | W55: ='Client Restocking'!L18
G56: =F56*C56 -> 0 | L56: =H56+U56+W56-O56-Q56-I56-J56 -> 0 | M56: =K56-L56 -> 0 | N56: =M56*C56 -> 0 | O56: ='Dala Sales & Deliveries'!L19 | P56: =O56*E56 -> 0 | Q56: ='External Delivery Fulfillment'!L19 | R56: =Q56*E56 -> 0 | S56: ='Forwarding From Client'!L19 | T56: =S56*E56 -> 0 | U56: ='Dala Restocking'!L19 | V56: =U56*D56 -> 0 | W56: ='Client Restocking'!L19
G57: =F57*C57 -> 0 | L57: =H57+U57+W57-O57-Q57-I57-J57 -> 0 | M57: =K57-L57 -> 0 | N57: =M57*C57 -> 0 | O57: ='Dala Sales & Deliveries'!L20 | P57: =O57*E57 -> 0 | Q57: ='External Delivery Fulfillment'!L20 | R57: =Q57*E57 -> 0 | S57: ='Forwarding From Client'!L20 | T57: =S57*E57 -> 0 | U57: ='Dala Restocking'!L20 | V57: =U57*D57 -> 0 | W57: ='Client Restocking'!L20
G58: =F58*C58 -> 0 | L58: =H58+U58+W58-O58-Q58-I58-J58 -> 0 | M58: =K58-L58 -> 0 | N58: =M58*C58 -> 0 | O58: ='Dala Sales & Deliveries'!L21 -> 0 | P58: =O58*E58 -> 0 | Q58: ='External Delivery Fulfillment'!L21 -> 0 | R58: =Q58*E58 -> 0 | S58: ='Forwarding From Client'!L21 | T58: =S58*E58 -> 0 | U58: ='Dala Restocking'!L21 -> 0 | V58: =U58*D58 -> 0 | W58: ='Client Restocking'!L21
G59: =F59*C59 -> 0 | L59: =H59+U59+W59-O59-Q59-I59-J59 -> 0 | M59: =K59-L59 -> 0 | N59: =M59*C59 -> 0 | O59: ='Dala Sales & Deliveries'!L22 | P59: =O59*E59 -> 0 | Q59: ='External Delivery Fulfillment'!L22 | R59: =Q59*E59 -> 0 | S59: ='Forwarding From Client'!L22 | T59: =S59*E59 -> 0 | U59: ='Dala Restocking'!L22 | V59: =U59*D59 -> 0 | W59: ='Client Restocking'!L22
G60: =F60*C60 -> 0 | L60: =H60+U60+W60-O60-Q60-I60-J60 -> 0 | M60: =K60-L60 -> 0 | N60: =M60*C60 -> 0 | O60: ='Dala Sales & Deliveries'!L23 | P60: =O60*E60 -> 0 | Q60: ='External Delivery Fulfillment'!L23 | R60: =Q60*E60 -> 0 | S60: ='Forwarding From Client'!L23 | T60: =S60*E60 -> 0 | U60: ='Dala Restocking'!L23 | V60: =U60*D60 -> 0 | W60: ='Client Restocking'!L23
G61: =F61*C61 -> 0 | L61: =H61+U61+W61-O61-Q61-I61-J61 -> 0 | M61: =K61-L61 -> 0 | N61: =M61*C61 -> 0 | O61: ='Dala Sales & Deliveries'!L24 -> 0 | P61: =O61*E61 -> 0 | Q61: ='External Delivery Fulfillment'!L24 -> 0 | R61: =Q61*E61 -> 0 | S61: ='Forwarding From Client'!L24 | T61: =S61*E61 -> 0 | U61: ='Dala Restocking'!L24 -> 0 | V61: =U61*D61 -> 0 | W61: ='Client Restocking'!L24
... G66: =F66*C66 -> 0 | L66: =H66+U66+W66-O66-Q66-I66-J66 -> 0 | M66: =K66-L66 -> 0 | N66: =M66*C66 -> 0 | O66: ='Dala Sales & Deliveries'!L29 | P66: =O66*E66 -> 0 | Q66: ='External Delivery Fulfillment'!L29 | R66: =Q66*E66 -> 0 | S66: ='Forwarding From Client'!L29 | T66: =S66*E66 -> 0 | U66: ='Dala Restocking'!L29 | V66: =U66*D66 -> 0 | W66: ='Client Restocking'!L29
G67: =F67*C67 -> 0 | L67: =H67+U67+W67-O67-Q67-I67-J67 -> 0 | M67: =K67-L67 -> 0 | N67: =M67*C67 -> 0 | P67: =O67*E67 -> 0 | R67: =Q67*E67 -> 0 | S67: ='Forwarding From Client'!L30 | T67: =S67*E67 -> 0 | V67: =U67*D67 -> 0
B68: TOTAL | F68: =sum(F39:F67) -> 0 | G68: =sum(G39:G67) -> 0 | H68: =sum(H39:H67) -> 0 | I68: =sum(I39:I67) -> 0 | J68: =sum(J39:J67) -> 0 | K68: =sum(K39:K67) -> 0 | L68: =sum(L39:L67) -> 0 | M68: =sum(M39:M67) -> 0 | ... W68: =sum(W39:W67) -> 0
C69: x | D69: x | E69: x | F69: x | G69: x | H69: x | I69: x | J69: x | K69: x | L69: x | M69: x | N69: x | O69: x | P69: x | Q69: x | R69: x | S69: x | T69: x | U69: x | V69: x | W69: x
