Workbook

Sheet Raw Data
A1: Exported from Tally | I1: Dala Sales & Deliveries | R1: External Deliveries | Z1: Forwarding From Client | AH1: Client Restock | AP1: Dala Restock | AX1: Unique Locations
A2: item name | B2: Date | C2: Particulars | D2: Vch Type | E2: Vch No. | F2: Quantity | G2: Value | I2: item name | J2: Date | K2: Particulars | L2: Vch Type | M2: Vch No. | N2: Quantity | O2: Value | P2: Total Value | R2: item name | S2: Date | T2: Particulars | U2: Vch Type | V2: Vch No. | W2: Quantity | X2: Value | Z2: item name | AA2: Date | AB2: Particulars | AC2: Vch Type | AD2: Vch No. | AE2: Quantity | AF2: Value | AH2: item name | AI2: Date | AJ2: Particulars | AK2: Vch Type | AL2: Vch No. | AM2: Quantity | AN2: Value | AP2: item name | AQ2: Date | AR2: Particulars | AS2: Vch Type | AT2: Vch No. | AU2: Quantity | AV2: Value | AX2: {=counta(unique(C:C))-3} -> 8
A3: 300ml Fabfresh Probiotic sweetened Yoghurt (12x) | B3: 46059 | C3: Q Mart Supermarket | D3: Sales | E3: DT:000680 | F3: 1 | G3: 13599.96 | I3: =IFERROR(__xludf.DUMMYFUNCTION("IFERROR( FILTER($A$3:$G1844, LEN($A$3:$A1844), LOWER(TRIM($D$3:$D1844))=""sales""), )"),"300ml Fabfresh Probiotic sweetened Yoghurt (12x)") -> 300ml Fabfresh Probiotic sweetened Yoghurt (12x) | J3: =IFERROR(__xludf.DUMMYFUNCTION("""COMPUTED_VALUE"""),46059.0) -> 46059 | K3: =IFERROR(__xludf.DUMMYFUNCTION("""COMPUTED_VALUE"""),"Q Mart Supermarket") -> Q Mart Supermarket | L3: =IFERROR(__xludf.DUMMYFUNCTION("""COMPUTED_VALUE"""),"Sales") -> Sales | M3: =IFERROR(__xludf.DUMMYFUNCTION("""COMPUTED_VALUE"""),"DT:000680") -> DT:000680 | N3: =IFERROR(__xludf.DUMMYFUNCTION("""COMPUTED_VALUE"""),1.0) -> 1 | O3: =IFERROR(__xludf.DUMMYFUNCTION("""COMPUTED_VALUE"""),13599.96) -> 13599.96 | P3: =sumif(M:M,M3,O:O) -> 35599.92 | R3: =IFERROR(__xludf.DUMMYFUNCTION("IFERROR( FILTER($A$3:$G1844, LEN($A$3:$A1844), REGEXMATCH(LOWER(TRIM($D$3:$D1844)), ""\bjournal\b"")), )"),"") | AH3: =IFERROR(__xludf.DUMMYFUNCTION("IFERROR(FILTER($A$3:$G1844, LEN($A$3:$A1844), LOWER(TRIM($D$3:$D1844))=""Inventory Supplied by Brands""),)"),"") | AP3: =IFERROR(__xludf.DUMMYFUNCTION("IFERROR(FILTER($A$3:$G1844, LEN($A$3:$A1844), LOWER(TRIM($D$3:$D1844))=""Inventory Pickup by Dala""),) "),"")
A4: 300ml Fabfresh Probiotic sweetened Yoghurt (12x) | B4: 46059 | C4: Skymart Supermarket, LANGBASA | D4: Sales | E4: DT:000690 | F4: 1 | G4: 13200 | I4: =IFERROR(__xludf.DUMMYFUNCTION("""COMPUTED_VALUE"""),"300ml Fabfresh Probiotic sweetened Yoghurt (12x)") -> 300ml Fabfresh Probiotic sweetened Yoghurt (12x) | J4: =IFERROR(__xludf.DUMMYFUNCTION("""COMPUTED_VALUE"""),46059.0) -> 46059 | K4: =IFERROR(__xludf.DUMMYFUNCTION("""COMPUTED_VALUE"""),"Skymart Supermarket, LANGBASA") -> Skymart Supermarket, LANGBASA | L4: =IFERROR(__xludf.DUMMYFUNCTION("""COMPUTED_VALUE"""),"Sales") -> Sales | M4: =IFERROR(__xludf.DUMMYFUNCTION("""COMPUTED_VALUE"""),"DT:000690") -> DT:000690 | N4: =IFERROR(__xludf.DUMMYFUNCTION("""COMPUTED_VALUE"""),1.0) -> 1 | O4: =IFERROR(__xludf.DUMMYFUNCTION("""COMPUTED_VALUE"""),13200.0) -> 13200 | P4: =sumif(M:M,M4,O:O) -> 35200
A5: 300ml Fabfresh Probiotic sweetened Yoghurt (12x) | B5: 46060 | C5: Eleyor Shopping Mall, ALAGBON OWODE | D5: Sales | E5: DT:000712 | F5: 1 | G5: 13599.96 | I5: =IFERROR(__xludf.DUMMYFUNCTION("""COMPUTED_VALUE"""),"300ml Fabfresh Probiotic sweetened Yoghurt (12x)") -> 300ml Fabfresh Probiotic sweetened Yoghurt (12x) | J5: =IFERROR(__xludf.DUMMYFUNCTION("""COMPUTED_VALUE"""),46060.0) -> 46060 | K5: =IFERROR(__xludf.DUMMYFUNCTION("""COMPUTED_VALUE"""),"Eleyor Shopping Mall, ALAGBON OWODE") -> Eleyor Shopping Mall, ALAGBON OWODE | L5: =IFERROR(__xludf.DUMMYFUNCTION("""COMPUTED_VALUE"""),"Sales") -> Sales | M5: =IFERROR(__xludf.DUMMYFUNCTION("""COMPUTED_VALUE"""),"DT:000712") -> DT:000712 | N5: =IFERROR(__xludf.DUMMYFUNCTION("""COMPUTED_VALUE"""),1.0) -> 1 | O5: =IFERROR(__xludf.DUMMYFUNCTION("""COMPUTED_VALUE"""),13599.96) -> 13599.96 | P5: =sumif(M:M,M5,O:O) -> 35599.92
A6: 300ml Fabfresh Probiotic sweetened Yoghurt (12x) | B6: 46060 | C6: Eleyor Shopping Mall, OWODE | D6: Sales | E6: DT:000713 | F6: 1 | G6: 13200 | I6: =IFERROR(__xludf.DUMMYFUNCTION("""COMPUTED_VALUE"""),"300ml Fabfresh Probiotic sweetened Yoghurt (12x)") -> 300ml Fabfresh Probiotic sweetened Yoghurt (12x) | J6: =IFERROR(__xludf.DUMMYFUNCTION("""COMPUTED_VALUE"""),46060.0) -> 46060 | K6: =IFERROR(__xludf.DUMMYFUNCTION("""COMPUTED_VALUE"""),"Eleyor Shopping Mall, OWODE") -> Eleyor Shopping Mall, OWODE | L6: =IFERROR(__xludf.DUMMYFUNCTION("""COMPUTED_VALUE"""),"Sales") -> Sales | M6: =IFERROR(__xludf.DUMMYFUNCTION("""COMPUTED_VALUE"""),"DT:000713") -> DT:000713 | N6: =IFERROR(__xludf.DUMMYFUNCTION("""COMPUTED_VALUE"""),1.0) -> 1 | O6: =IFERROR(__xludf.DUMMYFUNCTION("""COMPUTED_VALUE"""),13200.0) -> 13200 | P6: =sumif(M:M,M6,O:O) -> 35200
A7: 300ml Fabfresh Probiotic sweetened Yoghurt (12x) | B7: 46060 | C7: Buymore Supermarket, IBAFO | D7: Sales | E7: DT:000733 | F7: 1 | G7: 13599.96 | I7: =IFERROR(__xludf.DUMMYFUNCTION("""COMPUTED_VALUE"""),"300ml Fabfresh Probiotic sweetened Yoghurt (12x)") -> 300ml Fabfresh Probiotic sweetened Yoghurt (12x) | J7: =IFERROR(__xludf.DUMMYFUNCTION("""COMPUTED_VALUE"""),46060.0) -> 46060 | K7: =IFERROR(__xludf.DUMMYFUNCTION("""COMPUTED_VALUE"""),"Buymore Supermarket, IBAFO") -> Buymore Supermarket, IBAFO | L7: =IFERROR(__xludf.DUMMYFUNCTION("""COMPUTED_VALUE"""),"Sales") -> Sales | M7: =IFERROR(__xludf.DUMMYFUNCTION("""COMPUTED_VALUE"""),"DT:000733") -> DT:000733 | N7: =IFERROR(__xludf.DUMMYFUNCTION("""COMPUTED_VALUE"""),1.0) -> 1 | O7: =IFERROR(__xludf.DUMMYFUNCTION("""COMPUTED_VALUE"""),13599.96) -> 13599.96 | P7: =sumif(M:M,M7,O:O) -> 35599.92
A8: 300ml Fabfresh Probiotic sweetened Yoghurt (12x) | B8: 46062 | C8: Life Back Pharmacy & stores | D8: Sales | E8: DT:000759 | F8: 0.5 | G8: 6600 | I8: =IFERROR(__xludf.DUMMYFUNCTION("""COMPUTED_VALUE"""),"300ml Fabfresh Probiotic sweetened Yoghurt (12x)") -> 300ml Fabfresh Probiotic sweetened Yoghurt (12x) | J8: =IFERROR(__xludf.DUMMYFUNCTION("""COMPUTED_VALUE"""),46062.0) -> 46062 | K8: =IFERROR(__xludf.DUMMYFUNCTION("""COMPUTED_VALUE"""),"Life Back Pharmacy & stores") -> Life Back Pharmacy & stores | L8: =IFERROR(__xludf.DUMMYFUNCTION("""COMPUTED_VALUE"""),"Sales") -> Sales | M8: =IFERROR(__xludf.DUMMYFUNCTION("""COMPUTED_VALUE"""),"DT:000759") -> DT:000759 | N8: =IFERROR(__xludf.DUMMYFUNCTION("""COMPUTED_VALUE"""),0.5) -> 0.5 | O8: =IFERROR(__xludf.DUMMYFUNCTION("""COMPUTED_VALUE"""),6600.0) -> 6600 | P8: =sumif(M:M,M8,O:O) -> 28600
A9: 300ml Fabfresh Probiotic sweetened Yoghurt (12x) | B9: 46063 | C9: All in One Pharmacy & Supermarket | D9: Sales | E9: DT:000766 | F9: 0.25 | G9: 3399.99 | I9: =IFERROR(__xludf.DUMMYFUNCTION("""COMPUTED_VALUE"""),"300ml Fabfresh Probiotic sweetened Yoghurt (12x)") -> 300ml Fabfresh Probiotic sweetened Yoghurt (12x) | J9: =IFERROR(__xludf.DUMMYFUNCTION("""COMPUTED_VALUE"""),46063.0) -> 46063 | K9: =IFERROR(__xludf.DUMMYFUNCTION("""COMPUTED_VALUE"""),"All in One Pharmacy & Supermarket") -> All in One Pharmacy & Supermarket | L9: =IFERROR(__xludf.DUMMYFUNCTION("""COMPUTED_VALUE"""),"Sales") -> Sales | M9: =IFERROR(__xludf.DUMMYFUNCTION("""COMPUTED_VALUE"""),"DT:000766") -> DT:000766 | N9: =IFERROR(__xludf.DUMMYFUNCTION("""COMPUTED_VALUE"""),0.25) -> 0.25 | O9: =IFERROR(__xludf.DUMMYFUNCTION("""COMPUTED_VALUE"""),3399.99) -> 3399.99 | P9: =sumif(M:M,M9,O:O) -> 6799.98
A10: 300ml Fabfresh Probiotic sweetened Yoghurt (12x) | B10: 46065 | C10: Mega Mart | D10: Sales | E10: DT:000864 | F10: 1 | G10: 13599.96 | I10: =IFERROR(__xludf.DUMMYFUNCTION("""COMPUTED_VALUE"""),"300ml Fabfresh Probiotic sweetened Yoghurt (12x)") -> 300ml Fabfresh Probiotic sweetened Yoghurt (12x) | J10: =IFERROR(__xludf.DUMMYFUNCTION("""COMPUTED_VALUE"""),46065.0) -> 46065 | K10: =IFERROR(__xludf.DUMMYFUNCTION("""COMPUTED_VALUE"""),"Mega Mart") -> Mega Mart | L10: =IFERROR(__xludf.DUMMYFUNCTION("""COMPUTED_VALUE"""),"Sales") -> Sales | M10: =IFERROR(__xludf.DUMMYFUNCTION("""COMPUTED_VALUE"""),"DT:000864") -> DT:000864 | N10: =IFERROR(__xludf.DUMMYFUNCTION("""COMPUTED_VALUE"""),1.0) -> 1 | O10: =IFERROR(__xludf.DUMMYFUNCTION("""COMPUTED_VALUE"""),13599.96) -> 13599.96 | P10: =sumif(M:M,M10,O:O) -> 13599.96
A11: 300ml Fabfresh Unsweetened Yoghurt (12x) | B11: 46063 | C11: All in One Pharmacy & Supermarket | D11: Sales | E11: DT:000766 | F11: 0.25 | G11: 3399.99 | I11: =IFERROR(__xludf.DUMMYFUNCTION("""COMPUTED_VALUE"""),"300ml Fabfresh Unsweetened Yoghurt (12x)") -> 300ml Fabfresh Unsweetened Yoghurt (12x) | J11: =IFERROR(__xludf.DUMMYFUNCTION("""COMPUTED_VALUE"""),46063.0) -> 46063 | K11: =IFERROR(__xludf.DUMMYFUNCTION("""COMPUTED_VALUE"""),"All in One Pharmacy & Supermarket") -> All in One Pharmacy & Supermarket | L11: =IFERROR(__xludf.DUMMYFUNCTION("""COMPUTED_VALUE"""),"Sales") -> Sales | M11: =IFERROR(__xludf.DUMMYFUNCTION("""COMPUTED_VALUE"""),"DT:000766") -> DT:000766 | N11: =IFERROR(__xludf.DUMMYFUNCTION("""COMPUTED_VALUE"""),0.25) -> 0.25 | O11: =IFERROR(__xludf.DUMMYFUNCTION("""COMPUTED_VALUE"""),3399.99) -> 3399.99 | P11: =sumif(M:M,M11,O:O) -> 6799.98
A12: 500ml Fabfresh sweetened Yoghurt (12x) | B12: 46059 | C12: Q Mart Supermarket | D12: Sales | E12: DT:000680 | F12: 1 | G12: 21999.96 | I12: =IFERROR(__xludf.DUMMYFUNCTION("""COMPUTED_VALUE"""),"500ml Fabfresh sweetened Yoghurt (12x)") -> 500ml Fabfresh sweetened Yoghurt (12x) | J12: =IFERROR(__xludf.DUMMYFUNCTION("""COMPUTED_VALUE"""),46059.0) -> 46059 | K12: =IFERROR(__xludf.DUMMYFUNCTION("""COMPUTED_VALUE"""),"Q Mart Supermarket") -> Q Mart Supermarket | L12: =IFERROR(__xludf.DUMMYFUNCTION("""COMPUTED_VALUE"""),"Sales") -> Sales | M12: =IFERROR(__xludf.DUMMYFUNCTION("""COMPUTED_VALUE"""),"DT:000680") -> DT:000680 | N12: =IFERROR(__xludf.DUMMYFUNCTION("""COMPUTED_VALUE"""),1.0) -> 1 | O12: =IFERROR(__xludf.DUMMYFUNCTION("""COMPUTED_VALUE"""),21999.96) -> 21999.96 | P12: =sumif(M:M,M12,O:O) -> 35599.92
A13: 500ml Fabfresh sweetened Yoghurt (12x) | B13: 46059 | C13: Skymart Supermarket, LANGBASA | D13: Sales | E13: DT:000690 | F13: 1 | G13: 22000 | I13: =IFERROR(__xludf.DUMMYFUNCTION("""COMPUTED_VALUE"""),"500ml Fabfresh sweetened Yoghurt (12x)") -> 500ml Fabfresh sweetened Yoghurt (12x) | J13: =IFERROR(__xludf.DUMMYFUNCTION("""COMPUTED_VALUE"""),46059.0) -> 46059 | K13: =IFERROR(__xludf.DUMMYFUNCTION("""COMPUTED_VALUE"""),"Skymart Supermarket, LANGBASA") -> Skymart Supermarket, LANGBASA | L13: =IFERROR(__xludf.DUMMYFUNCTION("""COMPUTED_VALUE"""),"Sales") -> Sales | M13: =IFERROR(__xludf.DUMMYFUNCTION("""COMPUTED_VALUE"""),"DT:000690") -> DT:000690 | N13: =IFERROR(__xludf.DUMMYFUNCTION("""COMPUTED_VALUE"""),1.0) -> 1 | O13: =IFERROR(__xludf.DUMMYFUNCTION("""COMPUTED_VALUE"""),22000.0) -> 22000 | P13: =sumif(M:M,M13,O:O) -> 35200
A14: 500ml Fabfresh sweetened Yoghurt (12x) | B14: 46060 | C14: Eleyor Shopping Mall, ALAGBON OWODE | D14: Sales | E14: DT:000712 | F14: 1 | G14: 21999.96 | I14: =IFERROR(__xludf.DUMMYFUNCTION("""COMPUTED_VALUE"""),"500ml Fabfresh sweetened Yoghurt (12x)") -> 500ml Fabfresh sweetened Yoghurt (12x) | J14: =IFERROR(__xludf.DUMMYFUNCTION("""COMPUTED_VALUE"""),46060.0) -> 46060 | K14: =IFERROR(__xludf.DUMMYFUNCTION("""COMPUTED_VALUE"""),"Eleyor Shopping Mall, ALAGBON OWODE") -> Eleyor Shopping Mall, ALAGBON OWODE | L14: =IFERROR(__xludf.DUMMYFUNCTION("""COMPUTED_VALUE"""),"Sales") -> Sales | M14: =IFERROR(__xludf.DUMMYFUNCTION("""COMPUTED_VALUE"""),"DT:000712") -> DT:000712 | N14: =IFERROR(__xludf.DUMMYFUNCTION("""COMPUTED_VALUE"""),1.0) -> 1 | O14: =IFERROR(__xludf.DUMMYFUNCTION("""COMPUTED_VALUE"""),21999.96) -> 21999.96 | P14: =sumif(M:M,M14,O:O) -> 35599.92
A15: 500ml Fabfresh sweetened Yoghurt (12x) | B15: 46060 | C15: Eleyor Shopping Mall, OWODE | D15: Sales | E15: DT:000713 | F15: 1 | G15: 22000 | I15: =IFERROR(__xludf.DUMMYFUNCTION("""COMPUTED_VALUE"""),"500ml Fabfresh sweetened Yoghurt (12x)") -> 500ml Fabfresh sweetened Yoghurt (12x) | J15: =IFERROR(__xludf.DUMMYFUNCTION("""COMPUTED_VALUE"""),46060.0) -> 46060 | K15: =IFERROR(__xludf.DUMMYFUNCTION("""COMPUTED_VALUE"""),"Eleyor Shopping Mall, OWODE") -> Eleyor Shopping Mall, OWODE | L15: =IFERROR(__xludf.DUMMYFUNCTION("""COMPUTED_VALUE"""),"Sales") -> Sales | M15: =IFERROR(__xludf.DUMMYFUNCTION("""COMPUTED_VALUE"""),"DT:000713") -> DT:000713 | N15: =IFERROR(__xludf.DUMMYFUNCTION("""COMPUTED_VALUE"""),1.0) -> 1 | O15: =IFERROR(__xludf.DUMMYFUNCTION("""COMPUTED_VALUE"""),22000.0) -> 22000 | P15: =sumif(M:M,M15,O:O) -> 35200
A16: 500ml Fabfresh sweetened Yoghurt (12x) | B16: 46060 | C16: Hunters restaurant, EGBEDA | D16: Sales | E16: DT:000723 | F16: 0.5 | G16: 10999.98 | I16: =IFERROR(__xludf.DUMMYFUNCTION("""COMPUTED_VALUE"""),"500ml Fabfresh sweetened Yoghurt (12x)") -> 500ml Fabfresh sweetened Yoghurt (12x) | J16: =IFERROR(__xludf.DUMMYFUNCTION("""COMPUTED_VALUE"""),46060.0) -> 46060 | K16: =IFERROR(__xludf.DUMMYFUNCTION("""COMPUTED_VALUE"""),"Hunters restaurant, EGBEDA") -> Hunters restaurant, EGBEDA | L16: =IFERROR(__xludf.DUMMYFUNCTION("""COMPUTED_VALUE"""),"Sales") -> Sales | M16: =IFERROR(__xludf.DUMMYFUNCTION("""COMPUTED_VALUE"""),"DT:000723") -> DT:000723 | N16: =IFERROR(__xludf.DUMMYFUNCTION("""COMPUTED_VALUE"""),0.5) -> 0.5 | O16: =IFERROR(__xludf.DUMMYFUNCTION("""COMPUTED_VALUE"""),10999.98) -> 10999.98 | P16: =sumif(M:M,M16,O:O) -> 10999.98
A17: 500ml Fabfresh sweetened Yoghurt (12x) | B17: 46060 | C17: Buymore Supermarket, IBAFO | D17: Sales | E17: DT:000733 | F17: 1 | G17: 21999.96 | I17: =IFERROR(__xludf.DUMMYFUNCTION("""COMPUTED_VALUE"""),"500ml Fabfresh sweetened Yoghurt (12x)") -> 500ml Fabfresh sweetened Yoghurt (12x) | J17: =IFERROR(__xludf.DUMMYFUNCTION("""COMPUTED_VALUE"""),46060.0) -> 46060 | K17: =IFERROR(__xludf.DUMMYFUNCTION("""COMPUTED_VALUE"""),"Buymore Supermarket, IBAFO") -> Buymore Supermarket, IBAFO | L17: =IFERROR(__xludf.DUMMYFUNCTION("""COMPUTED_VALUE"""),"Sales") -> Sales | M17: =IFERROR(__xludf.DUMMYFUNCTION("""COMPUTED_VALUE"""),"DT:000733") -> DT:000733 | N17: =IFERROR(__xludf.DUMMYFUNCTION("""COMPUTED_VALUE"""),1.0) -> 1 | O17: =IFERROR(__xludf.DUMMYFUNCTION("""COMPUTED_VALUE"""),21999.96) -> 21999.96 | P17: =sumif(M:M,M17,O:O) -> 35599.92
A18: 500ml Fabfresh sweetened Yoghurt (12x) | B18: 46062 | C18: Ozzy Supermarket, mobile road | D18: Sales | E18: DT:000743 | F18: 0.5 | G18: 11000 | I18: =IFERROR(__xludf.DUMMYFUNCTION("""COMPUTED_VALUE"""),"500ml Fabfresh sweetened Yoghurt (12x)") -> 500ml Fabfresh sweetened Yoghurt (12x) | J18: =IFERROR(__xludf.DUMMYFUNCTION("""COMPUTED_VALUE"""),46062.0) -> 46062 | K18: =IFERROR(__xludf.DUMMYFUNCTION("""COMPUTED_VALUE"""),"Ozzy Supermarket, mobile road") -> Ozzy Supermarket, mobile road | L18: =IFERROR(__xludf.DUMMYFUNCTION("""COMPUTED_VALUE"""),"Sales") -> Sales | M18: =IFERROR(__xludf.DUMMYFUNCTION("""COMPUTED_VALUE"""),"DT:000743") -> DT:000743 | N18: =IFERROR(__xludf.DUMMYFUNCTION("""COMPUTED_VALUE"""),0.5) -> 0.5 | O18: =IFERROR(__xludf.DUMMYFUNCTION("""COMPUTED_VALUE"""),11000.0) -> 11000 | P18: =sumif(M:M,M18,O:O) -> 11000
A19: 500ml Fabfresh sweetened Yoghurt (12x) | B19: 46062 | C19: Life Back Pharmacy & stores | D19: Sales | E19: DT:000759 | F19: 1 | G19: 22000 | I19: =IFERROR(__xludf.DUMMYFUNCTION("""COMPUTED_VALUE"""),"500ml Fabfresh sweetened Yoghurt (12x)") -> 500ml Fabfresh sweetened Yoghurt (12x) | J19: =IFERROR(__xludf.DUMMYFUNCTION("""COMPUTED_VALUE"""),46062.0) -> 46062 | K19: =IFERROR(__xludf.DUMMYFUNCTION("""COMPUTED_VALUE"""),"Life Back Pharmacy & stores") -> Life Back Pharmacy & stores | L19: =IFERROR(__xludf.DUMMYFUNCTION("""COMPUTED_VALUE"""),"Sales") -> Sales | M19: =IFERROR(__xludf.DUMMYFUNCTION("""COMPUTED_VALUE"""),"DT:000759") -> DT:000759 | N19: =IFERROR(__xludf.DUMMYFUNCTION("""COMPUTED_VALUE"""),1.0) -> 1 | O19: =IFERROR(__xludf.DUMMYFUNCTION("""COMPUTED_VALUE"""),22000.0) -> 22000 | P19: =sumif(M:M,M19,O:O) -> 28600
P20: =sumif(M:M,M20,O:O) -> 0
P21: =sumif(M:M,M21,O:O) -> 0
P22: =sumif(M:M,M22,O:O) -> 0
P23: =sumif(M:M,M23,O:O) -> 0
P24: =sumif(M:M,M24,O:O) -> 0
P25: =sumif(M:M,M25,O:O) -> 0
P26: =sumif(M:M,M26,O:O) -> 0
P27: =sumif(M:M,M27,O:O) -> 0
P28: =sumif(M:M,M28,O:O) -> 0
P29: =sumif(M:M,M29,O:O) -> 0
P30: =sumif(M:M,M30,O:O) -> 0
P31: =sumif(M:M,M31,O:O) -> 0
... P95: =sumif(M:M,M95,O:O) -> 0
P96: =sumif(K:K,K96,O:O) -> 0
P97: =sumif(K:K,K97,O:O) -> 0
P98: =sumif(K:K,K98,O:O) -> 0
P99: =sumif(K:K,K99,O:O) -> 0
P100: =sumif(K:K,K100,O:O) -> 0
P101: =sumif(K:K,K101,O:O) -> 0
P102: =sumif(K:K,K102,O:O) -> 0
P103: =sumif(K:K,K103,O:O) -> 0
P104: =sumif(K:K,K104,O:O) -> 0
P105: =sumif(K:K,K105,O:O) -> 0
P106: =sumif(K:K,K106,O:O) -> 0
P107: =sumif(K:K,K107,O:O) -> 0
... P1844: =sumif(K:K,K1844,O:O) -> 0

Sheet Payment Advice
F3: =sum(D:D) -> 248199.68

Sheet Dala Sales & Deliveries
H1: Total Invoices Delivered | I1: =countifs(B:B,"<>",F:F,"<>")-1 -> 10 | K1: Sku Performance | L1: Units | M1: Value
H2: Unique Locations Supplied | I2: {=(COUNTA(UNIQUE(C:C))-1)} -> 10 | K2: ='Internal Summary'!B40 -> 1 Ltr Fabfresh sweetened Yoghurt (6x) | L2: =sumif(D:D,K2,E:E) -> 0 | M2: =sumif(D:D,K2,F:F) -> 0
H3: Total Value of orders | I3: =sum(F:F) -> 248199.68 | K3: ='Internal Summary'!B41 -> 1 Ltr Fabfresh Unsweetened Yoghurt (6x) | L3: =sumif(D:D,K3,E:E) -> 0 | M3: =sumif(D:D,K3,F:F) -> 0
K4: ='Internal Summary'!B42 -> 300ml Fabfresh Probiotic sweetened Yoghurt (12x) | L4: =sumif(D:D,K4,E:E) -> 6.75 | M4: =sumif(D:D,K4,F:F) -> 90799.83
K5: ='Internal Summary'!B43 -> 300ml Fabfresh Unsweetened Yoghurt (12x) | L5: =sumif(D:D,K5,E:E) -> 0.25 | M5: =sumif(D:D,K5,F:F) -> 3399.99
K6: ='Internal Summary'!B44 -> 500ml Fabfresh sweetened Yoghurt (12x) | L6: =sumif(D:D,K6,E:E) -> 7 | M6: =sumif(D:D,K6,F:F) -> 153999.86
K7: ='Internal Summary'!B45 -> 500ml Fabfresh Unsweetened Yoghurt (12x) | L7: =sumif(D:D,K7,E:E) -> 0 | M7: =sumif(D:D,K7,F:F) -> 0
K8: ='Internal Summary'!B46 -> 900g Fabfresh probiotic Set Greek Yoghurt (6x) | L8: =sumif(D:D,K8,E:E) -> 0 | M8: =sumif(D:D,K8,F:F) -> 0
K9: ='Internal Summary'!B47 -> FF- 900g Fabfresh Unsweetened Set Greek Yoghurt (6x) | L9: =sumif(D:D,K9,E:E) -> 0 | M9: =sumif(D:D,K9,F:F) -> 0
K10: ='Internal Summary'!B48 | L10: =sumif(D:D,K10,E:E) -> 0 | M10: =sumif(D:D,K10,F:F) -> 0
K11: ='Internal Summary'!B49 | L11: =sumif(D:D,K11,E:E) -> 0 | M11: =sumif(D:D,K11,F:F) -> 0
K12: ='Internal Summary'!B50 | L12: =sumif(D:D,K12,E:E) -> 0 | M12: =sumif(D:D,K12,F:F) -> 0
K13: ='Internal Summary'!B51 | L13: =sumif(D:D,K13,E:E) -> 0 | M13: =sumif(D:D,K13,F:F) -> 0
K14: ='Internal Summary'!B52 | L14: =sumif(D:D,K14,E:E) -> 0 | M14: =sumif(D:D,K14,F:F) -> 0
K15: ='Internal Summary'!B53 | L15: =sumif(D:D,K15,E:E) -> 0 | M15: =sumif(D:D,K15,F:F) -> 0

Sheet External Delivery Fulfillment
H1: Total Invoices Delivered | I1: =countifs(B:B,"<>",F:F,"<>")-1 -> 0 | K1: Sku Performance | L1: Units | M1: Value
H2: Unique Locations Supplied | I2: {=(COUNTA(UNIQUE(C:C))-1)} -> 0 | K2: ='Internal Summary'!B40 -> 1 Ltr Fabfresh sweetened Yoghurt (6x) | L2: =sumif(D:D,K2,E:E) -> 0 | M2: =sumif(D:D,K2,F:F) -> 0
H3: Total Value of orders | I3: =sum(F:F) -> 0 | K3: ='Internal Summary'!B41 -> 1 Ltr Fabfresh Unsweetened Yoghurt (6x) | L3: =sumif(D:D,K3,E:E) -> 0 | M3: =sumif(D:D,K3,F:F) -> 0
K4: ='Internal Summary'!B42 -> 300ml Fabfresh Probiotic sweetened Yoghurt (12x) | L4: =sumif(D:D,K4,E:E) -> 0 | M4: =sumif(D:D,K4,F:F) -> 0
K5: ='Internal Summary'!B43 -> 300ml Fabfresh Unsweetened Yoghurt (12x) | L5: =sumif(D:D,K5,E:E) -> 0 | M5: =sumif(D:D,K5,F:F) -> 0
K6: ='Internal Summary'!B44 -> 500ml Fabfresh sweetened Yoghurt (12x) | L6: =sumif(D:D,K6,E:E) -> 0 | M6: =sumif(D:D,K6,F:F) -> 0
K7: ='Internal Summary'!B45 -> 500ml Fabfresh Unsweetened Yoghurt (12x) | L7: =sumif(D:D,K7,E:E) -> 0 | M7: =sumif(D:D,K7,F:F) -> 0
K8: ='Internal Summary'!B46 -> 900g Fabfresh probiotic Set Greek Yoghurt (6x) | L8: =sumif(D:D,K8,E:E) -> 0 | M8: =sumif(D:D,K8,F:F) -> 0
K9: ='Internal Summary'!B47 -> FF- 900g Fabfresh Unsweetened Set Greek Yoghurt (6x) | L9: =sumif(D:D,K9,E:E) -> 0 | M9: =sumif(D:D,K9,F:F) -> 0
K10: ='Internal Summary'!B48 | L10: =sumif(D:D,K10,E:E) -> 0 | M10: =sumif(D:D,K10,F:F) -> 0
K11: ='Internal Summary'!B49 | L11: =sumif(D:D,K11,E:E) -> 0 | M11: =sumif(D:D,K11,F:F) -> 0
K12: ='Internal Summary'!B50 | L12: =sumif(D:D,K12,E:E) -> 0 | M12: =sumif(D:D,K12,F:F) -> 0
K13: ='Internal Summary'!B51 | L13: =sumif(D:D,K13,E:E) -> 0 | M13: =sumif(D:D,K13,F:F) -> 0
K14: ='Internal Summary'!B52 | L14: =sumif(D:D,K14,E:E) -> 0 | M14: =sumif(D:D,K14,F:F) -> 0
K15: ='Internal Summary'!B53 | L15: =sumif(D:D,K15,E:E) -> 0 | M15: =sumif(D:D,K15,F:F) -> 0
... K24: ='Internal Summary'!B62 | L24: =sumif(D:D,K24,E:E) -> 0 | M24: =sumif(D:D,K24,F:F) -> 0

Sheet Forwarding From Client
H1: Total Invoices Delivered | I1: =countifs(B:B,"<>",F:F,"<>")-1 -> 0 | K1: Sku Performance | L1: Units | M1: Value
H2: Unique Locations Supplied | I2: {=(COUNTA(UNIQUE(C:C))-1)} -> 0 | K2: ='Internal Summary'!B40 -> 1 Ltr Fabfresh sweetened Yoghurt (6x) | L2: =sumif(D:D,K2,E:E) -> 0
H3: Total Value of orders | I3: =sum(F:F) -> 0 | K3: ='Internal Summary'!B41 -> 1 Ltr Fabfresh Unsweetened Yoghurt (6x) | L3: =sumif(D:D,K3,E:E) -> 0
K4: ='Internal Summary'!B42 -> 300ml Fabfresh Probiotic sweetened Yoghurt (12x) | L4: =sumif(D:D,K4,E:E) -> 0
K5: ='Internal Summary'!B43 -> 300ml Fabfresh Unsweetened Yoghurt (12x) | L5: =sumif(D:D,K5,E:E) -> 0
K6: ='Internal Summary'!B44 -> 500ml Fabfresh sweetened Yoghurt (12x) | L6: =sumif(D:D,K6,E:E) -> 0
K7: ='Internal Summary'!B45 -> 500ml Fabfresh Unsweetened Yoghurt (12x) | L7: =sumif(D:D,K7,E:E) -> 0
K8: ='Internal Summary'!B46 -> 900g Fabfresh probiotic Set Greek Yoghurt (6x) | L8: =sumif(D:D,K8,E:E) -> 0
K9: ='Internal Summary'!B47 -> FF- 900g Fabfresh Unsweetened Set Greek Yoghurt (6x) | L9: =sumif(D:D,K9,E:E) -> 0
K10: ='Internal Summary'!B48 | L10: =sumif(D:D,K10,E:E) -> 0
K11: ='Internal Summary'!B49 | L11: =sumif(D:D,K11,E:E) -> 0
K12: ='Internal Summary'!B50 | L12: =sumif(D:D,K12,E:E) -> 0
K13: ='Internal Summary'!B51 | L13: =sumif(D:D,K13,E:E) -> 0
K14: ='Internal Summary'!B52 | L14: =sumif(D:D,K14,E:E) -> 0
K15: ='Internal Summary'!B53 | L15: =sumif(D:D,K15,E:E) -> 0

Sheet Dala Restocking
H1: Total Invoices Delivered | I1: =countifs(B:B,"<>",F:F,"<>")-1 -> 0 | K1: Sku Performance | L1: Units
H2: Unique Locations Supplied | I2: {=(COUNTA(UNIQUE(C:C,,0))-1)} -> 0 | K2: ='Internal Summary'!B40 -> 1 Ltr Fabfresh sweetened Yoghurt (6x) | L2: =sumif(D:D,K2,E:E) -> 0
H3: Total Value of orders | I3: =sum(F:F) -> 0 | K3: ='Internal Summary'!B41 -> 1 Ltr Fabfresh Unsweetened Yoghurt (6x) | L3: =sumif(D:D,K3,E:E) -> 0
K4: ='Internal Summary'!B42 -> 300ml Fabfresh Probiotic sweetened Yoghurt (12x) | L4: =sumif(D:D,K4,E:E) -> 0
K5: ='Internal Summary'!B43 -> 300ml Fabfresh Unsweetened Yoghurt (12x) | L5: =sumif(D:D,K5,E:E) -> 0
K6: ='Internal Summary'!B44 -> 500ml Fabfresh sweetened Yoghurt (12x) | L6: =sumif(D:D,K6,E:E) -> 0
K7: ='Internal Summary'!B45 -> 500ml Fabfresh Unsweetened Yoghurt (12x) | L7: =sumif(D:D,K7,E:E) -> 0
K8: ='Internal Summary'!B46 -> 900g Fabfresh probiotic Set Greek Yoghurt (6x) | L8: =sumif(D:D,K8,E:E) -> 0
K9: ='Internal Summary'!B47 -> FF- 900g Fabfresh Unsweetened Set Greek Yoghurt (6x) | L9: =sumif(D:D,K9,E:E) -> 0
K10: ='Internal Summary'!B48 | L10: =sumif(D:D,K10,E:E) -> 0
K11: ='Internal Summary'!B49 | L11: =sumif(D:D,K11,E:E) -> 0
K12: ='Internal Summary'!B50 | L12: =sumif(D:D,K12,E:E) -> 0
K13: ='Internal Summary'!B51 | L13: =sumif(D:D,K13,E:E) -> 0
K14: ='Internal Summary'!B52 | L14: =sumif(D:D,K14,E:E) -> 0
K15: ='Internal Summary'!B53 | L15: =sumif(D:D,K15,E:E) -> 0
... K27: ='Internal Summary'!B65 | L27: =sumif(D:D,K27,E:E) -> 0

Sheet Client Restocking
H1: Total Invoices Delivered | I1: =countifs(B:B,"<>",F:F,"<>")-1 -> 0 | K1: Sku Performance | L1: Units
H2: Unique Locations Supplied | I2: {=(COUNTA(UNIQUE(C:C,,0))-1)} -> 0 | K2: ='Internal Summary'!B40 -> 1 Ltr Fabfresh sweetened Yoghurt (6x) | L2: =sumif(D:D,K2,E:E) -> 0
H3: Total Value of orders | I3: =sum(F:F) -> 0 | K3: ='Internal Summary'!B41 -> 1 Ltr Fabfresh Unsweetened Yoghurt (6x) | L3: =sumif(D:D,K3,E:E) -> 0
K4: ='Internal Summary'!B42 -> 300ml Fabfresh Probiotic sweetened Yoghurt (12x) | L4: =sumif(D:D,K4,E:E) -> 0
K5: ='Internal Summary'!B43 -> 300ml Fabfresh Unsweetened Yoghurt (12x) | L5: =sumif(D:D,K5,E:E) -> 0
K6: ='Internal Summary'!B44 -> 500ml Fabfresh sweetened Yoghurt (12x) | L6: =sumif(D:D,K6,E:E) -> 0
K7: ='Internal Summary'!B45 -> 500ml Fabfresh Unsweetened Yoghurt (12x) | L7: =sumif(D:D,K7,E:E) -> 0
K8: ='Internal Summary'!B46 -> 900g Fabfresh probiotic Set Greek Yoghurt (6x) | L8: =sumif(D:D,K8,E:E) -> 0
K9: ='Internal Summary'!B47 -> FF- 900g Fabfresh Unsweetened Set Greek Yoghurt (6x) | L9: =sumif(D:D,K9,E:E) -> 0
K10: ='Internal Summary'!B48 | L10: =sumif(D:D,K10,E:E) -> 0
K11: ='Internal Summary'!B49 | L11: =sumif(D:D,K11,E:E) -> 0
K12: ='Internal Summary'!B50 | L12: =sumif(D:D,K12,E:E) -> 0
K13: ='Internal Summary'!B51 | L13: =sumif(D:D,K13,E:E) -> 0
K14: ='Internal Summary'!B52 | L14: =sumif(D:D,K14,E:E) -> 0
K15: ='Internal Summary'!B53 | L15: =sumif(D:D,K15,E:E) -> 0

Sheet Internal Summary
B1: Description | C1: Units | D1: measurements | E1: total
A2: SALES | B2: Total Invoices Delivered | E2: ='Dala Sales & Deliveries'!I1+'External Delivery Fulfillment'!I1 -> 10
B3: Unique Locations Delivered To | E3: ='Raw Data'!AX2 -> 8
B4: Value of Dala Deliveries | E4: ='Dala Sales & Deliveries'!I3 -> 248199.68
B5: VAT
B6: Total Value of Deliveries | E6: =sum(E4:E5) -> 248199.68
A7: Remittance & Deductions | B7: Total Remitted to Partner | E7: 0
B8: Collection Fees | C8: 0.17 | E8: =E7*(C8+100%)-E7 -> 0
A9: Invoice Value Due | B9: Outstanding Paymets For Sales | E9: =E6-E7-E8 -> 248199.68
A10: Debts | B10: Unpaid Subscription | C10: 0 | D10: 0 | E10: =C10*D10 -> 0
B11: Collection Fees | E11: =E9*C8 -> 42193.946
B12: Delivery Fees | E12: =C26 -> 12320
B13: Delivery Fees External & Pickup | D13: Table 1 | E13: =C28+C22 -> 0
B14: Reimbursements Due To DALA | E14: 0
B15: Retailer Deductions (EXPIRY) | E15: =C30 -> 0
B16: Total Deductions | E16: =sum(E10:E15) -> 54513.946
A17: Remmittance Due | B17: Total Balance to Remitt | E17: =E9-E16+C36 -> 193685.73
A20: Inventory and Operational Fees
B21: Dala Pickup for Warehouse | C21: =U69 -> 0
B22: Warehouse Delivery Fee | C22: =V69 -> 0
B23: Forwarding to Retail | C23: =S69 -> 0
B24: Forwarding Delivery Fee | C24: =T69 -> 0
B25: Dala Sales | C25: 0
B26: Dala Delivery Fees | C26: =P69 -> 12320
B27: Exteranl Deliveries | C27: =Q69 -> 0
B28: External Delivery Fees | C28: ='External Delivery Fulfillment'!I2*7% -> 0
B29: Product Defects and Expirey Issues | C29: =F69 -> 0
B30: Deductions From Retailer | C30: 0
B31: Samples used | C31: =I69 -> 0
B32: Produce Replacements | C32: 0
B33: Expected Closing Inventory | C33: =L69 -> 26.1
B34: Physical Stock count | C34: =K69 -> 26.1
B35: Inventory Shortages | C35: 0
B36: Inventory Shortage Costs | C36: 0
B39: SKUs | C39: Retail Value | D39: Inbound Delivery Fee | E39: Outbound Delivery Fee | F39: Defects/Expirey | G39: Deductions | H39: Opening Inventory | I39: Samples Used | J39: Product Replacements | K39: Physical Closing Stock Count | L39: Expected Closing Inventory | M39: Inventory Shortages | N39: Shortages Costs | O39: Dala Deliveries | P39: Retail Sales Fee | Q39: External Delivery | R39: External Delivery Fee | S39: Forwarding from Client | T39: Forwarding Delivery Fee | U39: Dala Restocking | V39: Dala Restocking Fee | W39: Client Restocking
B40: 1 Ltr Fabfresh sweetened Yoghurt (6x) | C40: 19500 | D40: 600 | E40: =C40*5% -> 975 | G40: =F40*C40 -> 0 | K40: 0.1 | L40: 0.1 | M40: =K40-L40 -> 0 | N40: =M40*C40 -> 0 | O40: ='Dala Sales & Deliveries'!L2 -> 0 | P40: =O40*E40 -> 0 | Q40: ='External Delivery Fulfillment'!L2 -> 0 | R40: =Q40*E40 -> 0 | S40: ='Forwarding From Client'!L2 -> 0 | T40: =S40*E40 -> 0 | U40: ='Dala Restocking'!L2 -> 0 | V40: =U40*D40 -> 0 | W40: ='Client Restocking'!L2 -> 0
B41: 1 Ltr Fabfresh Unsweetened Yoghurt (6x) | C41: 19500 | D41: 600 | E41: =C41*5% -> 975 | G41: =F41*C41 -> 0 | K41: 2 | L41: 2 | M41: =K41-L41 -> 0 | N41: =M41*C41 -> 0 | O41: ='Dala Sales & Deliveries'!L3 -> 0 | P41: =O41*E41 -> 0 | Q41: ='External Delivery Fulfillment'!L3 -> 0 | R41: =Q41*E41 -> 0 | S41: ='Forwarding From Client'!L3 -> 0 | T41: =S41*E41 -> 0 | U41: ='Dala Restocking'!L3 -> 0 | V41: =U41*D41 -> 0 | W41: ='Client Restocking'!L3 -> 0
B42: 300ml Fabfresh Probiotic sweetened Yoghurt (12x) | C42: 13200 | D42: 400 | E42: =C42*5% -> 660 | G42: =F42*C42 -> 0 | K42: 9 | L42: 9 | M42: =K42-L42 -> 0 | N42: =M42*C42 -> 0 | O42: ='Dala Sales & Deliveries'!L4 -> 6.75 | P42: =O42*E42 -> 4455 | Q42: ='External Delivery Fulfillment'!L4 -> 0 | R42: =Q42*E42 -> 0 | S42: ='Forwarding From Client'!L4 -> 0 | T42: =S42*E42 -> 0 | U42: ='Dala Restocking'!L4 -> 0 | V42: =U42*D42 -> 0 | W42: ='Client Restocking'!L4 -> 0
B43: 300ml Fabfresh Unsweetened Yoghurt (12x) | C43: 13200 | D43: 400 | E43: =C43*5% -> 660 | G43: =F43*C43 -> 0 | K43: 5 | L43: 5 | M43: =K43-L43 -> 0 | N43: =M43*C43 -> 0 | O43: ='Dala Sales & Deliveries'!L5 -> 0.25 | P43: =O43*E43 -> 165 | Q43: ='External Delivery Fulfillment'!L5 -> 0 | R43: =Q43*E43 -> 0 | S43: ='Forwarding From Client'!L5 -> 0 | T43: =S43*E43 -> 0 | U43: ='Dala Restocking'!L5 -> 0 | V43: =U43*D43 -> 0 | W43: ='Client Restocking'!L5 -> 0
B44: 500ml Fabfresh sweetened Yoghurt (12x) | C44: 22000 | D44: 660 | E44: =C44*5% -> 1100 | G44: =F44*C44 -> 0 | K44: 1 | L44: 1 | M44: =K44-L44 -> 0 | N44: =M44*C44 -> 0 | O44: ='Dala Sales & Deliveries'!L6 -> 7 | P44: =O44*E44 -> 7700 | Q44: ='External Delivery Fulfillment'!L6 -> 0 | R44: =Q44*E44 -> 0 | S44: ='Forwarding From Client'!L6 -> 0 | T44: =S44*E44 -> 0 | U44: ='Dala Restocking'!L6 -> 0 | V44: =U44*D44 -> 0 | W44: ='Client Restocking'!L6 -> 0
B45: 500ml Fabfresh Unsweetened Yoghurt (12x) | C45: 22000 | D45: 660 | E45: =C45*5% -> 1100 | G45: =F45*C45 -> 0 | K45: 4 | L45: 4 | M45: =K45-L45 -> 0 | N45: =M45*C45 -> 0 | O45: ='Dala Sales & Deliveries'!L7 -> 0 | P45: =O45*E45 -> 0 | Q45: ='External Delivery Fulfillment'!L7 -> 0 | R45: =Q45*E45 -> 0 | S45: ='Forwarding From Client'!L7 -> 0 | T45: =S45*E45 -> 0 | U45: ='Dala Restocking'!L7 -> 0 | V45: =U45*D45 -> 0 | W45: ='Client Restocking'!L7 -> 0
B46: 900g Fabfresh probiotic Set Greek Yoghurt (6x) | C46: 17100 | D46: 550 | E46: =C46*5% -> 855 | G46: =F46*C46 -> 0 | K46: 1 | L46: 1 | M46: =K46-L46 -> 0 | N46: =M46*C46 -> 0 | O46: ='Dala Sales & Deliveries'!L8 -> 0 | P46: =O46*E46 -> 0 | Q46: ='External Delivery Fulfillment'!L8 -> 0 | R46: =Q46*E46 -> 0 | S46: ='Forwarding From Client'!L8 -> 0 | T46: =S46*E46 -> 0 | U46: ='Dala Restocking'!L8 -> 0 | V46: =U46*D46 -> 0 | W46: ='Client Restocking'!L8 -> 0
B47: FF- 900g Fabfresh Unsweetened Set Greek Yoghurt (6x) | C47: 17100 | D47: 550 | E47: =C47*5% -> 855 | G47: =F47*C47 -> 0 | K47: 4 | L47: 4 | M47: =K47-L47 -> 0 | N47: =M47*C47 -> 0 | O47: ='Dala Sales & Deliveries'!L9 -> 0 | P47: =O47*E47 -> 0 | Q47: ='External Delivery Fulfillment'!L9 -> 0 | R47: =Q47*E47 -> 0 | S47: ='Forwarding From Client'!L9 -> 0 | T47: =S47*E47 -> 0 | U47: ='Dala Restocking'!L9 -> 0 | V47: =U47*D47 -> 0 | W47: ='Client Restocking'!L9 -> 0
G48: =F48*C48 -> 0 | M48: =K48-L48 -> 0 | N48: =M48*C48 -> 0 | O48: ='Dala Sales & Deliveries'!L10 -> 0 | P48: =O48*E48 -> 0 | Q48: ='External Delivery Fulfillment'!L10 -> 0 | R48: =Q48*E48 -> 0 | S48: ='Forwarding From Client'!L10 -> 0 | T48: =S48*E48 -> 0 | U48: ='Dala Restocking'!L10 -> 0 | V48: =U48*D48 -> 0 | W48: ='Client Restocking'!L10 -> 0
G49: =F49*C49 -> 0 | L49: =H49+U49+W49-O49-Q49-I49-J49 -> 0 | M49: =K49-L49 -> 0 | N49: =M49*C49 -> 0 | O49: ='Dala Sales & Deliveries'!L11 -> 0 | P49: =O49*E49 -> 0 | Q49: ='External Delivery Fulfillment'!L11 -> 0 | R49: =Q49*E49 -> 0 | S49: ='Forwarding From Client'!L11 -> 0 | T49: =S49*E49 -> 0 | U49: ='Dala Restocking'!L11 -> 0 | V49: =U49*D49 -> 0 | W49: ='Client Restocking'!L11 -> 0
G50: =F50*C50 -> 0 | L50: =H50+U50+W50-O50-Q50-I50-J50 -> 0 | M50: =K50-L50 -> 0 | N50: =M50*C50 -> 0 | O50: ='Dala Sales & Deliveries'!L12 -> 0 | P50: =O50*E50 -> 0 | Q50: ='External Delivery Fulfillment'!L12 -> 0 | R50: =Q50*E50 -> 0 | S50: ='Forwarding From Client'!L12 -> 0 | T50: =S50*E50 -> 0 | U50: ='Dala Restocking'!L12 -> 0 | V50: =U50*D50 -> 0 | W50: ='Client Restocking'!L12 -> 0
G51: =F51*C51 -> 0 | L51: =H51+U51+W51-O51-Q51-I51-J51 -> 0 | M51: =K51-L51 -> 0 | N51: =M51*C51 -> 0 | O51: ='Dala Sales & Deliveries'!L13 -> 0 | P51: =O51*E51 -> 0 | Q51: ='External Delivery Fulfillment'!L13 -> 0 | R51: =Q51*E51 -> 0 | S51: ='Forwarding From Client'!L13 -> 0 | T51: =S51*E51 -> 0 | U51: ='Dala Restocking'!L13 -> 0 | V51: =U51*D51 -> 0 | W51: ='Client Restocking'!L13 -> 0
G52: =F52*C52 -> 0 | L52: =H52+U52+W52-O52-Q52-I52-J52 -> 0 | M52: =K52-L52 -> 0 | N52: =M52*C52 -> 0 | O52: ='Dala Sales & Deliveries'!L14 -> 0 | P52: =O52*E52 -> 0 | Q52: ='External Delivery Fulfillment'!L14 -> 0 | R52: =Q52*E52 -> 0 | S52: ='Forwarding From Client'!L14 -> 0 | T52: =S52*E52 -> 0 | U52: ='Dala Restocking'!L14 -> 0 | V52: =U52*D52 -> 0 | W52: ='Client Restocking'!L14 -> 0
G53: =F53*C53 -> 0 | L53: =H53+U53+W53-O53-Q53-I53-J53 -> 0 | M53: =K53-L53 -> 0 | N53: =M53*C53 -> 0 | O53: ='Dala Sales & Deliveries'!L15 -> 0 | P53: =O53*E53 -> 0 | Q53: ='External Delivery Fulfillment'!L15 -> 0 | R53: =Q53*E53 -> 0 | S53: ='Forwarding From Client'!L15 -> 0 | T53: =S53*E53 -> 0 | U53: ='Dala Restocking'!L15 -> 0 | V53: =U53*D53 -> 0 | W53: ='Client Restocking'!L15 -> 0
G54: =F54*C54 -> 0 | L54: =H54+U54+W54-O54-Q54-I54-J54 -> 0 | M54: =K54-L54 -> 0 | N54: =M54*C54 -> 0 | O54: ='Dala Sales & Deliveries'!L16 | P54: =O54*E54 -> 0 | Q54: ='External Delivery Fulfillment'!L16 | R54: =Q54*E54 -> 0 | S54: ='Forwarding From Client'!L16 | T54: =S54*E54 -> 0 | U54: ='Dala Restocking'!L16 | V54: =U54*D54 -> 0 | W54: ='Client Restocking'!L16
G55: =F55*C55 -> 0 | L55: =H55+U55+W55-O55-Q55-I55-J55 -> 0 | M55: =K55-L55 -> 0 | N55: =M55*C55 -> 0 | O55: ='Dala Sales & Deliveries'!L17 | P55: =O55*E55 -> 0 | Q55: ='External Delivery Fulfillment'!L17 | R55: =Q55*E55 -> 0 | S55: ='Forwarding From Client'!L17 | T55: =S55*E55 -> 0 | U55: ='Dala Restocking'!L17 | V55: =U55*D55 -> 0 | W55: ='Client Restocking'!L17
G56: =F56*C56 -> 0 | L56: =H56+U56+W56-O56-Q56-I56-J56 -> 0 | M56: =K56-L56 -> 0 | N56: =M56*C56 -> 0 | O56: ='Dala Sales & Deliveries'!L18 | P56: =O56*E56 -> 0 | Q56: ='External Delivery Fulfillment'!L18 -> 0 | R56: =Q56*E56 -> 0 | S56: ='Forwarding From Client'!L18 | T56: =S56*E56 -> 0 | U56: ='Dala Restocking'!L18 -> 0 | V56: =U56*D56 -> 0 | W56: ='Client Restocking'!L18
G57: =F57*C57 -> 0 | L57: =H57+U57+W57-O57-Q57-I57-J57 -> 0 | M57: =K57-L57 -> 0 | N57: =M57*C57 -> 0 | O57: ='Dala Sales & Deliveries'!L19 | P57: =O57*E57 -> 0 | Q57: ='External Delivery Fulfillment'!L19 | R57: =Q57*E57 -> 0 | S57: ='Forwarding From Client'!L19 | T57: =S57*E57 -> 0 | U57: ='Dala Restocking'!L19 | V57: =U57*D57 -> 0 | W57: ='Client Restocking'!L19
G58: =F58*C58 -> 0 | L58: =H58+U58+W58-O58-Q58-I58-J58 -> 0 | M58: =K58-L58 -> 0 | N58: =M58*C58 -> 0 | O58: ='Dala Sales & Deliveries'!L20 | P58: =O58*E58 -> 0 | Q58: ='External Delivery Fulfillment'!L20 | R58: =Q58*E58 -> 0 | S58: ='Forwarding From Client'!L20 | T58: =S58*E58 -> 0 | U58: ='Dala Restocking'!L20 | V58: =U58*D58 -> 0 | W58: ='Client Restocking'!L20
G59: =F59*C59 -> 0 | L59: =H59+U59+W59-O59-Q59-I59-J59 -> 0 | M59: =K59-L59 -> 0 | N59: =M59*C59 -> 0 | O59: ='Dala Sales & Deliveries'!L21 | P59: =O59*E59 -> 0 | Q59: ='External Delivery Fulfillment'!L21 -> 0 | R59: =Q59*E59 -> 0 | S59: ='Forwarding From Client'!L21 | T59: =S59*E59 -> 0 | U59: ='Dala Restocking'!L21 -> 0 | V59: =U59*D59 -> 0 | W59: ='Client Restocking'!L21
G60: =F60*C60 -> 0 | L60: =H60+U60+W60-O60-Q60-I60-J60 -> 0 | M60: =K60-L60 -> 0 | N60: =M60*C60 -> 0 | O60: ='Dala Sales & Deliveries'!L22 | P60: =O60*E60 -> 0 | Q60: ='External Delivery Fulfillment'!L22 | R60: =Q60*E60 -> 0 | S60: ='Forwarding From Client'!L22 | T60: =S60*E60 -> 0 | U60: ='Dala Restocking'!L22 | V60: =U60*D60 -> 0 | W60: ='Client Restocking'!L22
... G67: =F67*C67 -> 0 | L67: =H67+U67+W67-O67-Q67-I67-J67 -> 0 | M67: =K67-L67 -> 0 | N67: =M67*C67 -> 0 | O67: ='Dala Sales & Deliveries'!L29 | P67: =O67*E67 -> 0 | Q67: ='External Delivery Fulfillment'!L29 | R67: =Q67*E67 -> 0 | S67: ='Forwarding From Client'!L29 | T67: =S67*E67 -> 0 | U67: ='Dala Restocking'!L29 | V67: =U67*D67 -> 0 | W67: ='Client Restocking'!L29
G68: =F68*C68 -> 0 | L68: =H68+U68+W68-O68-Q68-I68-J68 -> 0 | M68: =K68-L68 -> 0 | N68: =M68*C68 -> 0 | P68: =O68*E68 -> 0 | R68: =Q68*E68 -> 0 | S68: ='Forwarding From Client'!L30 | T68: =S68*E68 -> 0 | V68: =U68*D68 -> 0
B69: TOTAL | F69: =sum(F40:F68) -> 0 | G69: =sum(G40:G68) -> 0 | H69: =sum(H40:H68) -> 0 | I69: =sum(I40:I68) -> 0 | J69: =sum(J40:J68) -> 0 | K69: =sum(K40:K68) -> 26.1 | L69: =sum(L40:L68) -> 26.1 | M69: =sum(M40:M68) -> 0 | ... W69: =sum(W40:W68) -> 0
C70: x | D70: x | E70: x | F70: x | G70: x | H70: x | I70: x | J70: x | K70: x | L70: x | M70: x | N70: x | O70: x | P70: x | Q70: x | R70: x | S70: x | T70: x | U70: x | V70: x | W70: x
